Workbook

Sheet 通関業者向けレター
I1: 45257
A2: 関係者 ご各位様
I3: 東レインターナショナル㈱ アパレル物流課
A5: 【ご依頼】APIC、BTNB生産の輸入におけるTIVNの業務委託費用の評価加算について
A7: 逆委託加工における手数料の法改正遵守が強化されていく中で、弊方でも、表題を中心に、
A8: あるべき姿を神戸税関や関係者と協議してきました。TIベトナムの100項目に細分化された業務内容を
A9: 1項目ずつ検討した結果、6項目が評価加算を要する課税対象とすべき内容と判断されたたため、
A10: 12月より評価加算を開始いたします。つきましては、下記詳細をご確認、ご対応願います。
A13: （１）評価加算すべき委託業務 6/100 項目 （神戸税関 包括評価申請にて以下項目について了承済み）
A22: （２）評価加算すべき額（2023年度）
A23: APIC： | B23: ='参考_APIC(2023年度) '!AV113*1000 -> 22915.059 | C23: /年 | D23: =B23/500000 -> 0.045830118 | E23: /50万着/年≒$0.05/着★
A24: BTNB： | B24: ='参考_BTNB(2023年度) '!AT114*1000 -> 6243.8232 | C24: /年 | D24: =B24/450000 -> 0.013875163 | E24: /45万着/年≒$0.02/着★
A26: （３）加算エビデンス について
A27: ベトナム側より弊各営業担当に、評価加算用エビデンスがインボイスと一緒に届くこととなります。
A28: 当該書面を各担当から御社にお渡しするように伝えております。
A29: 管理上の都合で、申告額への加算ではなく、評価加算にて対応願います。
A31: （４）開始時期
A32: 2023年度は11月の相当費用を2023年12月の出荷分より評価加算が必要。
A33: 来年5月より2024年度分の新価格にて評価加算をしていくこととなる。
A34: (以前のものに関しては今年の事後調査で修正）
A36: ≪問合せ先：東レインターナショナル㈱ アパレル物流課 田中（TEL:080-1529-8014）≫
I38: 以 上

Sheet 営業部向けレター
I1: 45257
A2: アパレル製品第2部 各位
I3: アパレル物流課
A5: 【ご依頼】APIC、BTNB生産の輸入におけるTIVNの業務委託費用の評価加算について
A7: 税関にて、逆委託加工における手数料の評価加算への考え方が、変わっていく中で、弊方でも、
A8: あるべき姿を神戸税関や関係者と協議してきました。TIVNｂの100項目に細分化された業務内容を
A9: 1項目ずつ検討した結果、6項目が評価加算を要する課税対象とすべき内容と判断されたたため、
A10: 12月より評価加算をお願いいたします。つきましては、詳細を下記いたしますので、ご確認願います。
A12: （１）評価加算すべき委託業務 6/100 項目 （神戸税関 包括評価申請にて以下項目について了承済み）
A21: （２）評価加算すべき額（2023年度）
A22: APIC： | B22: ='参考_APIC(2023年度) '!AV113*1000 -> 22915.059 | C22: /年 | D22: =B22/500000 -> 0.045830118 | E22: /50万着/年≒$0.05/着★
A23: BTNB： | B23: ='参考_BTNB(2023年度) '!AT114*1000 -> 6243.8232 | C23: /年 | D23: =B23/450000 -> 0.013875163 | E23: /45万着/年≒$0.02/着★
A24: ※生産計画から減産したことを考慮し、過少申告とならない様に、按分する着数を低めに設定。
A25: （APIC50万着、BTNB45万着) 更に､第三国向け分は考慮せず、係る全額を日本向けにて評価加算。
A26: ※上記の額が原価や工賃に加算されるわけではなく、あくまでも課税対象の額となります。
A27: 但し、有税の事案については、上記に関税率を乗じた額が原価に加わることとなります。
A28: ※年間の評価すべき額の算定については同Excelファイル内の参考シート参照
A30: （３）評価加算申告方法
A31: インボイスと一緒に評価加算要のエビデンスが皆様に届きますので、乙仲に、インボイスと一緒に
A32: 渡してください。申告額への加算ではなく、評価加算額に計上されるようにお願いいたします。
A33: ※エビデンスはあくまでも通関用の資料ですので、支払わないでください。別途業務委託費用として
A34: 支払われている費用です。
I35: （同内容を入船ダイナミックシッピング、日新運輸、鴻池運輸に弊方より伝達予定。）
A37: （４）開始時期
A38: 2023年度は11月の相当費用を2023年12月の出荷分より評価加算が必要。
A39: 来年5月より2024年度分の新価格にて評価加算をしていくこととなる。
A40: (以前のものに関しては今年の事後調査で修正）
A42: ≪問合せ先：アパレル物流課 田中（TEL:080-1529-8014）≫
I43: 以 上

Sheet 20240130 TIVN議事録
I2: 45321
A4: APIC、BTNB生産の輸入におけるTIVNの業務委託費用 会議
A6: 日にち：1/30（火）10：30～
A7: 参加者：TIVN 井上副部長、Chanh課長、Thong課長
A8: TI アパレル事業企画推進課 長岡町、石坂さん/アパレル物流課 宇都宮課長、荒井課員、田中
A11: （１）評価加算すべき額（2023年度現行）と評価加算額達成の見通し
A12: APIC： | B12: 22915.059 | C12: /年 | D12: 0.045830118 | E12: /50万着/年≒$0.05★
A13: BTNB： | B13: 6243.8232 | C13: /年 | D13: 0.013875163 | E13: /45万着/年≒$0.02★
A14: 12-4月評価加算額 | B14: 12-4月分岐枚数 | C14: 12月 | D14: 1月 | E14: 2月 | F14: 3月 | G14: 4月 | H14: 12月-4月 | I14: 過剰枚数 | J14: 評価額
A15: =B13/12*5 -> 2601.593 | B15: =A15/0.02 -> 130079.65 | C15: 3379 | D15: 130000 | E15: 76000 | F15: 5000 | G15: ？ | H15: =C15+D15+E15+F15 -> 214379 | I15: =H15-B15 -> 84299.35 | J15: =H15/B15 -> 1.6480595
A16: =B12/12*5 -> 9547.9412 | B16: =A16/0.05 -> 190958.82 | C16: 99327 | D16: 105000 | E16: 9300 | F16: 75000 | G16: ？ | H16: =C16+D16+E16+F16 -> 288627 | I16: =H16-B16 -> 97668.175 | J16: =H16/B16 -> 1.511462
A17: ➡上記予定通りに進めば、課税価格に参入すべき評価加算額を達成できる見込み。
A19: （２）評価加算すべき額（2024年5月～2025年4月）
A20: APIC： | B20: 15929.308 | C20: /年 | D20: =B20/600000 -> 0.026548846 | E20: /60万着/年≒$0.03★ | G20: (APIC 0.05➡0.03）
A21: BTNB： | B21: 8549.4182 | C21: /年 | D21: =B21/500000 -> 0.017098836 | E21: /50万着/年≒$0.02★ | G21: (BTNBは変更なし）
A23: （３）BTNB | B23: 35000 | C23: レンタルミシン費用 の評価要否
A24: TIに請求がくる場合：要課税
A25: BTNB負担のまま ：貨物代金に含まれているとして評価加算不要
A26: ➡後者のため、何等かのアクションは不要
A28: （４）QN工場 業務委託費
A29: 日本人3名の役務に係る費用、23年度、24年度ともに発生。
A30: 業務内容のリストアップ資料はなし。今後、考えていかなくてはならない部分。
A31: 加算すべき費用があった場合、2024年10月のAPIC、BTNBにおけるTIVN業務委託費用の
A32: 包括評価申請と合わせて行うか
A34: （５）TIVN業務委託費用のうち加算すべき年間金額の算出方法
A35: Ⅰ.必要書類 a.予算策定資料_年間TIVN業務委託費用-USD表記版
A36: b.APIC・BTNB_TIVNスタッフ業務分析表/2024年度業務委託料配分
A38: Ⅱ.算出工程
A39: 工程１： | B39: 上記Ⅰ.aに記載の数値をbの以下上部にある表に当て込む
J45: 以上
B47: 注：①＝2024年度はTIVN日本人スタッフ$743÷4名＝＄180.75/人を各工場に配分
B48: ②=2024年度はAPIC：295.83÷13名＝$22.76、BTNB：$335.87÷11名＝$30.53
B49: ③＝2024年度はAPIC：＄91.50、BTNB：＄91.50
A50: 工程２： | B50: 工数は当ファイル内2024年度のbの資料より自動で入力される形式にしているが、
B51: 念のため確認する
A52: 工程３： | B52: 小計の自動計算が合っているか確認する
A53: 工程４： | B53: 工程３で算出された総計と業務分析表の総計が一致しているか確認
A54: 工程５： | B54: 業務分析表の右端最下部の課税価格参入金額総計が各工場､1年当りの評価加算額(自動計算)となる｡
A55: 工程６： | B55: 工程５の数値が千USD単位なので、1000を乗じる
A56: 工程７： | B56: 工程6の数値を年間生産枚数で除算（上記（１）、（２）参照）し当該年度の1着当りの加算単価の算出完了。

Sheet 参考b_APIC(2024年度)
M1: 工数 | O1: 金額（千USD）※１ | AW1: 45320
A2: (予算ヒアリング補足資料からの編集版） | O2: 一人当たり | R2: 小計 | V2: 295.83 | Y2: 91.5 | AX2: Toray International Vietnam Co., Ltd
I3: 日本人管理者 | M3: =K12 -> 1 | O3: 180.75 | R3: =M3*O3 -> 180.75 | V3: =V2/13 -> 22.756154
I4: ナショナルスタッフ/管理グループ | M4: 8 | O4: =V3 -> 22.756154 | R4: =M4*O4 -> 182.04923
A5: APIC TIVNスタッフ業務分析表/2024年度業務委託料配分 | I5: ナショナルスタッフ/技術グループ | M5: =AO12 -> 5 | O5: =V3 -> 22.756154 | R5: =M5*O5 -> 113.78077 | U5: ※1：資料「(1)②TIVN業務委託費用配分」より抜粋
I6: TIVN本社ﾏﾈｰｼﾞﾒﾝﾄ※2 | M6: 1 | O6: =R6/M6 -> 91.5 | R6: 91.5 | U6: ※2：出張アテンドや配車手配
I7: 合計 | M7: =SUM(M3:N6) -> 15 | O7: - | R7: =SUM(R3:T6) -> 568.08 | U7: → | V7: =R7/12 -> 47.34 | W7: /月 | X7: ≒ | Y7: =V7*1000*135 -> 6390900 | AA7: /月(\135/USD換算）
AX8: 単位/千USD
G9: 日本人管理者 | M9: 管理グループ | AE9: 技術グループ | AQ9: TIVN本社ﾏﾈｰｼﾞﾒﾝﾄ(出張･配車手配） | AU9: 総計
G10: Inoue | K10: 計 | M10: Chanh | O10: Cuong | Q10: Hien | S10: Huy | U10: Khanh | W10: Luan | Y10: Nhu | AA10: Cau | AC10: 計 | AE10: Vy | AG10: Quyen | AI10: Hong | AK10: Phuong | AM10: Luu | AO10: 計 | AQ10: - | AS10: 計
G11: 工数 | H11: 金額 | I11: 工数 | J11: 金額 | K11: 工数 | L11: 金額 | M11: 工数 | N11: 金額 | O11: 工数 | P11: 金額 | Q11: 工数 | R11: 金額 | S11: 工数 | T11: 金額 | U11: 工数 | V11: 金額 | W11: 工数 | X11: 金額 | Y11: 工数 | Z11: 金額 | AA11: 工数 | AB11: 金額 | AC11: 工数 | AD11: 金額 | AE11: 工数 | AF11: 金額 | AG11: 工数 | AH11: 金額 | AI11: 工数 | AJ11: 金額 | AK11: 工数 | AL11: 金額 | AM11: 工数 | AN11: 金額 | AO11: 工数 | AP11: 金額 | AQ11: 工数 | AR11: 金額 | AS11: 工数 | AT11: 金額 | AU11: 工数 | AV11: 金額 | AW11: 該否 | AX11: 課税価格参入金額
A12: 分類 | B12: 工程 | D12: 作業 | E12: 作業内容 | F12: 発生頻度 | G12: 1 | H12: =O3 -> 180.75 | K12: =G12+I12 -> 1 | L12: =H12+J12 -> 180.75 | M12: 1 | N12: =O4 -> 22.756154 | O12: 1 | P12: =O4 -> 22.756154 | Q12: 1 | R12: =O4 -> 22.756154 | S12: 1 | T12: =O4 -> 22.756154 | U12: 1 | V12: =O4 -> 22.756154 | W12: 1 | X12: =O4 -> 22.756154 | Y12: 1 | Z12: =O4 -> 22.756154 | AA12: 1 | AB12: =O4 -> 22.756154 | AC12: =M4 -> 8 | AD12: =N12+P12+R12+T12+V12+X12+Z12+AB12 -> 182.04923 | AE12: 1 | AF12: =O5 -> 22.756154 | AG12: 1 | AH12: =O5 -> 22.756154 | AI12: 1 | AJ12: =O5 -> 22.756154 | AK12: 1 | AL12: =O5 -> 22.756154 | AM12: 1 | AN12: =O5 -> 22.756154 | AO12: =AE12+AG12+AK12+AM12+AI12 -> 5 | AP12: =AF12+AH12+AL12+AN12+AJ12 -> 113.78077 | AQ12: 1 | AR12: =O6 -> 91.5 | AS12: =AQ12 -> 1 | AT12: =AR12 -> 91.5 | AU12: =K12+AC12+AO12+AS12 -> 15 | AV12: =L12+AD12+AP12+AT12 -> 568.08
A13: 総括 | B13: 契約管理 | C13: 1 | D13: Debit Note | E13: Debit Note確認、実績踏まえ更新交渉 | F13: 月次 | H13: =$H$12/$G$12*G13 -> 0 | K13: =G13+I13 -> 0 | L13: =H13+J13 -> 0 | M13: 0.01 | N13: =N$12/M$12*M13 -> 0.22756154 | P13: =P$12/O$12*O13 -> 0 | R13: =R$12/Q$12*Q13 -> 0 | T13: =T$12/S$12*S13 -> 0 | V13: =V$12/U$12*U13 -> 0 | X13: =X$12/W$12*W13 -> 0 | Y13: 0.01 | Z13: =Z$12/Y$12*Y13 -> 0.22756154 | AB13: =AB$12/AA$12*AA13 -> 0 | AC13: =M13+O13+Q13+S13+U13+W13+Y13+AA13 -> 0.02 | AD13: =N13+P13+R13+T13+V13+X13+Z13+AB13 -> 0.45512308 | AF13: =AF$12/AE$12*AE13 -> 0 | AH13: =AH$12/AG$12*AG13 -> 0 | AJ13: =AJ$12/AI$12*AI13 -> 0 | AL13: =AL$12/AK$12*AK13 -> 0 | AN13: =AN$12/AM$12*AM13 -> 0 | AO13: =AE13+AG13+AK13+AM13+AI13 -> 0 | AP13: =AF13+AH13+AL13+AN13+AJ13 -> 0 | AS13: =AQ13 -> 0 | AT13: =AR13 -> 0 | AU13: =K13+AC13+AO13 -> 0.02 | AV13: =L13+AD13+AP13+AT13 -> 0.45512308 | AW13: - | AX13: =IF(AW13="●",AV13,0) -> 0 | AZ13: ●
B14: 交渉 | C14: 2 | D14: 出勤管理 | E14: 月ごとの出勤状況をまとめる | F14: 月次 | H14: =$H$12/$G$12*G14 -> 0 | K14: =G14+I14 -> 0 | L14: =H14+J14 -> 0 | N14: =N$12/M$12*M14 -> 0 | P14: =P$12/O$12*O14 -> 0 | R14: =R$12/Q$12*Q14 -> 0 | T14: =T$12/S$12*S14 -> 0 | V14: =V$12/U$12*U14 -> 0 | X14: =X$12/W$12*W14 -> 0 | Z14: =Z$12/Y$12*Y14 -> 0 | AB14: =AB$12/AA$12*AA14 -> 0 | AC14: =M14+O14+Q14+S14+U14+W14+Y14+AA14 -> 0 | AD14: =N14+P14+R14+T14+V14+X14+Z14+AB14 -> 0 | AF14: =AF$12/AE$12*AE14 -> 0 | AH14: =AH$12/AG$12*AG14 -> 0 | AJ14: =AJ$12/AI$12*AI14 -> 0 | AL14: =AL$12/AK$12*AK14 -> 0 | AN14: =AN$12/AM$12*AM14 -> 0 | AO14: =AE14+AG14+AK14+AM14+AI14 -> 0 | AP14: =AF14+AH14+AL14+AN14+AJ14 -> 0 | AS14: =AQ14 -> 0 | AT14: =AR14 -> 0 | AU14: =K14+AC14+AO14 -> 0 | AV14: =L14+AD14+AP14+AT14 -> 0 | AW14: - | AX14: =IF(AW14="●",AV14,0) -> 0 | AZ14: -
C15: 3 | D15: 期中変更対応 | E15: 工場からの業務内容変更要請対応 | F15: 不定期（頻度低） | G15: 0.01 | H15: =$H$12/$G$12*G15 -> 1.8075 | K15: =G15+I15 -> 0.01 | L15: =H15+J15 -> 1.8075 | M15: 0.01 | N15: =N$12/M$12*M15 -> 0.22756154 | P15: =P$12/O$12*O15 -> 0 | R15: =R$12/Q$12*Q15 -> 0 | T15: =T$12/S$12*S15 -> 0 | V15: =V$12/U$12*U15 -> 0 | X15: =X$12/W$12*W15 -> 0 | Z15: =Z$12/Y$12*Y15 -> 0 | AB15: =AB$12/AA$12*AA15 -> 0 | AC15: =M15+O15+Q15+S15+U15+W15+Y15+AA15 -> 0.01 | AD15: =N15+P15+R15+T15+V15+X15+Z15+AB15 -> 0.22756154 | AF15: =AF$12/AE$12*AE15 -> 0 | AH15: =AH$12/AG$12*AG15 -> 0 | AJ15: =AJ$12/AI$12*AI15 -> 0 | AL15: =AL$12/AK$12*AK15 -> 0 | AN15: =AN$12/AM$12*AM15 -> 0 | AO15: =AE15+AG15+AK15+AM15+AI15 -> 0 | AP15: =AF15+AH15+AL15+AN15+AJ15 -> 0 | AS15: =AQ15 -> 0 | AT15: =AR15 -> 0 | AU15: =K15+AC15+AO15 -> 0.02 | AV15: =L15+AD15+AP15+AT15 -> 2.0350615 | AW15: - | AX15: =IF(AW15="●",AV15,0) -> 0
C16: 4 | D16: 生産計画調整 | E16: 工場との生産計画調整・決定 | F16: 週次 | G16: 0.08 | H16: =$H$12/$G$12*G16 -> 14.46 | K16: =G16+I16 -> 0.08 | L16: =H16+J16 -> 14.46 | M16: 0.01 | N16: =N$12/M$12*M16 -> 0.22756154 | P16: =P$12/O$12*O16 -> 0 | R16: =R$12/Q$12*Q16 -> 0 | T16: =T$12/S$12*S16 -> 0 | V16: =V$12/U$12*U16 -> 0 | X16: =X$12/W$12*W16 -> 0 | Z16: =Z$12/Y$12*Y16 -> 0 | AB16: =AB$12/AA$12*AA16 -> 0 | AC16: =M16+O16+Q16+S16+U16+W16+Y16+AA16 -> 0.01 | AD16: =N16+P16+R16+T16+V16+X16+Z16+AB16 -> 0.22756154 | AF16: =AF$12/AE$12*AE16 -> 0 | AH16: =AH$12/AG$12*AG16 -> 0 | AJ16: =AJ$12/AI$12*AI16 -> 0 | AL16: =AL$12/AK$12*AK16 -> 0 | AN16: =AN$12/AM$12*AM16 -> 0 | AO16: =AE16+AG16+AK16+AM16+AI16 -> 0 | AP16: =AF16+AH16+AL16+AN16+AJ16 -> 0 | AS16: =AQ16 -> 0 | AT16: =AR16 -> 0 | AU16: =K16+AC16+AO16 -> 0.09 | AV16: =L16+AD16+AP16+AT16 -> 14.687562 | AW16: - | AX16: =IF(AW16="●",AV16,0) -> 0
C17: 5 | D17: 残業要請 | F17: 不定期（頻度低） | G17: 0.01 | H17: =$H$12/$G$12*G17 -> 1.8075 | K17: =G17+I17 -> 0.01 | L17: =H17+J17 -> 1.8075 | M17: 0.01 | N17: =N$12/M$12*M17 -> 0.22756154 | P17: =P$12/O$12*O17 -> 0 | R17: =R$12/Q$12*Q17 -> 0 | T17: =T$12/S$12*S17 -> 0 | V17: =V$12/U$12*U17 -> 0 | X17: =X$12/W$12*W17 -> 0 | Z17: =Z$12/Y$12*Y17 -> 0 | AB17: =AB$12/AA$12*AA17 -> 0 | AC17: =M17+O17+Q17+S17+U17+W17+Y17+AA17 -> 0.01 | AD17: =N17+P17+R17+T17+V17+X17+Z17+AB17 -> 0.22756154 | AF17: =AF$12/AE$12*AE17 -> 0 | AH17: =AH$12/AG$12*AG17 -> 0 | AJ17: =AJ$12/AI$12*AI17 -> 0 | AL17: =AL$12/AK$12*AK17 -> 0 | AN17: =AN$12/AM$12*AM17 -> 0 | AO17: =AE17+AG17+AK17+AM17+AI17 -> 0 | AP17: =AF17+AH17+AL17+AN17+AJ17 -> 0 | AS17: =AQ17 -> 0 | AT17: =AR17 -> 0 | AU17: =K17+AC17+AO17 -> 0.02 | AV17: =L17+AD17+AP17+AT17 -> 2.0350615 | AW17: - | AX17: =IF(AW17="●",AV17,0) -> 0
C18: 6 | D18: Air代負担交渉 | F18: 不定期（頻度低） | G18: 0.01 | H18: =$H$12/$G$12*G18 -> 1.8075 | K18: =G18+I18 -> 0.01 | L18: =H18+J18 -> 1.8075 | M18: 0.01 | N18: =N$12/M$12*M18 -> 0.22756154 | P18: =P$12/O$12*O18 -> 0 | R18: =R$12/Q$12*Q18 -> 0 | T18: =T$12/S$12*S18 -> 0 | V18: =V$12/U$12*U18 -> 0 | X18: =X$12/W$12*W18 -> 0 | Z18: =Z$12/Y$12*Y18 -> 0 | AB18: =AB$12/AA$12*AA18 -> 0 | AC18: =M18+O18+Q18+S18+U18+W18+Y18+AA18 -> 0.01 | AD18: =N18+P18+R18+T18+V18+X18+Z18+AB18 -> 0.22756154 | AF18: =AF$12/AE$12*AE18 -> 0 | AH18: =AH$12/AG$12*AG18 -> 0 | AJ18: =AJ$12/AI$12*AI18 -> 0 | AL18: =AL$12/AK$12*AK18 -> 0 | AN18: =AN$12/AM$12*AM18 -> 0 | AO18: =AE18+AG18+AK18+AM18+AI18 -> 0 | AP18: =AF18+AH18+AL18+AN18+AJ18 -> 0 | AS18: =AQ18 -> 0 | AT18: =AR18 -> 0 | AU18: =K18+AC18+AO18 -> 0.02 | AV18: =L18+AD18+AP18+AT18 -> 2.0350615 | AW18: - | AX18: =IF(AW18="●",AV18,0) -> 0
C19: 7 | D19: 外注工賃交渉 | F19: 不定期（頻度低） | G19: 0.01 | H19: =$H$12/$G$12*G19 -> 1.8075 | K19: =G19+I19 -> 0.01 | L19: =H19+J19 -> 1.8075 | M19: 0.01 | N19: =N$12/M$12*M19 -> 0.22756154 | P19: =P$12/O$12*O19 -> 0 | R19: =R$12/Q$12*Q19 -> 0 | T19: =T$12/S$12*S19 -> 0 | V19: =V$12/U$12*U19 -> 0 | X19: =X$12/W$12*W19 -> 0 | Z19: =Z$12/Y$12*Y19 -> 0 | AB19: =AB$12/AA$12*AA19 -> 0 | AC19: =M19+O19+Q19+S19+U19+W19+Y19+AA19 -> 0.01 | AD19: =N19+P19+R19+T19+V19+X19+Z19+AB19 -> 0.22756154 | AF19: =AF$12/AE$12*AE19 -> 0 | AH19: =AH$12/AG$12*AG19 -> 0 | AJ19: =AJ$12/AI$12*AI19 -> 0 | AL19: =AL$12/AK$12*AK19 -> 0 | AN19: =AN$12/AM$12*AM19 -> 0 | AO19: =AE19+AG19+AK19+AM19+AI19 -> 0 | AP19: =AF19+AH19+AL19+AN19+AJ19 -> 0 | AS19: =AQ19 -> 0 | AT19: =AR19 -> 0 | AU19: =K19+AC19+AO19 -> 0.02 | AV19: =L19+AD19+AP19+AT19 -> 2.0350615 | AW19: - | AX19: =IF(AW19="●",AV19,0) -> 0
B20: AUDIT | C20: 8 | D20: 事前準備 | E20: 提出書類、工場指導 | F20: 不定期（頻度低） | H20: =$H$12/$G$12*G20 -> 0 | K20: =G20+I20 -> 0 | L20: =H20+J20 -> 0 | M20: 0.01 | N20: =N$12/M$12*M20 -> 0.22756154 | P20: =P$12/O$12*O20 -> 0 | R20: =R$12/Q$12*Q20 -> 0 | T20: =T$12/S$12*S20 -> 0 | V20: =V$12/U$12*U20 -> 0 | X20: =X$12/W$12*W20 -> 0 | Y20: 0.01 | Z20: =Z$12/Y$12*Y20 -> 0.22756154 | AB20: =AB$12/AA$12*AA20 -> 0 | AC20: =M20+O20+Q20+S20+U20+W20+Y20+AA20 -> 0.02 | AD20: =N20+P20+R20+T20+V20+X20+Z20+AB20 -> 0.45512308 | AF20: =AF$12/AE$12*AE20 -> 0 | AH20: =AH$12/AG$12*AG20 -> 0 | AJ20: =AJ$12/AI$12*AI20 -> 0 | AL20: =AL$12/AK$12*AK20 -> 0 | AN20: =AN$12/AM$12*AM20 -> 0 | AO20: =AE20+AG20+AK20+AM20+AI20 -> 0 | AP20: =AF20+AH20+AL20+AN20+AJ20 -> 0 | AS20: =AQ20 -> 0 | AT20: =AR20 -> 0 | AU20: =K20+AC20+AO20 -> 0.02 | AV20: =L20+AD20+AP20+AT20 -> 0.45512308 | AW20: - | AX20: =IF(AW20="●",AV20,0) -> 0
B21: ※１ | C21: 9 | D21: 当日対応 | F21: 不定期（頻度低） | G21: 0.01 | H21: =$H$12/$G$12*G21 -> 1.8075 | K21: =G21+I21 -> 0.01 | L21: =H21+J21 -> 1.8075 | M21: 0.01 | N21: =N$12/M$12*M21 -> 0.22756154 | P21: =P$12/O$12*O21 -> 0 | R21: =R$12/Q$12*Q21 -> 0 | T21: =T$12/S$12*S21 -> 0 | V21: =V$12/U$12*U21 -> 0 | X21: =X$12/W$12*W21 -> 0 | Y21: 0.01 | Z21: =Z$12/Y$12*Y21 -> 0.22756154 | AB21: =AB$12/AA$12*AA21 -> 0 | AC21: =M21+O21+Q21+S21+U21+W21+Y21+AA21 -> 0.02 | AD21: =N21+P21+R21+T21+V21+X21+Z21+AB21 -> 0.45512308 | AF21: =AF$12/AE$12*AE21 -> 0 | AH21: =AH$12/AG$12*AG21 -> 0 | AJ21: =AJ$12/AI$12*AI21 -> 0 | AL21: =AL$12/AK$12*AK21 -> 0 | AN21: =AN$12/AM$12*AM21 -> 0 | AO21: =AE21+AG21+AK21+AM21+AI21 -> 0 | AP21: =AF21+AH21+AL21+AN21+AJ21 -> 0 | AS21: =AQ21 -> 0 | AT21: =AR21 -> 0 | AU21: =K21+AC21+AO21 -> 0.03 | AV21: =L21+AD21+AP21+AT21 -> 2.2626231 | AW21: - | AX21: =IF(AW21="●",AV21,0) -> 0
B22: 来客、 | C22: 10 | D22: 移動 | E22: 車、ホテル手配 | F22: 不定期（頻度高） | G22: 0.01 | H22: =$H$12/$G$12*G22 -> 1.8075 | K22: =G22+I22 -> 0.01 | L22: =H22+J22 -> 1.8075 | M22: 0.01 | N22: =N$12/M$12*M22 -> 0.22756154 | P22: =P$12/O$12*O22 -> 0 | R22: =R$12/Q$12*Q22 -> 0 | T22: =T$12/S$12*S22 -> 0 | V22: =V$12/U$12*U22 -> 0 | X22: =X$12/W$12*W22 -> 0 | Z22: =Z$12/Y$12*Y22 -> 0 | AA22: 0.01 | AB22: =AB$12/AA$12*AA22 -> 0.22756154 | AC22: =M22+O22+Q22+S22+U22+W22+Y22+AA22 -> 0.02 | AD22: =N22+P22+R22+T22+V22+X22+Z22+AB22 -> 0.45512308 | AF22: =AF$12/AE$12*AE22 -> 0 | AH22: =AH$12/AG$12*AG22 -> 0 | AJ22: =AJ$12/AI$12*AI22 -> 0 | AL22: =AL$12/AK$12*AK22 -> 0 | AN22: =AN$12/AM$12*AM22 -> 0 | AO22: =AE22+AG22+AK22+AM22+AI22 -> 0 | AP22: =AF22+AH22+AL22+AN22+AJ22 -> 0 | AQ22: 0.5 | AR22: =$AR$12/$AQ$12*AQ22 -> 45.75 | AS22: =AQ22 -> 0.5 | AT22: =AR22 -> 45.75 | AU22: =K22+AC22+AO22 -> 0.03 | AV22: =L22+AD22+AP22+AT22 -> 48.012623 | AW22: - | AX22: =IF(AW22="●",AV22,0) -> 0
B23: 出張対応 | C23: 11 | D23: 工場アテンド | E23: 案内、食事 | F23: 不定期（頻度低） | G23: 0.05 | H23: =$H$12/$G$12*G23 -> 9.0375 | K23: =G23+I23 -> 0.05 | L23: =H23+J23 -> 9.0375 | M23: 0.01 | N23: =N$12/M$12*M23 -> 0.22756154 | P23: =P$12/O$12*O23 -> 0 | R23: =R$12/Q$12*Q23 -> 0 | T23: =T$12/S$12*S23 -> 0 | V23: =V$12/U$12*U23 -> 0 | X23: =X$12/W$12*W23 -> 0 | Z23: =Z$12/Y$12*Y23 -> 0 | AB23: =AB$12/AA$12*AA23 -> 0 | AC23: =M23+O23+Q23+S23+U23+W23+Y23+AA23 -> 0.01 | AD23: =N23+P23+R23+T23+V23+X23+Z23+AB23 -> 0.22756154 | AF23: =AF$12/AE$12*AE23 -> 0 | AG23: 0.05 | AH23: =AH$12/AG$12*AG23 -> 1.1378077 | AI23: 0.02 | AJ23: =AJ$12/AI$12*AI23 -> 0.45512308 | AK23: 0.03 | AL23: =AL$12/AK$12*AK23 -> 0.68268462 | AM23: 0.02 | AN23: =AN$12/AM$12*AM23 -> 0.45512308 | AO23: =AE23+AG23+AK23+AM23+AI23 -> 0.12 | AP23: =AF23+AH23+AL23+AN23+AJ23 -> 2.7307385 | AQ23: 0.5 | AR23: =$AR$12/$AQ$12*AQ23 -> 45.75 | AS23: =AQ23 -> 0.5 | AT23: =AR23 -> 45.75 | AU23: =K23+AC23+AO23 -> 0.18 | AV23: =L23+AD23+AP23+AT23 -> 57.7458 | AW23: - | AX23: =IF(AW23="●",AV23,0) -> 0
C24: 12 | D24: 安全管理 | E24: 行程把握、緊急時対応 | F24: 不定期（頻度高） | G24: 0.05 | H24: =$H$12/$G$12*G24 -> 9.0375 | K24: =G24+I24 -> 0.05 | L24: =H24+J24 -> 9.0375 | M24: 0.01 | N24: =N$12/M$12*M24 -> 0.22756154 | P24: =P$12/O$12*O24 -> 0 | R24: =R$12/Q$12*Q24 -> 0 | T24: =T$12/S$12*S24 -> 0 | V24: =V$12/U$12*U24 -> 0 | X24: =X$12/W$12*W24 -> 0 | Z24: =Z$12/Y$12*Y24 -> 0 | AB24: =AB$12/AA$12*AA24 -> 0 | AC24: =M24+O24+Q24+S24+U24+W24+Y24+AA24 -> 0.01 | AD24: =N24+P24+R24+T24+V24+X24+Z24+AB24 -> 0.22756154 | AF24: =AF$12/AE$12*AE24 -> 0 | AH24: =AH$12/AG$12*AG24 -> 0 | AJ24: =AJ$12/AI$12*AI24 -> 0 | AL24: =AL$12/AK$12*AK24 -> 0 | AN24: =AN$12/AM$12*AM24 -> 0 | AO24: =AE24+AG24+AK24+AM24+AI24 -> 0 | AP24: =AF24+AH24+AL24+AN24+AJ24 -> 0 | AS24: =AQ24 -> 0 | AT24: =AR24 -> 0 | AU24: =K24+AC24+AO24 -> 0.06 | AV24: =L24+AD24+AP24+AT24 -> 9.2650615 | AW24: - | AX24: =IF(AW24="●",AV24,0) -> 0
A25: 企画 | B25: 開発 | C25: 13 | D25: 商品開発 | E25: 新規素材、加工技術調査、サンプル試作 | F25: 不定期（頻度中） | H25: =$H$12/$G$12*G25 -> 0 | K25: =G25+I25 -> 0 | L25: =H25+J25 -> 0 | N25: =N$12/M$12*M25 -> 0 | P25: =P$12/O$12*O25 -> 0 | R25: =R$12/Q$12*Q25 -> 0 | T25: =T$12/S$12*S25 -> 0 | V25: =V$12/U$12*U25 -> 0 | X25: =X$12/W$12*W25 -> 0 | Z25: =Z$12/Y$12*Y25 -> 0 | AA25: 0.02 | AB25: =AB$12/AA$12*AA25 -> 0.45512308 | AC25: =M25+O25+Q25+S25+U25+W25+Y25+AA25 -> 0.02 | AD25: =N25+P25+R25+T25+V25+X25+Z25+AB25 -> 0.45512308 | AF25: =AF$12/AE$12*AE25 -> 0 | AH25: =AH$12/AG$12*AG25 -> 0 | AJ25: =AJ$12/AI$12*AI25 -> 0 | AL25: =AL$12/AK$12*AK25 -> 0 | AN25: =AN$12/AM$12*AM25 -> 0 | AO25: =AE25+AG25+AK25+AM25+AI25 -> 0 | AP25: =AF25+AH25+AL25+AN25+AJ25 -> 0 | AS25: =AQ25 -> 0 | AT25: =AR25 -> 0 | AU25: =K25+AC25+AO25 -> 0.02 | AV25: =L25+AD25+AP25+AT25 -> 0.45512308 | AW25: ● | AX25: =IF(AW25="●",AV25,0) -> 0.45512308
C26: 14 | D26: 加工技術 | E26: 溶着縫製、パターン自動機、ダウン充填機設計 | F26: 不定期（頻度中） | H26: =$H$12/$G$12*G26 -> 0 | K26: =G26+I26 -> 0 | L26: =H26+J26 -> 0 | N26: =N$12/M$12*M26 -> 0 | P26: =P$12/O$12*O26 -> 0 | R26: =R$12/Q$12*Q26 -> 0 | T26: =T$12/S$12*S26 -> 0 | V26: =V$12/U$12*U26 -> 0 | X26: =X$12/W$12*W26 -> 0 | Z26: =Z$12/Y$12*Y26 -> 0 | AA26: 0.01 | AB26: =AB$12/AA$12*AA26 -> 0.22756154 | AC26: =M26+O26+Q26+S26+U26+W26+Y26+AA26 -> 0.01 | AD26: =N26+P26+R26+T26+V26+X26+Z26+AB26 -> 0.22756154 | AF26: =AF$12/AE$12*AE26 -> 0 | AH26: =AH$12/AG$12*AG26 -> 0 | AJ26: =AJ$12/AI$12*AI26 -> 0 | AL26: =AL$12/AK$12*AK26 -> 0 | AN26: =AN$12/AM$12*AM26 -> 0 | AO26: =AE26+AG26+AK26+AM26+AI26 -> 0 | AP26: =AF26+AH26+AL26+AN26+AJ26 -> 0 | AS26: =AQ26 -> 0 | AT26: =AR26 -> 0 | AU26: =K26+AC26+AO26 -> 0.01 | AV26: =L26+AD26+AP26+AT26 -> 0.22756154 | AW26: ● | AX26: =IF(AW26="●",AV26,0) -> 0.22756154
C27: 15 | D27: 生産技術 | E27: IE、ライン設計 | F27: 不定期（頻度低） | H27: =$H$12/$G$12*G27 -> 0 | K27: =G27+I27 -> 0 | L27: =H27+J27 -> 0 | N27: =N$12/M$12*M27 -> 0 | P27: =P$12/O$12*O27 -> 0 | R27: =R$12/Q$12*Q27 -> 0 | T27: =T$12/S$12*S27 -> 0 | V27: =V$12/U$12*U27 -> 0 | X27: =X$12/W$12*W27 -> 0 | Z27: =Z$12/Y$12*Y27 -> 0 | AA27: 0.01 | AB27: =AB$12/AA$12*AA27 -> 0.22756154 | AC27: =M27+O27+Q27+S27+U27+W27+Y27+AA27 -> 0.01 | AD27: =N27+P27+R27+T27+V27+X27+Z27+AB27 -> 0.22756154 | AF27: =AF$12/AE$12*AE27 -> 0 | AH27: =AH$12/AG$12*AG27 -> 0 | AJ27: =AJ$12/AI$12*AI27 -> 0 | AL27: =AL$12/AK$12*AK27 -> 0 | AN27: =AN$12/AM$12*AM27 -> 0 | AO27: =AE27+AG27+AK27+AM27+AI27 -> 0 | AP27: =AF27+AH27+AL27+AN27+AJ27 -> 0 | AS27: =AQ27 -> 0 | AT27: =AR27 -> 0 | AU27: =K27+AC27+AO27 -> 0.01 | AV27: =L27+AD27+AP27+AT27 -> 0.22756154 | AW27: ● | AX27: =IF(AW27="●",AV27,0) -> 0.22756154
C28: 16 | D28: 管理技術 | E28: 工程分析、進捗ばらつき、QC管理手法 | F28: 不定期（頻度中） | H28: =$H$12/$G$12*G28 -> 0 | K28: =G28+I28 -> 0 | L28: =H28+J28 -> 0 | N28: =N$12/M$12*M28 -> 0 | P28: =P$12/O$12*O28 -> 0 | R28: =R$12/Q$12*Q28 -> 0 | T28: =T$12/S$12*S28 -> 0 | V28: =V$12/U$12*U28 -> 0 | X28: =X$12/W$12*W28 -> 0 | Z28: =Z$12/Y$12*Y28 -> 0 | AA28: 0.02 | AB28: =AB$12/AA$12*AA28 -> 0.45512308 | AC28: =M28+O28+Q28+S28+U28+W28+Y28+AA28 -> 0.02 | AD28: =N28+P28+R28+T28+V28+X28+Z28+AB28 -> 0.45512308 | AF28: =AF$12/AE$12*AE28 -> 0 | AH28: =AH$12/AG$12*AG28 -> 0 | AJ28: =AJ$12/AI$12*AI28 -> 0 | AL28: =AL$12/AK$12*AK28 -> 0 | AN28: =AN$12/AM$12*AM28 -> 0 | AO28: =AE28+AG28+AK28+AM28+AI28 -> 0 | AP28: =AF28+AH28+AL28+AN28+AJ28 -> 0 | AS28: =AQ28 -> 0 | AT28: =AR28 -> 0 | AU28: =K28+AC28+AO28 -> 0.02 | AV28: =L28+AD28+AP28+AT28 -> 0.45512308 | AW28: - | AX28: =IF(AW28="●",AV28,0) -> 0
C29: 17 | D29: 評価技術 | E29: 機能性評価、商品評価、物性試験等 | F29: 不定期（頻度中） | H29: =$H$12/$G$12*G29 -> 0 | K29: =G29+I29 -> 0 | L29: =H29+J29 -> 0 | N29: =N$12/M$12*M29 -> 0 | P29: =P$12/O$12*O29 -> 0 | R29: =R$12/Q$12*Q29 -> 0 | T29: =T$12/S$12*S29 -> 0 | V29: =V$12/U$12*U29 -> 0 | X29: =X$12/W$12*W29 -> 0 | Z29: =Z$12/Y$12*Y29 -> 0 | AA29: 0.01 | AB29: =AB$12/AA$12*AA29 -> 0.22756154 | AC29: =M29+O29+Q29+S29+U29+W29+Y29+AA29 -> 0.01 | AD29: =N29+P29+R29+T29+V29+X29+Z29+AB29 -> 0.22756154 | AF29: =AF$12/AE$12*AE29 -> 0 | AH29: =AH$12/AG$12*AG29 -> 0 | AJ29: =AJ$12/AI$12*AI29 -> 0 | AL29: =AL$12/AK$12*AK29 -> 0 | AN29: =AN$12/AM$12*AM29 -> 0 | AO29: =AE29+AG29+AK29+AM29+AI29 -> 0 | AP29: =AF29+AH29+AL29+AN29+AJ29 -> 0 | AS29: =AQ29 -> 0 | AT29: =AR29 -> 0 | AU29: =K29+AC29+AO29 -> 0.01 | AV29: =L29+AD29+AP29+AT29 -> 0.22756154 | AW29: ● | AX29: =IF(AW29="●",AV29,0) -> 0.22756154
A30: 前段取り | B30: 生産計画 | C30: 18 | D30: プランテーブル | E30: 長期生産計画 | F30: 週次 | G30: 0.02 | H30: =$H$12/$G$12*G30 -> 3.615 | K30: =G30+I30 -> 0.02 | L30: =H30+J30 -> 3.615 | M30: 0.05 | N30: =N$12/M$12*M30 -> 1.1378077 | P30: =P$12/O$12*O30 -> 0 | R30: =R$12/Q$12*Q30 -> 0 | T30: =T$12/S$12*S30 -> 0 | V30: =V$12/U$12*U30 -> 0 | X30: =X$12/W$12*W30 -> 0 | Z30: =Z$12/Y$12*Y30 -> 0 | AB30: =AB$12/AA$12*AA30 -> 0 | AC30: =M30+O30+Q30+S30+U30+W30+Y30+AA30 -> 0.05 | AD30: =N30+P30+R30+T30+V30+X30+Z30+AB30 -> 1.1378077 | AF30: =AF$12/AE$12*AE30 -> 0 | AH30: =AH$12/AG$12*AG30 -> 0 | AJ30: =AJ$12/AI$12*AI30 -> 0 | AL30: =AL$12/AK$12*AK30 -> 0 | AN30: =AN$12/AM$12*AM30 -> 0 | AO30: =AE30+AG30+AK30+AM30+AI30 -> 0 | AP30: =AF30+AH30+AL30+AN30+AJ30 -> 0 | AS30: =AQ30 -> 0 | AT30: =AR30 -> 0 | AU30: =K30+AC30+AO30 -> 0.07 | AV30: =L30+AD30+AP30+AT30 -> 4.7528077 | AW30: - | AX30: =IF(AW30="●",AV30,0) -> 0
C31: 19 | D31: 明細連絡 | E31: SKU明細を工場へ連絡する | F31: 日次 | H31: =$H$12/$G$12*G31 -> 0 | K31: =G31+I31 -> 0 | L31: =H31+J31 -> 0 | M31: 0.01 | N31: =N$12/M$12*M31 -> 0.22756154 | O31: 0.01 | P31: =P$12/O$12*O31 -> 0.22756154 | Q31: 0.01 | R31: =R$12/Q$12*Q31 -> 0.22756154 | S31: 0.01 | T31: =T$12/S$12*S31 -> 0.22756154 | U31: 0.01 | V31: =V$12/U$12*U31 -> 0.22756154 | W31: 0.01 | X31: =X$12/W$12*W31 -> 0.22756154 | Y31: 0.01 | Z31: =Z$12/Y$12*Y31 -> 0.22756154 | AB31: =AB$12/AA$12*AA31 -> 0 | AC31: =M31+O31+Q31+S31+U31+W31+Y31+AA31 -> 0.07 | AD31: =N31+P31+R31+T31+V31+X31+Z31+AB31 -> 1.5929308 | AF31: =AF$12/AE$12*AE31 -> 0 | AH31: =AH$12/AG$12*AG31 -> 0 | AJ31: =AJ$12/AI$12*AI31 -> 0 | AL31: =AL$12/AK$12*AK31 -> 0 | AN31: =AN$12/AM$12*AM31 -> 0 | AO31: =AE31+AG31+AK31+AM31+AI31 -> 0 | AP31: =AF31+AH31+AL31+AN31+AJ31 -> 0 | AS31: =AQ31 -> 0 | AT31: =AR31 -> 0 | AU31: =K31+AC31+AO31 -> 0.07 | AV31: =L31+AD31+AP31+AT31 -> 1.5929308 | AW31: - | AX31: =IF(AW31="●",AV31,0) -> 0
C32: 20 | D32: 工場生産計画 | E32: 中期生産計画 | F32: 週次 | G32: 0.02 | H32: =$H$12/$G$12*G32 -> 3.615 | K32: =G32+I32 -> 0.02 | L32: =H32+J32 -> 3.615 | M32: 0.04 | N32: =N$12/M$12*M32 -> 0.91024615 | P32: =P$12/O$12*O32 -> 0 | R32: =R$12/Q$12*Q32 -> 0 | T32: =T$12/S$12*S32 -> 0 | V32: =V$12/U$12*U32 -> 0 | X32: =X$12/W$12*W32 -> 0 | Z32: =Z$12/Y$12*Y32 -> 0 | AB32: =AB$12/AA$12*AA32 -> 0 | AC32: =M32+O32+Q32+S32+U32+W32+Y32+AA32 -> 0.04 | AD32: =N32+P32+R32+T32+V32+X32+Z32+AB32 -> 0.91024615 | AF32: =AF$12/AE$12*AE32 -> 0 | AH32: =AH$12/AG$12*AG32 -> 0 | AJ32: =AJ$12/AI$12*AI32 -> 0 | AL32: =AL$12/AK$12*AK32 -> 0 | AN32: =AN$12/AM$12*AM32 -> 0 | AO32: =AE32+AG32+AK32+AM32+AI32 -> 0 | AP32: =AF32+AH32+AL32+AN32+AJ32 -> 0 | AS32: =AQ32 -> 0 | AT32: =AR32 -> 0 | AU32: =K32+AC32+AO32 -> 0.06 | AV32: =L32+AD32+AP32+AT32 -> 4.5252462 | AW32: - | AX32: =IF(AW32="●",AV32,0) -> 0
C33: 21 | D33: 資材進捗 | E33: 材料の進捗状況を確認し工場へ報告する | F33: 日次 | H33: =$H$12/$G$12*G33 -> 0 | K33: =G33+I33 -> 0 | L33: =H33+J33 -> 0 | M33: 0.05 | N33: =N$12/M$12*M33 -> 1.1378077 | O33: 0.02 | P33: =P$12/O$12*O33 -> 0.45512308 | Q33: 0.02 | R33: =R$12/Q$12*Q33 -> 0.45512308 | S33: 0.02 | T33: =T$12/S$12*S33 -> 0.45512308 | U33: 0.02 | V33: =V$12/U$12*U33 -> 0.45512308 | W33: 0.05 | X33: =X$12/W$12*W33 -> 1.1378077 | Y33: 0.01 | Z33: =Z$12/Y$12*Y33 -> 0.22756154 | AB33: =AB$12/AA$12*AA33 -> 0 | AC33: =M33+O33+Q33+S33+U33+W33+Y33+AA33 -> 0.19 | AD33: =N33+P33+R33+T33+V33+X33+Z33+AB33 -> 4.3236692 | AF33: =AF$12/AE$12*AE33 -> 0 | AH33: =AH$12/AG$12*AG33 -> 0 | AJ33: =AJ$12/AI$12*AI33 -> 0 | AL33: =AL$12/AK$12*AK33 -> 0 | AN33: =AN$12/AM$12*AM33 -> 0 | AO33: =AE33+AG33+AK33+AM33+AI33 -> 0 | AP33: =AF33+AH33+AL33+AN33+AJ33 -> 0 | AS33: =AQ33 -> 0 | AT33: =AR33 -> 0 | AU33: =K33+AC33+AO33 -> 0.19 | AV33: =L33+AD33+AP33+AT33 -> 4.3236692 | AW33: - | AX33: =IF(AW33="●",AV33,0) -> 0
C34: 22 | D34: 注意連絡 | E34: 特別に注視する内容を工場へ連絡 | F34: 週次 | G34: 0.01 | H34: =$H$12/$G$12*G34 -> 1.8075 | K34: =G34+I34 -> 0.01 | L34: =H34+J34 -> 1.8075 | M34: 0.01 | N34: =N$12/M$12*M34 -> 0.22756154 | P34: =P$12/O$12*O34 -> 0 | R34: =R$12/Q$12*Q34 -> 0 | S34: 0.01 | T34: =T$12/S$12*S34 -> 0.22756154 | V34: =V$12/U$12*U34 -> 0 | X34: =X$12/W$12*W34 -> 0 | Z34: =Z$12/Y$12*Y34 -> 0 | AA34: 0.01 | AB34: =AB$12/AA$12*AA34 -> 0.22756154 | AC34: =M34+O34+Q34+S34+U34+W34+Y34+AA34 -> 0.03 | AD34: =N34+P34+R34+T34+V34+X34+Z34+AB34 -> 0.68268462 | AF34: =AF$12/AE$12*AE34 -> 0 | AG34: 0.01 | AH34: =AH$12/AG$12*AG34 -> 0.22756154 | AI34: 0.01 | AJ34: =AJ$12/AI$12*AI34 -> 0.22756154 | AL34: =AL$12/AK$12*AK34 -> 0 | AN34: =AN$12/AM$12*AM34 -> 0 | AO34: =AE34+AG34+AK34+AM34+AI34 -> 0.02 | AP34: =AF34+AH34+AL34+AN34+AJ34 -> 0.45512308 | AS34: =AQ34 -> 0 | AT34: =AR34 -> 0 | AU34: =K34+AC34+AO34 -> 0.06 | AV34: =L34+AD34+AP34+AT34 -> 2.9453077 | AW34: - | AX34: =IF(AW34="●",AV34,0) -> 0
B35: サンプル | C35: 23 | D35: 受注 | E35: 営業オーダー受注。サンプル管理表への記入 | F35: 日次 | H35: =$H$12/$G$12*G35 -> 0 | K35: =G35+I35 -> 0 | L35: =H35+J35 -> 0 | N35: =N$12/M$12*M35 -> 0 | O35: 0.02 | P35: =P$12/O$12*O35 -> 0.45512308 | Q35: 0.02 | R35: =R$12/Q$12*Q35 -> 0.45512308 | S35: 0.02 | T35: =T$12/S$12*S35 -> 0.45512308 | U35: 0.02 | V35: =V$12/U$12*U35 -> 0.45512308 | W35: 0.01 | X35: =X$12/W$12*W35 -> 0.22756154 | Y35: 0.01 | Z35: =Z$12/Y$12*Y35 -> 0.22756154 | AB35: =AB$12/AA$12*AA35 -> 0 | AC35: =M35+O35+Q35+S35+U35+W35+Y35+AA35 -> 0.1 | AD35: =N35+P35+R35+T35+V35+X35+Z35+AB35 -> 2.2756154 | AE35: 0.04 | AF35: =AF$12/AE$12*AE35 -> 0.91024615 | AH35: =AH$12/AG$12*AG35 -> 0 | AJ35: =AJ$12/AI$12*AI35 -> 0 | AL35: =AL$12/AK$12*AK35 -> 0 | AN35: =AN$12/AM$12*AM35 -> 0 | AO35: =AE35+AG35+AK35+AM35+AI35 -> 0.04 | AP35: =AF35+AH35+AL35+AN35+AJ35 -> 0.91024615 | AS35: =AQ35 -> 0 | AT35: =AR35 -> 0 | AU35: =K35+AC35+AO35 -> 0.14 | AV35: =L35+AD35+AP35+AT35 -> 3.1858615 | AW35: - | AX35: =IF(AW35="●",AV35,0) -> 0
C36: 24 | D36: 工場指示 | E36: 日本からのサンプル依頼を工場へ連絡 | F36: 日次 | G36: 0.01 | H36: =$H$12/$G$12*G36 -> 1.8075 | K36: =G36+I36 -> 0.01 | L36: =H36+J36 -> 1.8075 | N36: =N$12/M$12*M36 -> 0 | O36: 0.01 | P36: =P$12/O$12*O36 -> 0.22756154 | Q36: 0.01 | R36: =R$12/Q$12*Q36 -> 0.22756154 | S36: 0.01 | T36: =T$12/S$12*S36 -> 0.22756154 | U36: 0.01 | V36: =V$12/U$12*U36 -> 0.22756154 | W36: 0.01 | X36: =X$12/W$12*W36 -> 0.22756154 | Y36: 0.01 | Z36: =Z$12/Y$12*Y36 -> 0.22756154 | AB36: =AB$12/AA$12*AA36 -> 0 | AC36: =M36+O36+Q36+S36+U36+W36+Y36+AA36 -> 0.06 | AD36: =N36+P36+R36+T36+V36+X36+Z36+AB36 -> 1.3653692 | AF36: =AF$12/AE$12*AE36 -> 0 | AH36: =AH$12/AG$12*AG36 -> 0 | AJ36: =AJ$12/AI$12*AI36 -> 0 | AL36: =AL$12/AK$12*AK36 -> 0 | AN36: =AN$12/AM$12*AM36 -> 0 | AO36: =AE36+AG36+AK36+AM36+AI36 -> 0 | AP36: =AF36+AH36+AL36+AN36+AJ36 -> 0 | AS36: =AQ36 -> 0 | AT36: =AR36 -> 0 | AU36: =K36+AC36+AO36 -> 0.07 | AV36: =L36+AD36+AP36+AT36 -> 3.1728692 | AW36: - | AX36: =IF(AW36="●",AV36,0) -> 0
C37: 25 | D37: 納期回答 | E37: 工場スケジューリング、納期回答 | F37: 日次 | G37: 0.01 | H37: =$H$12/$G$12*G37 -> 1.8075 | K37: =G37+I37 -> 0.01 | L37: =H37+J37 -> 1.8075 | N37: =N$12/M$12*M37 -> 0 | O37: 0.01 | P37: =P$12/O$12*O37 -> 0.22756154 | Q37: 0.01 | R37: =R$12/Q$12*Q37 -> 0.22756154 | S37: 0.01 | T37: =T$12/S$12*S37 -> 0.22756154 | U37: 0.01 | V37: =V$12/U$12*U37 -> 0.22756154 | W37: 0.01 | X37: =X$12/W$12*W37 -> 0.22756154 | Y37: 0.01 | Z37: =Z$12/Y$12*Y37 -> 0.22756154 | AB37: =AB$12/AA$12*AA37 -> 0 | AC37: =M37+O37+Q37+S37+U37+W37+Y37+AA37 -> 0.06 | AD37: =N37+P37+R37+T37+V37+X37+Z37+AB37 -> 1.3653692 | AE37: 0.04 | AF37: =AF$12/AE$12*AE37 -> 0.91024615 | AH37: =AH$12/AG$12*AG37 -> 0 | AJ37: =AJ$12/AI$12*AI37 -> 0 | AL37: =AL$12/AK$12*AK37 -> 0 | AN37: =AN$12/AM$12*AM37 -> 0 | AO37: =AE37+AG37+AK37+AM37+AI37 -> 0.04 | AP37: =AF37+AH37+AL37+AN37+AJ37 -> 0.91024615 | AS37: =AQ37 -> 0 | AT37: =AR37 -> 0 | AU37: =K37+AC37+AO37 -> 0.11 | AV37: =L37+AD37+AP37+AT37 -> 4.0831154 | AW37: - | AX37: =IF(AW37="●",AV37,0) -> 0
C38: 26 | D38: 仕様 | E38: 仕様書の受領、翻訳 | F38: 日次 | H38: =$H$12/$G$12*G38 -> 0 | K38: =G38+I38 -> 0 | L38: =H38+J38 -> 0 | N38: =N$12/M$12*M38 -> 0 | O38: 0.14 | P38: =P$12/O$12*O38 -> 3.1858615 | Q38: 0.14 | R38: =R$12/Q$12*Q38 -> 3.1858615 | S38: 0.14 | T38: =T$12/S$12*S38 -> 3.1858615 | U38: 0.14 | V38: =V$12/U$12*U38 -> 3.1858615 | W38: 0.15 | X38: =X$12/W$12*W38 -> 3.4134231 | Y38: 0.05 | Z38: =Z$12/Y$12*Y38 -> 1.1378077 | AB38: =AB$12/AA$12*AA38 -> 0 | AC38: =M38+O38+Q38+S38+U38+W38+Y38+AA38 -> 0.76 | AD38: =N38+P38+R38+T38+V38+X38+Z38+AB38 -> 17.294677 | AF38: =AF$12/AE$12*AE38 -> 0 | AH38: =AH$12/AG$12*AG38 -> 0 | AJ38: =AJ$12/AI$12*AI38 -> 0 | AL38: =AL$12/AK$12*AK38 -> 0 | AN38: =AN$12/AM$12*AM38 -> 0 | AO38: =AE38+AG38+AK38+AM38+AI38 -> 0 | AP38: =AF38+AH38+AL38+AN38+AJ38 -> 0 | AS38: =AQ38 -> 0 | AT38: =AR38 -> 0 | AU38: =K38+AC38+AO38 -> 0.76 | AV38: =L38+AD38+AP38+AT38 -> 17.294677 | AW38: - | AX38: =IF(AW38="●",AV38,0) -> 0
C39: 27 | D39: パターンチェック | E39: パターンの受領、寸法チェック | F39: 日次 | H39: =$H$12/$G$12*G39 -> 0 | K39: =G39+I39 -> 0 | L39: =H39+J39 -> 0 | N39: =N$12/M$12*M39 -> 0 | O39: 0.01 | P39: =P$12/O$12*O39 -> 0.22756154 | Q39: 0.01 | R39: =R$12/Q$12*Q39 -> 0.22756154 | S39: 0.01 | T39: =T$12/S$12*S39 -> 0.22756154 | U39: 0.01 | V39: =V$12/U$12*U39 -> 0.22756154 | W39: 0.01 | X39: =X$12/W$12*W39 -> 0.22756154 | Y39: 0.01 | Z39: =Z$12/Y$12*Y39 -> 0.22756154 | AB39: =AB$12/AA$12*AA39 -> 0 | AC39: =M39+O39+Q39+S39+U39+W39+Y39+AA39 -> 0.06 | AD39: =N39+P39+R39+T39+V39+X39+Z39+AB39 -> 1.3653692 | AE39: 0.1 | AF39: =AF$12/AE$12*AE39 -> 2.2756154 | AH39: =AH$12/AG$12*AG39 -> 0 | AJ39: =AJ$12/AI$12*AI39 -> 0 | AL39: =AL$12/AK$12*AK39 -> 0 | AN39: =AN$12/AM$12*AM39 -> 0 | AO39: =AE39+AG39+AK39+AM39+AI39 -> 0.1 | AP39: =AF39+AH39+AL39+AN39+AJ39 -> 2.2756154 | AS39: =AQ39 -> 0 | AT39: =AR39 -> 0 | AU39: =K39+AC39+AO39 -> 0.16 | AV39: =L39+AD39+AP39+AT39 -> 3.6409846 | AW39: - | AX39: =IF(AW39="●",AV39,0) -> 0
C40: 28 | D40: 用尺計算 | E40: 工場の作成したマーカー図のチェック、修正依頼 | F40: 日次 | H40: =$H$12/$G$12*G40 -> 0 | K40: =G40+I40 -> 0 | L40: =H40+J40 -> 0 | N40: =N$12/M$12*M40 -> 0 | O40: 0.01 | P40: =P$12/O$12*O40 -> 0.22756154 | Q40: 0.01 | R40: =R$12/Q$12*Q40 -> 0.22756154 | S40: 0.01 | T40: =T$12/S$12*S40 -> 0.22756154 | U40: 0.01 | V40: =V$12/U$12*U40 -> 0.22756154 | W40: 0.01 | X40: =X$12/W$12*W40 -> 0.22756154 | Y40: 0.01 | Z40: =Z$12/Y$12*Y40 -> 0.22756154 | AB40: =AB$12/AA$12*AA40 -> 0 | AC40: =M40+O40+Q40+S40+U40+W40+Y40+AA40 -> 0.06 | AD40: =N40+P40+R40+T40+V40+X40+Z40+AB40 -> 1.3653692 | AF40: =AF$12/AE$12*AE40 -> 0 | AH40: =AH$12/AG$12*AG40 -> 0 | AJ40: =AJ$12/AI$12*AI40 -> 0 | AL40: =AL$12/AK$12*AK40 -> 0 | AN40: =AN$12/AM$12*AM40 -> 0 | AO40: =AE40+AG40+AK40+AM40+AI40 -> 0 | AP40: =AF40+AH40+AL40+AN40+AJ40 -> 0 | AS40: =AQ40 -> 0 | AT40: =AR40 -> 0 | AU40: =K40+AC40+AO40 -> 0.06 | AV40: =L40+AD40+AP40+AT40 -> 1.3653692 | AW40: - | AX40: =IF(AW40="●",AV40,0) -> 0
C41: 29 | D41: 資材不足確認 | E41: 不足資材を確認してTIへ連絡する | F41: 日次 | H41: =$H$12/$G$12*G41 -> 0 | K41: =G41+I41 -> 0 | L41: =H41+J41 -> 0 | N41: =N$12/M$12*M41 -> 0 | O41: 0.05 | P41: =P$12/O$12*O41 -> 1.1378077 | Q41: 0.05 | R41: =R$12/Q$12*Q41 -> 1.1378077 | S41: 0.05 | T41: =T$12/S$12*S41 -> 1.1378077 | U41: 0.05 | V41: =V$12/U$12*U41 -> 1.1378077 | W41: 0.01 | X41: =X$12/W$12*W41 -> 0.22756154 | Y41: 0.01 | Z41: =Z$12/Y$12*Y41 -> 0.22756154 | AB41: =AB$12/AA$12*AA41 -> 0 | AC41: =M41+O41+Q41+S41+U41+W41+Y41+AA41 -> 0.22 | AD41: =N41+P41+R41+T41+V41+X41+Z41+AB41 -> 5.0063538 | AF41: =AF$12/AE$12*AE41 -> 0 | AH41: =AH$12/AG$12*AG41 -> 0 | AJ41: =AJ$12/AI$12*AI41 -> 0 | AL41: =AL$12/AK$12*AK41 -> 0 | AN41: =AN$12/AM$12*AM41 -> 0 | AO41: =AE41+AG41+AK41+AM41+AI41 -> 0 | AP41: =AF41+AH41+AL41+AN41+AJ41 -> 0 | AS41: =AQ41 -> 0 | AT41: =AR41 -> 0 | AU41: =K41+AC41+AO41 -> 0.22 | AV41: =L41+AD41+AP41+AT41 -> 5.0063538 | AW41: - | AX41: =IF(AW41="●",AV41,0) -> 0
C42: 30 | D42: 進捗フォロー | E42: サンプルラインへの進捗フォロー | F42: 週3回程度 | H42: =$H$12/$G$12*G42 -> 0 | K42: =G42+I42 -> 0 | L42: =H42+J42 -> 0 | N42: =N$12/M$12*M42 -> 0 | P42: =P$12/O$12*O42 -> 0 | R42: =R$12/Q$12*Q42 -> 0 | T42: =T$12/S$12*S42 -> 0 | V42: =V$12/U$12*U42 -> 0 | X42: =X$12/W$12*W42 -> 0 | Z42: =Z$12/Y$12*Y42 -> 0 | AB42: =AB$12/AA$12*AA42 -> 0 | AC42: =M42+O42+Q42+S42+U42+W42+Y42+AA42 -> 0 | AD42: =N42+P42+R42+T42+V42+X42+Z42+AB42 -> 0 | AE42: 0.05 | AF42: =AF$12/AE$12*AE42 -> 1.1378077 | AH42: =AH$12/AG$12*AG42 -> 0 | AI42: 0.01 | AJ42: =AJ$12/AI$12*AI42 -> 0.22756154 | AL42: =AL$12/AK$12*AK42 -> 0 | AN42: =AN$12/AM$12*AM42 -> 0 | AO42: =AE42+AG42+AK42+AM42+AI42 -> 0.06 | AP42: =AF42+AH42+AL42+AN42+AJ42 -> 1.3653692 | AS42: =AQ42 -> 0 | AT42: =AR42 -> 0 | AU42: =K42+AC42+AO42 -> 0.06 | AV42: =L42+AD42+AP42+AT42 -> 1.3653692 | AW42: - | AX42: =IF(AW42="●",AV42,0) -> 0
C43: 31 | D43: 諸確認 | E43: サンプル班からの問合せ・質問対応 | F43: 週3回程度 | G43: 0.01 | H43: =$H$12/$G$12*G43 -> 1.8075 | K43: =G43+I43 -> 0.01 | L43: =H43+J43 -> 1.8075 | N43: =N$12/M$12*M43 -> 0 | P43: =P$12/O$12*O43 -> 0 | R43: =R$12/Q$12*Q43 -> 0 | T43: =T$12/S$12*S43 -> 0 | V43: =V$12/U$12*U43 -> 0 | X43: =X$12/W$12*W43 -> 0 | Z43: =Z$12/Y$12*Y43 -> 0 | AB43: =AB$12/AA$12*AA43 -> 0 | AC43: =M43+O43+Q43+S43+U43+W43+Y43+AA43 -> 0 | AD43: =N43+P43+R43+T43+V43+X43+Z43+AB43 -> 0 | AE43: 0.1 | AF43: =AF$12/AE$12*AE43 -> 2.2756154 | AG43: 0.08 | AH43: =AH$12/AG$12*AG43 -> 1.8204923 | AI43: 0.02 | AJ43: =AJ$12/AI$12*AI43 -> 0.45512308 | AL43: =AL$12/AK$12*AK43 -> 0 | AN43: =AN$12/AM$12*AM43 -> 0 | AO43: =AE43+AG43+AK43+AM43+AI43 -> 0.2 | AP43: =AF43+AH43+AL43+AN43+AJ43 -> 4.5512308 | AS43: =AQ43 -> 0 | AT43: =AR43 -> 0 | AU43: =K43+AC43+AO43 -> 0.21 | AV43: =L43+AD43+AP43+AT43 -> 6.3587308 | AW43: - | AX43: =IF(AW43="●",AV43,0) -> 0
C44: 32 | D44: 問題抽出・改善提案 | E44: 仕様・素材に不具合があればアラート・改善提案する。 | F44: 不定期（頻度中） | H44: =$H$12/$G$12*G44 -> 0 | K44: =G44+I44 -> 0 | L44: =H44+J44 -> 0 | N44: =N$12/M$12*M44 -> 0 | P44: =P$12/O$12*O44 -> 0 | R44: =R$12/Q$12*Q44 -> 0 | T44: =T$12/S$12*S44 -> 0 | V44: =V$12/U$12*U44 -> 0 | X44: =X$12/W$12*W44 -> 0 | Z44: =Z$12/Y$12*Y44 -> 0 | AB44: =AB$12/AA$12*AA44 -> 0 | AC44: =M44+O44+Q44+S44+U44+W44+Y44+AA44 -> 0 | AD44: =N44+P44+R44+T44+V44+X44+Z44+AB44 -> 0 | AE44: 0.03 | AF44: =AF$12/AE$12*AE44 -> 0.68268462 | AG44: 0.09 | AH44: =AH$12/AG$12*AG44 -> 2.0480538 | AI44: 0.02 | AJ44: =AJ$12/AI$12*AI44 -> 0.45512308 | AL44: =AL$12/AK$12*AK44 -> 0 | AN44: =AN$12/AM$12*AM44 -> 0 | AO44: =AE44+AG44+AK44+AM44+AI44 -> 0.14 | AP44: =AF44+AH44+AL44+AN44+AJ44 -> 3.1858615 | AS44: =AQ44 -> 0 | AT44: =AR44 -> 0 | AU44: =K44+AC44+AO44 -> 0.14 | AV44: =L44+AD44+AP44+AT44 -> 3.1858615 | AW44: - | AX44: =IF(AW44="●",AV44,0) -> 0
C45: 33 | D45: コメント連絡 | E45: サンプルコメント・採寸表の記入と連絡 | F45: 日次 | H45: =$H$12/$G$12*G45 -> 0 | K45: =G45+I45 -> 0 | L45: =H45+J45 -> 0 | N45: =N$12/M$12*M45 -> 0 | P45: =P$12/O$12*O45 -> 0 | R45: =R$12/Q$12*Q45 -> 0 | T45: =T$12/S$12*S45 -> 0 | V45: =V$12/U$12*U45 -> 0 | X45: =X$12/W$12*W45 -> 0 | Z45: =Z$12/Y$12*Y45 -> 0 | AB45: =AB$12/AA$12*AA45 -> 0 | AC45: =M45+O45+Q45+S45+U45+W45+Y45+AA45 -> 0 | AD45: =N45+P45+R45+T45+V45+X45+Z45+AB45 -> 0 | AE45: 0.22 | AF45: =AF$12/AE$12*AE45 -> 5.0063538 | AH45: =AH$12/AG$12*AG45 -> 0 | AJ45: =AJ$12/AI$12*AI45 -> 0 | AL45: =AL$12/AK$12*AK45 -> 0 | AN45: =AN$12/AM$12*AM45 -> 0 | AO45: =AE45+AG45+AK45+AM45+AI45 -> 0.22 | AP45: =AF45+AH45+AL45+AN45+AJ45 -> 5.0063538 | AS45: =AQ45 -> 0 | AT45: =AR45 -> 0 | AU45: =K45+AC45+AO45 -> 0.22 | AV45: =L45+AD45+AP45+AT45 -> 5.0063538 | AW45: - | AX45: =IF(AW45="●",AV45,0) -> 0
C46: 34 | D46: 二次加工 | E46: 外部工場の見本に関してバルクでの問題点を確認・連絡 | F46: 不定期（頻度低） | H46: =$H$12/$G$12*G46 -> 0 | K46: =G46+I46 -> 0 | L46: =H46+J46 -> 0 | N46: =N$12/M$12*M46 -> 0 | O46: 0.01 | P46: =P$12/O$12*O46 -> 0.22756154 | Q46: 0.01 | R46: =R$12/Q$12*Q46 -> 0.22756154 | S46: 0.01 | T46: =T$12/S$12*S46 -> 0.22756154 | U46: 0.01 | V46: =V$12/U$12*U46 -> 0.22756154 | W46: 0.01 | X46: =X$12/W$12*W46 -> 0.22756154 | Y46: 0.01 | Z46: =Z$12/Y$12*Y46 -> 0.22756154 | AB46: =AB$12/AA$12*AA46 -> 0 | AC46: =M46+O46+Q46+S46+U46+W46+Y46+AA46 -> 0.06 | AD46: =N46+P46+R46+T46+V46+X46+Z46+AB46 -> 1.3653692 | AF46: =AF$12/AE$12*AE46 -> 0 | AH46: =AH$12/AG$12*AG46 -> 0 | AJ46: =AJ$12/AI$12*AI46 -> 0 | AL46: =AL$12/AK$12*AK46 -> 0 | AN46: =AN$12/AM$12*AM46 -> 0 | AO46: =AE46+AG46+AK46+AM46+AI46 -> 0 | AP46: =AF46+AH46+AL46+AN46+AJ46 -> 0 | AS46: =AQ46 -> 0 | AT46: =AR46 -> 0 | AU46: =K46+AC46+AO46 -> 0.06 | AV46: =L46+AD46+AP46+AT46 -> 1.3653692 | AW46: - | AX46: =IF(AW46="●",AV46,0) -> 0
C47: 35 | D47: 出荷連絡 | E47: 出荷明細、送り状NoをTIへ連絡する | F47: 日次 | H47: =$H$12/$G$12*G47 -> 0 | K47: =G47+I47 -> 0 | L47: =H47+J47 -> 0 | N47: =N$12/M$12*M47 -> 0 | P47: =P$12/O$12*O47 -> 0 | R47: =R$12/Q$12*Q47 -> 0 | T47: =T$12/S$12*S47 -> 0 | V47: =V$12/U$12*U47 -> 0 | X47: =X$12/W$12*W47 -> 0 | Z47: =Z$12/Y$12*Y47 -> 0 | AA47: 0.02 | AB47: =AB$12/AA$12*AA47 -> 0.45512308 | AC47: =M47+O47+Q47+S47+U47+W47+Y47+AA47 -> 0.02 | AD47: =N47+P47+R47+T47+V47+X47+Z47+AB47 -> 0.45512308 | AF47: =AF$12/AE$12*AE47 -> 0 | AH47: =AH$12/AG$12*AG47 -> 0 | AJ47: =AJ$12/AI$12*AI47 -> 0 | AL47: =AL$12/AK$12*AK47 -> 0 | AN47: =AN$12/AM$12*AM47 -> 0 | AO47: =AE47+AG47+AK47+AM47+AI47 -> 0 | AP47: =AF47+AH47+AL47+AN47+AJ47 -> 0 | AS47: =AQ47 -> 0 | AT47: =AR47 -> 0 | AU47: =K47+AC47+AO47 -> 0.02 | AV47: =L47+AD47+AP47+AT47 -> 0.45512308 | AW47: - | AX47: =IF(AW47="●",AV47,0) -> 0
C48: 36 | D48: 発送 | E48: 0 | F48: 日次 | H48: =$H$12/$G$12*G48 -> 0 | K48: =G48+I48 -> 0 | L48: =H48+J48 -> 0 | N48: =N$12/M$12*M48 -> 0 | P48: =P$12/O$12*O48 -> 0 | R48: =R$12/Q$12*Q48 -> 0 | T48: =T$12/S$12*S48 -> 0 | V48: =V$12/U$12*U48 -> 0 | X48: =X$12/W$12*W48 -> 0 | Z48: =Z$12/Y$12*Y48 -> 0 | AA48: 0.02 | AB48: =AB$12/AA$12*AA48 -> 0.45512308 | AC48: =M48+O48+Q48+S48+U48+W48+Y48+AA48 -> 0.02 | AD48: =N48+P48+R48+T48+V48+X48+Z48+AB48 -> 0.45512308 | AF48: =AF$12/AE$12*AE48 -> 0 | AH48: =AH$12/AG$12*AG48 -> 0 | AJ48: =AJ$12/AI$12*AI48 -> 0 | AL48: =AL$12/AK$12*AK48 -> 0 | AN48: =AN$12/AM$12*AM48 -> 0 | AO48: =AE48+AG48+AK48+AM48+AI48 -> 0 | AP48: =AF48+AH48+AL48+AN48+AJ48 -> 0 | AS48: =AQ48 -> 0 | AT48: =AR48 -> 0 | AU48: =K48+AC48+AO48 -> 0.02 | AV48: =L48+AD48+AP48+AT48 -> 0.45512308 | AW48: ● | AX48: =IF(AW48="●",AV48,0) -> 0.45512308
C49: 37 | D49: 生産条件設定 | E49: 接着・シーム条件検討。機能性検査・記録 | F49: 日次 | H49: =$H$12/$G$12*G49 -> 0 | K49: =G49+I49 -> 0 | L49: =H49+J49 -> 0 | N49: =N$12/M$12*M49 -> 0 | P49: =P$12/O$12*O49 -> 0 | R49: =R$12/Q$12*Q49 -> 0 | T49: =T$12/S$12*S49 -> 0 | V49: =V$12/U$12*U49 -> 0 | X49: =X$12/W$12*W49 -> 0 | Z49: =Z$12/Y$12*Y49 -> 0 | AB49: =AB$12/AA$12*AA49 -> 0 | AC49: =M49+O49+Q49+S49+U49+W49+Y49+AA49 -> 0 | AD49: =N49+P49+R49+T49+V49+X49+Z49+AB49 -> 0 | AE49: 0.05 | AF49: =AF$12/AE$12*AE49 -> 1.1378077 | AG49: 0.01 | AH49: =AH$12/AG$12*AG49 -> 0.22756154 | AI49: 0.01 | AJ49: =AJ$12/AI$12*AI49 -> 0.22756154 | AL49: =AL$12/AK$12*AK49 -> 0 | AN49: =AN$12/AM$12*AM49 -> 0 | AO49: =AE49+AG49+AK49+AM49+AI49 -> 0.07 | AP49: =AF49+AH49+AL49+AN49+AJ49 -> 1.5929308 | AS49: =AQ49 -> 0 | AT49: =AR49 -> 0 | AU49: =K49+AC49+AO49 -> 0.07 | AV49: =L49+AD49+AP49+AT49 -> 1.5929308 | AW49: - | AX49: =IF(AW49="●",AV49,0) -> 0
C50: 38 | D50: 工程分析 | E50: 生産能力・コスト試算 | F50: 不定期（頻度低） | G50: 0.01 | H50: =$H$12/$G$12*G50 -> 1.8075 | K50: =G50+I50 -> 0.01 | L50: =H50+J50 -> 1.8075 | M50: 0.01 | N50: =N$12/M$12*M50 -> 0.22756154 | P50: =P$12/O$12*O50 -> 0 | R50: =R$12/Q$12*Q50 -> 0 | T50: =T$12/S$12*S50 -> 0 | V50: =V$12/U$12*U50 -> 0 | X50: =X$12/W$12*W50 -> 0 | Z50: =Z$12/Y$12*Y50 -> 0 | AB50: =AB$12/AA$12*AA50 -> 0 | AC50: =M50+O50+Q50+S50+U50+W50+Y50+AA50 -> 0.01 | AD50: =N50+P50+R50+T50+V50+X50+Z50+AB50 -> 0.22756154 | AF50: =AF$12/AE$12*AE50 -> 0 | AH50: =AH$12/AG$12*AG50 -> 0 | AJ50: =AJ$12/AI$12*AI50 -> 0 | AL50: =AL$12/AK$12*AK50 -> 0 | AN50: =AN$12/AM$12*AM50 -> 0 | AO50: =AE50+AG50+AK50+AM50+AI50 -> 0 | AP50: =AF50+AH50+AL50+AN50+AJ50 -> 0 | AS50: =AQ50 -> 0 | AT50: =AR50 -> 0 | AU50: =K50+AC50+AO50 -> 0.02 | AV50: =L50+AD50+AP50+AT50 -> 2.0350615 | AW50: - | AX50: =IF(AW50="●",AV50,0) -> 0
C51: 39 | D51: 元見本管理 | E51: 元見本台帳を作成し入出庫を管理する | F51: 不定期（頻度中） | H51: =$H$12/$G$12*G51 -> 0 | K51: =G51+I51 -> 0 | L51: =H51+J51 -> 0 | N51: =N$12/M$12*M51 -> 0 | O51: 0.01 | P51: =P$12/O$12*O51 -> 0.22756154 | Q51: 0.01 | R51: =R$12/Q$12*Q51 -> 0.22756154 | S51: 0.01 | T51: =T$12/S$12*S51 -> 0.22756154 | U51: 0.01 | V51: =V$12/U$12*U51 -> 0.22756154 | W51: 0.01 | X51: =X$12/W$12*W51 -> 0.22756154 | Y51: 0.01 | Z51: =Z$12/Y$12*Y51 -> 0.22756154 | AA51: 0.01 | AB51: =AB$12/AA$12*AA51 -> 0.22756154 | AC51: =M51+O51+Q51+S51+U51+W51+Y51+AA51 -> 0.07 | AD51: =N51+P51+R51+T51+V51+X51+Z51+AB51 -> 1.5929308 | AE51: 0.02 | AF51: =AF$12/AE$12*AE51 -> 0.45512308 | AH51: =AH$12/AG$12*AG51 -> 0 | AJ51: =AJ$12/AI$12*AI51 -> 0 | AL51: =AL$12/AK$12*AK51 -> 0 | AN51: =AN$12/AM$12*AM51 -> 0 | AO51: =AE51+AG51+AK51+AM51+AI51 -> 0.02 | AP51: =AF51+AH51+AL51+AN51+AJ51 -> 0.45512308 | AS51: =AQ51 -> 0 | AT51: =AR51 -> 0 | AU51: =K51+AC51+AO51 -> 0.09 | AV51: =L51+AD51+AP51+AT51 -> 2.0480538 | AW51: - | AX51: =IF(AW51="●",AV51,0) -> 0
B52: 仕様書 | C52: 40 | D52: ファイル作成 | E52: 仕様書をプリントアウトしブランド・シーズン別にファイルを作成 | F52: 不定期（頻度中） | H52: =$H$12/$G$12*G52 -> 0 | K52: =G52+I52 -> 0 | L52: =H52+J52 -> 0 | N52: =N$12/M$12*M52 -> 0 | O52: 0.01 | P52: =P$12/O$12*O52 -> 0.22756154 | Q52: 0.01 | R52: =R$12/Q$12*Q52 -> 0.22756154 | S52: 0.01 | T52: =T$12/S$12*S52 -> 0.22756154 | U52: 0.01 | V52: =V$12/U$12*U52 -> 0.22756154 | W52: 0.01 | X52: =X$12/W$12*W52 -> 0.22756154 | Y52: 0.01 | Z52: =Z$12/Y$12*Y52 -> 0.22756154 | AB52: =AB$12/AA$12*AA52 -> 0 | AC52: =M52+O52+Q52+S52+U52+W52+Y52+AA52 -> 0.06 | AD52: =N52+P52+R52+T52+V52+X52+Z52+AB52 -> 1.3653692 | AF52: =AF$12/AE$12*AE52 -> 0 | AH52: =AH$12/AG$12*AG52 -> 0 | AJ52: =AJ$12/AI$12*AI52 -> 0 | AL52: =AL$12/AK$12*AK52 -> 0 | AN52: =AN$12/AM$12*AM52 -> 0 | AO52: =AE52+AG52+AK52+AM52+AI52 -> 0 | AP52: =AF52+AH52+AL52+AN52+AJ52 -> 0 | AS52: =AQ52 -> 0 | AT52: =AR52 -> 0 | AU52: =K52+AC52+AO52 -> 0.06 | AV52: =L52+AD52+AP52+AT52 -> 1.3653692 | AW52: - | AX52: =IF(AW52="●",AV52,0) -> 0
C53: 41 | D53: 翻訳 | E53: ベトナム語への翻訳 | F53: 日次 | H53: =$H$12/$G$12*G53 -> 0 | K53: =G53+I53 -> 0 | L53: =H53+J53 -> 0 | N53: =N$12/M$12*M53 -> 0 | O53: 0.15 | P53: =P$12/O$12*O53 -> 3.4134231 | Q53: 0.15 | R53: =R$12/Q$12*Q53 -> 3.4134231 | S53: 0.15 | T53: =T$12/S$12*S53 -> 3.4134231 | U53: 0.15 | V53: =V$12/U$12*U53 -> 3.4134231 | W53: 0.15 | X53: =X$12/W$12*W53 -> 3.4134231 | Y53: 0.1 | Z53: =Z$12/Y$12*Y53 -> 2.2756154 | AB53: =AB$12/AA$12*AA53 -> 0 | AC53: =M53+O53+Q53+S53+U53+W53+Y53+AA53 -> 0.85 | AD53: =N53+P53+R53+T53+V53+X53+Z53+AB53 -> 19.342731 | AF53: =AF$12/AE$12*AE53 -> 0 | AH53: =AH$12/AG$12*AG53 -> 0 | AJ53: =AJ$12/AI$12*AI53 -> 0 | AL53: =AL$12/AK$12*AK53 -> 0 | AN53: =AN$12/AM$12*AM53 -> 0 | AO53: =AE53+AG53+AK53+AM53+AI53 -> 0 | AP53: =AF53+AH53+AL53+AN53+AJ53 -> 0 | AS53: =AQ53 -> 0 | AT53: =AR53 -> 0 | AU53: =K53+AC53+AO53 -> 0.85 | AV53: =L53+AD53+AP53+AT53 -> 19.342731 | AW53: - | AX53: =IF(AW53="●",AV53,0) -> 0
C54: 42 | D54: チェック | E54: パターンや元見本と違ったり問題があった場合、TIへ連絡する | F54: 日次 | H54: =$H$12/$G$12*G54 -> 0 | K54: =G54+I54 -> 0 | L54: =H54+J54 -> 0 | N54: =N$12/M$12*M54 -> 0 | O54: 0.03 | P54: =P$12/O$12*O54 -> 0.68268462 | Q54: 0.03 | R54: =R$12/Q$12*Q54 -> 0.68268462 | S54: 0.03 | T54: =T$12/S$12*S54 -> 0.68268462 | U54: 0.02 | V54: =V$12/U$12*U54 -> 0.45512308 | W54: 0.04 | X54: =X$12/W$12*W54 -> 0.91024615 | Y54: 0.05 | Z54: =Z$12/Y$12*Y54 -> 1.1378077 | AB54: =AB$12/AA$12*AA54 -> 0 | AC54: =M54+O54+Q54+S54+U54+W54+Y54+AA54 -> 0.2 | AD54: =N54+P54+R54+T54+V54+X54+Z54+AB54 -> 4.5512308 | AF54: =AF$12/AE$12*AE54 -> 0 | AH54: =AH$12/AG$12*AG54 -> 0 | AJ54: =AJ$12/AI$12*AI54 -> 0 | AL54: =AL$12/AK$12*AK54 -> 0 | AN54: =AN$12/AM$12*AM54 -> 0 | AO54: =AE54+AG54+AK54+AM54+AI54 -> 0 | AP54: =AF54+AH54+AL54+AN54+AJ54 -> 0 | AS54: =AQ54 -> 0 | AT54: =AR54 -> 0 | AU54: =K54+AC54+AO54 -> 0.2 | AV54: =L54+AD54+AP54+AT54 -> 4.5512308 | AW54: - | AX54: =IF(AW54="●",AV54,0) -> 0
C55: 43 | D55: 修正連絡 | E55: 修正があれば修正仕様書を翻訳し工場へ連絡する | F55: 不定期（頻度高） | H55: =$H$12/$G$12*G55 -> 0 | K55: =G55+I55 -> 0 | L55: =H55+J55 -> 0 | N55: =N$12/M$12*M55 -> 0 | O55: 0.01 | P55: =P$12/O$12*O55 -> 0.22756154 | Q55: 0.01 | R55: =R$12/Q$12*Q55 -> 0.22756154 | S55: 0.01 | T55: =T$12/S$12*S55 -> 0.22756154 | U55: 0.01 | V55: =V$12/U$12*U55 -> 0.22756154 | W55: 0.04 | X55: =X$12/W$12*W55 -> 0.91024615 | Y55: 0.04 | Z55: =Z$12/Y$12*Y55 -> 0.91024615 | AB55: =AB$12/AA$12*AA55 -> 0 | AC55: =M55+O55+Q55+S55+U55+W55+Y55+AA55 -> 0.12 | AD55: =N55+P55+R55+T55+V55+X55+Z55+AB55 -> 2.7307385 | AF55: =AF$12/AE$12*AE55 -> 0 | AH55: =AH$12/AG$12*AG55 -> 0 | AJ55: =AJ$12/AI$12*AI55 -> 0 | AL55: =AL$12/AK$12*AK55 -> 0 | AN55: =AN$12/AM$12*AM55 -> 0 | AO55: =AE55+AG55+AK55+AM55+AI55 -> 0 | AP55: =AF55+AH55+AL55+AN55+AJ55 -> 0 | AS55: =AQ55 -> 0 | AT55: =AR55 -> 0 | AU55: =K55+AC55+AO55 -> 0.12 | AV55: =L55+AD55+AP55+AT55 -> 2.7307385 | AW55: - | AX55: =IF(AW55="●",AV55,0) -> 0
B56: パターン | C56: 44 | D56: パターン連絡 | E56: パターンデータを工場に転送する | F56: 不定期（頻度高） | H56: =$H$12/$G$12*G56 -> 0 | K56: =G56+I56 -> 0 | L56: =H56+J56 -> 0 | N56: =N$12/M$12*M56 -> 0 | O56: 0.01 | P56: =P$12/O$12*O56 -> 0.22756154 | Q56: 0.01 | R56: =R$12/Q$12*Q56 -> 0.22756154 | S56: 0.01 | T56: =T$12/S$12*S56 -> 0.22756154 | U56: 0.01 | V56: =V$12/U$12*U56 -> 0.22756154 | W56: 0.01 | X56: =X$12/W$12*W56 -> 0.22756154 | Y56: 0.01 | Z56: =Z$12/Y$12*Y56 -> 0.22756154 | AB56: =AB$12/AA$12*AA56 -> 0 | AC56: =M56+O56+Q56+S56+U56+W56+Y56+AA56 -> 0.06 | AD56: =N56+P56+R56+T56+V56+X56+Z56+AB56 -> 1.3653692 | AF56: =AF$12/AE$12*AE56 -> 0 | AH56: =AH$12/AG$12*AG56 -> 0 | AJ56: =AJ$12/AI$12*AI56 -> 0 | AL56: =AL$12/AK$12*AK56 -> 0 | AN56: =AN$12/AM$12*AM56 -> 0 | AO56: =AE56+AG56+AK56+AM56+AI56 -> 0 | AP56: =AF56+AH56+AL56+AN56+AJ56 -> 0 | AS56: =AQ56 -> 0 | AT56: =AR56 -> 0 | AU56: =K56+AC56+AO56 -> 0.06 | AV56: =L56+AD56+AP56+AT56 -> 1.3653692 | AW56: - | AX56: =IF(AW56="●",AV56,0) -> 0
C57: 45 | D57: チェック | E57: 仕様書と違ったり問題があった場合、TIへ連絡する | F57: 不定期（頻度中） | H57: =$H$12/$G$12*G57 -> 0 | K57: =G57+I57 -> 0 | L57: =H57+J57 -> 0 | N57: =N$12/M$12*M57 -> 0 | O57: 0.01 | P57: =P$12/O$12*O57 -> 0.22756154 | Q57: 0.01 | R57: =R$12/Q$12*Q57 -> 0.22756154 | S57: 0.01 | T57: =T$12/S$12*S57 -> 0.22756154 | U57: 0.01 | V57: =V$12/U$12*U57 -> 0.22756154 | W57: 0.01 | X57: =X$12/W$12*W57 -> 0.22756154 | Y57: 0.01 | Z57: =Z$12/Y$12*Y57 -> 0.22756154 | AB57: =AB$12/AA$12*AA57 -> 0 | AC57: =M57+O57+Q57+S57+U57+W57+Y57+AA57 -> 0.06 | AD57: =N57+P57+R57+T57+V57+X57+Z57+AB57 -> 1.3653692 | AF57: =AF$12/AE$12*AE57 -> 0 | AH57: =AH$12/AG$12*AG57 -> 0 | AJ57: =AJ$12/AI$12*AI57 -> 0 | AL57: =AL$12/AK$12*AK57 -> 0 | AN57: =AN$12/AM$12*AM57 -> 0 | AO57: =AE57+AG57+AK57+AM57+AI57 -> 0 | AP57: =AF57+AH57+AL57+AN57+AJ57 -> 0 | AS57: =AQ57 -> 0 | AT57: =AR57 -> 0 | AU57: =K57+AC57+AO57 -> 0.06 | AV57: =L57+AD57+AP57+AT57 -> 1.3653692 | AW57: - | AX57: =IF(AW57="●",AV57,0) -> 0
C58: 46 | D58: 修正 | E58: 一部不具合を工場で修正するように指示 | F58: 不定期（頻度中） | H58: =$H$12/$G$12*G58 -> 0 | K58: =G58+I58 -> 0 | L58: =H58+J58 -> 0 | N58: =N$12/M$12*M58 -> 0 | O58: 0.01 | P58: =P$12/O$12*O58 -> 0.22756154 | Q58: 0.01 | R58: =R$12/Q$12*Q58 -> 0.22756154 | S58: 0.01 | T58: =T$12/S$12*S58 -> 0.22756154 | U58: 0.01 | V58: =V$12/U$12*U58 -> 0.22756154 | W58: 0.01 | X58: =X$12/W$12*W58 -> 0.22756154 | Y58: 0.01 | Z58: =Z$12/Y$12*Y58 -> 0.22756154 | AB58: =AB$12/AA$12*AA58 -> 0 | AC58: =M58+O58+Q58+S58+U58+W58+Y58+AA58 -> 0.06 | AD58: =N58+P58+R58+T58+V58+X58+Z58+AB58 -> 1.3653692 | AE58: 0.2 | AF58: =AF$12/AE$12*AE58 -> 4.5512308 | AG58: 0.01 | AH58: =AH$12/AG$12*AG58 -> 0.22756154 | AI58: 0.01 | AJ58: =AJ$12/AI$12*AI58 -> 0.22756154 | AL58: =AL$12/AK$12*AK58 -> 0 | AN58: =AN$12/AM$12*AM58 -> 0 | AO58: =AE58+AG58+AK58+AM58+AI58 -> 0.22 | AP58: =AF58+AH58+AL58+AN58+AJ58 -> 5.0063538 | AS58: =AQ58 -> 0 | AT58: =AR58 -> 0 | AU58: =K58+AC58+AO58 -> 0.28 | AV58: =L58+AD58+AP58+AT58 -> 6.3717231 | AW58: - | AX58: =IF(AW58="●",AV58,0) -> 0
B59: 資材管理 | C59: 47 | D59: 資材着荷確認 | E59: BL、P/L、DHL No などを工場へ連絡する | F59: 日次 | H59: =$H$12/$G$12*G59 -> 0 | K59: =G59+I59 -> 0 | L59: =H59+J59 -> 0 | N59: =N$12/M$12*M59 -> 0 | O59: 0.02 | P59: =P$12/O$12*O59 -> 0.45512308 | Q59: 0.02 | R59: =R$12/Q$12*Q59 -> 0.45512308 | S59: 0.02 | T59: =T$12/S$12*S59 -> 0.45512308 | U59: 0.01 | V59: =V$12/U$12*U59 -> 0.22756154 | W59: 0.01 | X59: =X$12/W$12*W59 -> 0.22756154 | Y59: 0.01 | Z59: =Z$12/Y$12*Y59 -> 0.22756154 | AB59: =AB$12/AA$12*AA59 -> 0 | AC59: =M59+O59+Q59+S59+U59+W59+Y59+AA59 -> 0.09 | AD59: =N59+P59+R59+T59+V59+X59+Z59+AB59 -> 2.0480538 | AF59: =AF$12/AE$12*AE59 -> 0 | AH59: =AH$12/AG$12*AG59 -> 0 | AJ59: =AJ$12/AI$12*AI59 -> 0 | AL59: =AL$12/AK$12*AK59 -> 0 | AN59: =AN$12/AM$12*AM59 -> 0 | AO59: =AE59+AG59+AK59+AM59+AI59 -> 0 | AP59: =AF59+AH59+AL59+AN59+AJ59 -> 0 | AS59: =AQ59 -> 0 | AT59: =AR59 -> 0 | AU59: =K59+AC59+AO59 -> 0.09 | AV59: =L59+AD59+AP59+AT59 -> 2.0480538 | AW59: - | AX59: =IF(AW59="●",AV59,0) -> 0
C60: 48 | D60: 資材不足確認 | E60: 工場からのバランスシートをもとにTIへ不足連絡をする | F60: 日次 | H60: =$H$12/$G$12*G60 -> 0 | K60: =G60+I60 -> 0 | L60: =H60+J60 -> 0 | N60: =N$12/M$12*M60 -> 0 | O60: 0.16 | P60: =P$12/O$12*O60 -> 3.6409846 | Q60: 0.16 | R60: =R$12/Q$12*Q60 -> 3.6409846 | S60: 0.13 | T60: =T$12/S$12*S60 -> 2.9583 | U60: 0.2 | V60: =V$12/U$12*U60 -> 4.5512308 | W60: 0.01 | X60: =X$12/W$12*W60 -> 0.22756154 | Y60: 0.1 | Z60: =Z$12/Y$12*Y60 -> 2.2756154 | AA60: 0.01 | AB60: =AB$12/AA$12*AA60 -> 0.22756154 | AC60: =M60+O60+Q60+S60+U60+W60+Y60+AA60 -> 0.77 | AD60: =N60+P60+R60+T60+V60+X60+Z60+AB60 -> 17.522238 | AF60: =AF$12/AE$12*AE60 -> 0 | AH60: =AH$12/AG$12*AG60 -> 0 | AJ60: =AJ$12/AI$12*AI60 -> 0 | AL60: =AL$12/AK$12*AK60 -> 0 | AN60: =AN$12/AM$12*AM60 -> 0 | AO60: =AE60+AG60+AK60+AM60+AI60 -> 0 | AP60: =AF60+AH60+AL60+AN60+AJ60 -> 0 | AS60: =AQ60 -> 0 | AT60: =AR60 -> 0 | AU60: =K60+AC60+AO60 -> 0.77 | AV60: =L60+AD60+AP60+AT60 -> 17.522238 | AW60: - | AX60: =IF(AW60="●",AV60,0) -> 0
C61: 49 | D61: 生地不良確認 | E61: 工場から検反報告をもらい不良内容をTIへ確認する | F61: 日次 | H61: =$H$12/$G$12*G61 -> 0 | K61: =G61+I61 -> 0 | L61: =H61+J61 -> 0 | N61: =N$12/M$12*M61 -> 0 | O61: 0.02 | P61: =P$12/O$12*O61 -> 0.45512308 | Q61: 0.02 | R61: =R$12/Q$12*Q61 -> 0.45512308 | S61: 0.02 | T61: =T$12/S$12*S61 -> 0.45512308 | U61: 0.01 | V61: =V$12/U$12*U61 -> 0.22756154 | W61: 0.01 | X61: =X$12/W$12*W61 -> 0.22756154 | Y61: 0.01 | Z61: =Z$12/Y$12*Y61 -> 0.22756154 | AA61: 0.01 | AB61: =AB$12/AA$12*AA61 -> 0.22756154 | AC61: =M61+O61+Q61+S61+U61+W61+Y61+AA61 -> 0.1 | AD61: =N61+P61+R61+T61+V61+X61+Z61+AB61 -> 2.2756154 | AF61: =AF$12/AE$12*AE61 -> 0 | AH61: =AH$12/AG$12*AG61 -> 0 | AJ61: =AJ$12/AI$12*AI61 -> 0 | AL61: =AL$12/AK$12*AK61 -> 0 | AN61: =AN$12/AM$12*AM61 -> 0 | AO61: =AE61+AG61+AK61+AM61+AI61 -> 0 | AP61: =AF61+AH61+AL61+AN61+AJ61 -> 0 | AS61: =AQ61 -> 0 | AT61: =AR61 -> 0 | AU61: =K61+AC61+AO61 -> 0.1 | AV61: =L61+AD61+AP61+AT61 -> 2.2756154 | AW61: - | AX61: =IF(AW61="●",AV61,0) -> 0
A62: 本生産 | B62: 裁断 | C62: 50 | D62: 明細確認 | E62: 工場が作成した裁断明細を入手しチェックする | F62: 日次 | H62: =$H$12/$G$12*G62 -> 0 | K62: =G62+I62 -> 0 | L62: =H62+J62 -> 0 | N62: =N$12/M$12*M62 -> 0 | O62: 0.01 | P62: =P$12/O$12*O62 -> 0.22756154 | Q62: 0.01 | R62: =R$12/Q$12*Q62 -> 0.22756154 | S62: 0.01 | T62: =T$12/S$12*S62 -> 0.22756154 | U62: 0.01 | V62: =V$12/U$12*U62 -> 0.22756154 | W62: 0.01 | X62: =X$12/W$12*W62 -> 0.22756154 | Y62: 0.01 | Z62: =Z$12/Y$12*Y62 -> 0.22756154 | AB62: =AB$12/AA$12*AA62 -> 0 | AC62: =M62+O62+Q62+S62+U62+W62+Y62+AA62 -> 0.06 | AD62: =N62+P62+R62+T62+V62+X62+Z62+AB62 -> 1.3653692 | AF62: =AF$12/AE$12*AE62 -> 0 | AH62: =AH$12/AG$12*AG62 -> 0 | AJ62: =AJ$12/AI$12*AI62 -> 0 | AL62: =AL$12/AK$12*AK62 -> 0 | AN62: =AN$12/AM$12*AM62 -> 0 | AO62: =AE62+AG62+AK62+AM62+AI62 -> 0 | AP62: =AF62+AH62+AL62+AN62+AJ62 -> 0 | AS62: =AQ62 -> 0 | AT62: =AR62 -> 0 | AU62: =K62+AC62+AO62 -> 0.06 | AV62: =L62+AD62+AP62+AT62 -> 1.3653692 | AW62: - | AX62: =IF(AW62="●",AV62,0) -> 0
C63: 51 | D63: 要尺確認 | E63: サンプル要尺を確認してTIへ連絡する | F63: 日次 | H63: =$H$12/$G$12*G63 -> 0 | K63: =G63+I63 -> 0 | L63: =H63+J63 -> 0 | N63: =N$12/M$12*M63 -> 0 | O63: 0.02 | P63: =P$12/O$12*O63 -> 0.45512308 | Q63: 0.02 | R63: =R$12/Q$12*Q63 -> 0.45512308 | S63: 0.02 | T63: =T$12/S$12*S63 -> 0.45512308 | U63: 0.01 | V63: =V$12/U$12*U63 -> 0.22756154 | W63: 0.01 | X63: =X$12/W$12*W63 -> 0.22756154 | Y63: 0.01 | Z63: =Z$12/Y$12*Y63 -> 0.22756154 | AB63: =AB$12/AA$12*AA63 -> 0 | AC63: =M63+O63+Q63+S63+U63+W63+Y63+AA63 -> 0.09 | AD63: =N63+P63+R63+T63+V63+X63+Z63+AB63 -> 2.0480538 | AF63: =AF$12/AE$12*AE63 -> 0 | AH63: =AH$12/AG$12*AG63 -> 0 | AJ63: =AJ$12/AI$12*AI63 -> 0 | AL63: =AL$12/AK$12*AK63 -> 0 | AN63: =AN$12/AM$12*AM63 -> 0 | AO63: =AE63+AG63+AK63+AM63+AI63 -> 0 | AP63: =AF63+AH63+AL63+AN63+AJ63 -> 0 | AS63: =AQ63 -> 0 | AT63: =AR63 -> 0 | AU63: =K63+AC63+AO63 -> 0.09 | AV63: =L63+AD63+AP63+AT63 -> 2.0480538 | AW63: - | AX63: =IF(AW63="●",AV63,0) -> 0
C64: 52 | D64: トラブル対応 | E64: 色違い・収縮等のトラブル発生時の対応 | F64: 不定期（頻度高） | G64: 0.02 | H64: =$H$12/$G$12*G64 -> 3.615 | K64: =G64+I64 -> 0.02 | L64: =H64+J64 -> 3.615 | M64: 0.02 | N64: =N$12/M$12*M64 -> 0.45512308 | O64: 0.01 | P64: =P$12/O$12*O64 -> 0.22756154 | Q64: 0.01 | R64: =R$12/Q$12*Q64 -> 0.22756154 | S64: 0.01 | T64: =T$12/S$12*S64 -> 0.22756154 | U64: 0.01 | V64: =V$12/U$12*U64 -> 0.22756154 | W64: 0.02 | X64: =X$12/W$12*W64 -> 0.45512308 | Y64: 0.01 | Z64: =Z$12/Y$12*Y64 -> 0.22756154 | AA64: 0.05 | AB64: =AB$12/AA$12*AA64 -> 1.1378077 | AC64: =M64+O64+Q64+S64+U64+W64+Y64+AA64 -> 0.14 | AD64: =N64+P64+R64+T64+V64+X64+Z64+AB64 -> 3.1858615 | AF64: =AF$12/AE$12*AE64 -> 0 | AG64: 0.18 | AH64: =AH$12/AG$12*AG64 -> 4.0961077 | AI64: 0.18 | AJ64: =AJ$12/AI$12*AI64 -> 4.0961077 | AK64: 0.06 | AL64: =AL$12/AK$12*AK64 -> 1.3653692 | AM64: 0.06 | AN64: =AN$12/AM$12*AM64 -> 1.3653692 | AO64: =AE64+AG64+AK64+AM64+AI64 -> 0.48 | AP64: =AF64+AH64+AL64+AN64+AJ64 -> 10.922954 | AS64: =AQ64 -> 0 | AT64: =AR64 -> 0 | AU64: =K64+AC64+AO64 -> 0.64 | AV64: =L64+AD64+AP64+AT64 -> 17.723815 | AW64: - | AX64: =IF(AW64="●",AV64,0) -> 0
B65: 二次加工 | C65: 53 | D65: 刺繍 | E65: 刺繍データを入手し、刺繍屋に連絡する | F65: 不定期（頻度中） | H65: =$H$12/$G$12*G65 -> 0 | K65: =G65+I65 -> 0 | L65: =H65+J65 -> 0 | N65: =N$12/M$12*M65 -> 0 | O65: 0.01 | P65: =P$12/O$12*O65 -> 0.22756154 | Q65: 0.01 | R65: =R$12/Q$12*Q65 -> 0.22756154 | S65: 0.01 | T65: =T$12/S$12*S65 -> 0.22756154 | U65: 0.01 | V65: =V$12/U$12*U65 -> 0.22756154 | W65: 0.01 | X65: =X$12/W$12*W65 -> 0.22756154 | Y65: 0.01 | Z65: =Z$12/Y$12*Y65 -> 0.22756154 | AB65: =AB$12/AA$12*AA65 -> 0 | AC65: =M65+O65+Q65+S65+U65+W65+Y65+AA65 -> 0.06 | AD65: =N65+P65+R65+T65+V65+X65+Z65+AB65 -> 1.3653692 | AF65: =AF$12/AE$12*AE65 -> 0 | AH65: =AH$12/AG$12*AG65 -> 0 | AJ65: =AJ$12/AI$12*AI65 -> 0 | AL65: =AL$12/AK$12*AK65 -> 0 | AN65: =AN$12/AM$12*AM65 -> 0 | AO65: =AE65+AG65+AK65+AM65+AI65 -> 0 | AP65: =AF65+AH65+AL65+AN65+AJ65 -> 0 | AS65: =AQ65 -> 0 | AT65: =AR65 -> 0 | AU65: =K65+AC65+AO65 -> 0.06 | AV65: =L65+AD65+AP65+AT65 -> 1.3653692 | AW65: - | AX65: =IF(AW65="●",AV65,0) -> 0
B66: ※2 | C66: 54 | D66: プリント | E66: プリントデータを入手し、プリント屋に連絡する | F66: 不定期（頻度中） | H66: =$H$12/$G$12*G66 -> 0 | K66: =G66+I66 -> 0 | L66: =H66+J66 -> 0 | N66: =N$12/M$12*M66 -> 0 | O66: 0.01 | P66: =P$12/O$12*O66 -> 0.22756154 | Q66: 0.01 | R66: =R$12/Q$12*Q66 -> 0.22756154 | S66: 0.01 | T66: =T$12/S$12*S66 -> 0.22756154 | U66: 0.01 | V66: =V$12/U$12*U66 -> 0.22756154 | W66: 0.01 | X66: =X$12/W$12*W66 -> 0.22756154 | Y66: 0.01 | Z66: =Z$12/Y$12*Y66 -> 0.22756154 | AB66: =AB$12/AA$12*AA66 -> 0 | AC66: =M66+O66+Q66+S66+U66+W66+Y66+AA66 -> 0.06 | AD66: =N66+P66+R66+T66+V66+X66+Z66+AB66 -> 1.3653692 | AF66: =AF$12/AE$12*AE66 -> 0 | AH66: =AH$12/AG$12*AG66 -> 0 | AJ66: =AJ$12/AI$12*AI66 -> 0 | AL66: =AL$12/AK$12*AK66 -> 0 | AN66: =AN$12/AM$12*AM66 -> 0 | AO66: =AE66+AG66+AK66+AM66+AI66 -> 0 | AP66: =AF66+AH66+AL66+AN66+AJ66 -> 0 | AS66: =AQ66 -> 0 | AT66: =AR66 -> 0 | AU66: =K66+AC66+AO66 -> 0.06 | AV66: =L66+AD66+AP66+AT66 -> 1.3653692 | AW66: - | AX66: =IF(AW66="●",AV66,0) -> 0
C67: 55 | D67: キルト | E67: 依頼内容のバルク展開可否判断 | F67: 不定期（頻度低） | H67: =$H$12/$G$12*G67 -> 0 | K67: =G67+I67 -> 0 | L67: =H67+J67 -> 0 | N67: =N$12/M$12*M67 -> 0 | O67: 0.01 | P67: =P$12/O$12*O67 -> 0.22756154 | Q67: 0.01 | R67: =R$12/Q$12*Q67 -> 0.22756154 | S67: 0.01 | T67: =T$12/S$12*S67 -> 0.22756154 | U67: 0.01 | V67: =V$12/U$12*U67 -> 0.22756154 | W67: 0.01 | X67: =X$12/W$12*W67 -> 0.22756154 | Y67: 0.01 | Z67: =Z$12/Y$12*Y67 -> 0.22756154 | AB67: =AB$12/AA$12*AA67 -> 0 | AC67: =M67+O67+Q67+S67+U67+W67+Y67+AA67 -> 0.06 | AD67: =N67+P67+R67+T67+V67+X67+Z67+AB67 -> 1.3653692 | AF67: =AF$12/AE$12*AE67 -> 0 | AH67: =AH$12/AG$12*AG67 -> 0 | AJ67: =AJ$12/AI$12*AI67 -> 0 | AL67: =AL$12/AK$12*AK67 -> 0 | AN67: =AN$12/AM$12*AM67 -> 0 | AO67: =AE67+AG67+AK67+AM67+AI67 -> 0 | AP67: =AF67+AH67+AL67+AN67+AJ67 -> 0 | AS67: =AQ67 -> 0 | AT67: =AR67 -> 0 | AU67: =K67+AC67+AO67 -> 0.06 | AV67: =L67+AD67+AP67+AT67 -> 1.3653692 | AW67: - | AX67: =IF(AW67="●",AV67,0) -> 0
C68: 56 | D68: 品位確認・評価 | E68: 現物確認、客先個別試験 | F68: 不定期（頻度低） | G68: 0.01 | H68: =$H$12/$G$12*G68 -> 1.8075 | K68: =G68+I68 -> 0.01 | L68: =H68+J68 -> 1.8075 | M68: 0.04 | N68: =N$12/M$12*M68 -> 0.91024615 | O68: 0.01 | P68: =P$12/O$12*O68 -> 0.22756154 | Q68: 0.01 | R68: =R$12/Q$12*Q68 -> 0.22756154 | S68: 0.01 | T68: =T$12/S$12*S68 -> 0.22756154 | U68: 0.01 | V68: =V$12/U$12*U68 -> 0.22756154 | W68: 0.01 | X68: =X$12/W$12*W68 -> 0.22756154 | Y68: 0.01 | Z68: =Z$12/Y$12*Y68 -> 0.22756154 | AA68: 0.02 | AB68: =AB$12/AA$12*AA68 -> 0.45512308 | AC68: =M68+O68+Q68+S68+U68+W68+Y68+AA68 -> 0.12 | AD68: =N68+P68+R68+T68+V68+X68+Z68+AB68 -> 2.7307385 | AF68: =AF$12/AE$12*AE68 -> 0 | AH68: =AH$12/AG$12*AG68 -> 0 | AJ68: =AJ$12/AI$12*AI68 -> 0 | AL68: =AL$12/AK$12*AK68 -> 0 | AN68: =AN$12/AM$12*AM68 -> 0 | AO68: =AE68+AG68+AK68+AM68+AI68 -> 0 | AP68: =AF68+AH68+AL68+AN68+AJ68 -> 0 | AS68: =AQ68 -> 0 | AT68: =AR68 -> 0 | AU68: =K68+AC68+AO68 -> 0.13 | AV68: =L68+AD68+AP68+AT68 -> 4.5382385 | AW68: - | AX68: =IF(AW68="●",AV68,0) -> 0
B69: 生産 | C69: 57 | D69: 仕様確認 | E69: TIとの量産品の仕様確認 | F69: 日次 | H69: =$H$12/$G$12*G69 -> 0 | K69: =G69+I69 -> 0 | L69: =H69+J69 -> 0 | N69: =N$12/M$12*M69 -> 0 | P69: =P$12/O$12*O69 -> 0 | R69: =R$12/Q$12*Q69 -> 0 | T69: =T$12/S$12*S69 -> 0 | V69: =V$12/U$12*U69 -> 0 | X69: =X$12/W$12*W69 -> 0 | Z69: =Z$12/Y$12*Y69 -> 0 | AA69: 0.03 | AB69: =AB$12/AA$12*AA69 -> 0.68268462 | AC69: =M69+O69+Q69+S69+U69+W69+Y69+AA69 -> 0.03 | AD69: =N69+P69+R69+T69+V69+X69+Z69+AB69 -> 0.68268462 | AF69: =AF$12/AE$12*AE69 -> 0 | AG69: 0.07 | AH69: =AH$12/AG$12*AG69 -> 1.5929308 | AI69: 0.07 | AJ69: =AJ$12/AI$12*AI69 -> 1.5929308 | AK69: 0.1 | AL69: =AL$12/AK$12*AK69 -> 2.2756154 | AM69: 0.07 | AN69: =AN$12/AM$12*AM69 -> 1.5929308 | AO69: =AE69+AG69+AK69+AM69+AI69 -> 0.31 | AP69: =AF69+AH69+AL69+AN69+AJ69 -> 7.0544077 | AS69: =AQ69 -> 0 | AT69: =AR69 -> 0 | AU69: =K69+AC69+AO69 -> 0.34 | AV69: =L69+AD69+AP69+AT69 -> 7.7370923 | AW69: - | AX69: =IF(AW69="●",AV69,0) -> 0
C70: 58 | D70: 資材不足確認 | E70: 不足資材を確認してTIへ連絡する | F70: 日次 | H70: =$H$12/$G$12*G70 -> 0 | K70: =G70+I70 -> 0 | L70: =H70+J70 -> 0 | N70: =N$12/M$12*M70 -> 0 | O70: 0.1 | P70: =P$12/O$12*O70 -> 2.2756154 | Q70: 0.1 | R70: =R$12/Q$12*Q70 -> 2.2756154 | S70: 0.1 | T70: =T$12/S$12*S70 -> 2.2756154 | U70: 0.1 | V70: =V$12/U$12*U70 -> 2.2756154 | W70: 0.15 | X70: =X$12/W$12*W70 -> 3.4134231 | Y70: 0.05 | Z70: =Z$12/Y$12*Y70 -> 1.1378077 | AA70: 0.03 | AB70: =AB$12/AA$12*AA70 -> 0.68268462 | AC70: =M70+O70+Q70+S70+U70+W70+Y70+AA70 -> 0.63 | AD70: =N70+P70+R70+T70+V70+X70+Z70+AB70 -> 14.336377 | AF70: =AF$12/AE$12*AE70 -> 0 | AH70: =AH$12/AG$12*AG70 -> 0 | AJ70: =AJ$12/AI$12*AI70 -> 0 | AL70: =AL$12/AK$12*AK70 -> 0 | AN70: =AN$12/AM$12*AM70 -> 0 | AO70: =AE70+AG70+AK70+AM70+AI70 -> 0 | AP70: =AF70+AH70+AL70+AN70+AJ70 -> 0 | AS70: =AQ70 -> 0 | AT70: =AR70 -> 0 | AU70: =K70+AC70+AO70 -> 0.63 | AV70: =L70+AD70+AP70+AT70 -> 14.336377 | AW70: ● | AX70: =IF(AW70="●",AV70,0) -> 14.336377
C71: 59 | D71: 縫製指導 | E71: 現場での縫製指導 | F71: 日次 | H71: =$H$12/$G$12*G71 -> 0 | K71: =G71+I71 -> 0 | L71: =H71+J71 -> 0 | N71: =N$12/M$12*M71 -> 0 | P71: =P$12/O$12*O71 -> 0 | R71: =R$12/Q$12*Q71 -> 0 | T71: =T$12/S$12*S71 -> 0 | V71: =V$12/U$12*U71 -> 0 | X71: =X$12/W$12*W71 -> 0 | Z71: =Z$12/Y$12*Y71 -> 0 | AA71: 0.02 | AB71: =AB$12/AA$12*AA71 -> 0.45512308 | AC71: =M71+O71+Q71+S71+U71+W71+Y71+AA71 -> 0.02 | AD71: =N71+P71+R71+T71+V71+X71+Z71+AB71 -> 0.45512308 | AF71: =AF$12/AE$12*AE71 -> 0 | AG71: 0.05 | AH71: =AH$12/AG$12*AG71 -> 1.1378077 | AI71: 0.05 | AJ71: =AJ$12/AI$12*AI71 -> 1.1378077 | AK71: 0.1 | AL71: =AL$12/AK$12*AK71 -> 2.2756154 | AM71: 0.08 | AN71: =AN$12/AM$12*AM71 -> 1.8204923 | AO71: =AE71+AG71+AK71+AM71+AI71 -> 0.28 | AP71: =AF71+AH71+AL71+AN71+AJ71 -> 6.3717231 | AS71: =AQ71 -> 0 | AT71: =AR71 -> 0 | AU71: =K71+AC71+AO71 -> 0.3 | AV71: =L71+AD71+AP71+AT71 -> 6.8268462 | AW71: - | AX71: =IF(AW71="●",AV71,0) -> 0
C72: 60 | D72: シーム・溶着指導 | E72: 現場での縫製指導 | F72: 日次 | H72: =$H$12/$G$12*G72 -> 0 | K72: =G72+I72 -> 0 | L72: =H72+J72 -> 0 | N72: =N$12/M$12*M72 -> 0 | P72: =P$12/O$12*O72 -> 0 | R72: =R$12/Q$12*Q72 -> 0 | T72: =T$12/S$12*S72 -> 0 | V72: =V$12/U$12*U72 -> 0 | X72: =X$12/W$12*W72 -> 0 | Z72: =Z$12/Y$12*Y72 -> 0 | AB72: =AB$12/AA$12*AA72 -> 0 | AC72: =M72+O72+Q72+S72+U72+W72+Y72+AA72 -> 0 | AD72: =N72+P72+R72+T72+V72+X72+Z72+AB72 -> 0 | AF72: =AF$12/AE$12*AE72 -> 0 | AG72: 0.03 | AH72: =AH$12/AG$12*AG72 -> 0.68268462 | AI72: 0.03 | AJ72: =AJ$12/AI$12*AI72 -> 0.68268462 | AL72: =AL$12/AK$12*AK72 -> 0 | AN72: =AN$12/AM$12*AM72 -> 0 | AO72: =AE72+AG72+AK72+AM72+AI72 -> 0.06 | AP72: =AF72+AH72+AL72+AN72+AJ72 -> 1.3653692 | AS72: =AQ72 -> 0 | AT72: =AR72 -> 0 | AU72: =K72+AC72+AO72 -> 0.06 | AV72: =L72+AD72+AP72+AT72 -> 1.3653692 | AW72: - | AX72: =IF(AW72="●",AV72,0) -> 0
C73: 61 | D73: 納期管理 | E73: 生産日報、進捗の確認 | F73: 日次 | G73: 0.1 | H73: =$H$12/$G$12*G73 -> 18.075 | K73: =G73+I73 -> 0.1 | L73: =H73+J73 -> 18.075 | M73: 0.1 | N73: =N$12/M$12*M73 -> 2.2756154 | P73: =P$12/O$12*O73 -> 0 | R73: =R$12/Q$12*Q73 -> 0 | T73: =T$12/S$12*S73 -> 0 | V73: =V$12/U$12*U73 -> 0 | X73: =X$12/W$12*W73 -> 0 | Z73: =Z$12/Y$12*Y73 -> 0 | AB73: =AB$12/AA$12*AA73 -> 0 | AC73: =M73+O73+Q73+S73+U73+W73+Y73+AA73 -> 0.1 | AD73: =N73+P73+R73+T73+V73+X73+Z73+AB73 -> 2.2756154 | AF73: =AF$12/AE$12*AE73 -> 0 | AH73: =AH$12/AG$12*AG73 -> 0 | AJ73: =AJ$12/AI$12*AI73 -> 0 | AL73: =AL$12/AK$12*AK73 -> 0 | AN73: =AN$12/AM$12*AM73 -> 0 | AO73: =AE73+AG73+AK73+AM73+AI73 -> 0 | AP73: =AF73+AH73+AL73+AN73+AJ73 -> 0 | AS73: =AQ73 -> 0 | AT73: =AR73 -> 0 | AU73: =K73+AC73+AO73 -> 0.2 | AV73: =L73+AD73+AP73+AT73 -> 20.350615 | AW73: - | AX73: =IF(AW73="●",AV73,0) -> 0
C74: 62 | D74: トラブルシュート | E74: 各種トラブル対応(段取り、計画、工程、品質) | F74: 不定期（頻度高） | G74: 0.02 | H74: =$H$12/$G$12*G74 -> 3.615 | K74: =G74+I74 -> 0.02 | L74: =H74+J74 -> 3.615 | M74: 0.02 | N74: =N$12/M$12*M74 -> 0.45512308 | P74: =P$12/O$12*O74 -> 0 | R74: =R$12/Q$12*Q74 -> 0 | T74: =T$12/S$12*S74 -> 0 | V74: =V$12/U$12*U74 -> 0 | X74: =X$12/W$12*W74 -> 0 | Z74: =Z$12/Y$12*Y74 -> 0 | AB74: =AB$12/AA$12*AA74 -> 0 | AC74: =M74+O74+Q74+S74+U74+W74+Y74+AA74 -> 0.02 | AD74: =N74+P74+R74+T74+V74+X74+Z74+AB74 -> 0.45512308 | AF74: =AF$12/AE$12*AE74 -> 0 | AG74: 0.05 | AH74: =AH$12/AG$12*AG74 -> 1.1378077 | AI74: 0.05 | AJ74: =AJ$12/AI$12*AI74 -> 1.1378077 | AK74: 0.18 | AL74: =AL$12/AK$12*AK74 -> 4.0961077 | AM74: 0.17 | AN74: =AN$12/AM$12*AM74 -> 3.8685462 | AO74: =AE74+AG74+AK74+AM74+AI74 -> 0.45 | AP74: =AF74+AH74+AL74+AN74+AJ74 -> 10.240269 | AS74: =AQ74 -> 0 | AT74: =AR74 -> 0 | AU74: =K74+AC74+AO74 -> 0.49 | AV74: =L74+AD74+AP74+AT74 -> 14.310392 | AW74: - | AX74: =IF(AW74="●",AV74,0) -> 0
C75: 63 | D75: 生産結果記録 | E75: 問題・対策内容の記録と類似生産への水平展開 | F75: 不定期（頻度中） | G75: 0.01 | H75: =$H$12/$G$12*G75 -> 1.8075 | K75: =G75+I75 -> 0.01 | L75: =H75+J75 -> 1.8075 | M75: 0.01 | N75: =N$12/M$12*M75 -> 0.22756154 | P75: =P$12/O$12*O75 -> 0 | R75: =R$12/Q$12*Q75 -> 0 | T75: =T$12/S$12*S75 -> 0 | V75: =V$12/U$12*U75 -> 0 | X75: =X$12/W$12*W75 -> 0 | Z75: =Z$12/Y$12*Y75 -> 0 | AA75: 0.02 | AB75: =AB$12/AA$12*AA75 -> 0.45512308 | AC75: =M75+O75+Q75+S75+U75+W75+Y75+AA75 -> 0.03 | AD75: =N75+P75+R75+T75+V75+X75+Z75+AB75 -> 0.68268462 | AF75: =AF$12/AE$12*AE75 -> 0 | AG75: 0.03 | AH75: =AH$12/AG$12*AG75 -> 0.68268462 | AI75: 0.03 | AJ75: =AJ$12/AI$12*AI75 -> 0.68268462 | AK75: 0.05 | AL75: =AL$12/AK$12*AK75 -> 1.1378077 | AM75: 0.06 | AN75: =AN$12/AM$12*AM75 -> 1.3653692 | AO75: =AE75+AG75+AK75+AM75+AI75 -> 0.17 | AP75: =AF75+AH75+AL75+AN75+AJ75 -> 3.8685462 | AS75: =AQ75 -> 0 | AT75: =AR75 -> 0 | AU75: =K75+AC75+AO75 -> 0.21 | AV75: =L75+AD75+AP75+AT75 -> 6.3587308 | AW75: - | AX75: =IF(AW75="●",AV75,0) -> 0
C76: 64 | D76: 技術者MTG | E76: 工場の投入前MTGに参加し注意事項の確認 | F76: 日次 | H76: =$H$12/$G$12*G76 -> 0 | K76: =G76+I76 -> 0 | L76: =H76+J76 -> 0 | N76: =N$12/M$12*M76 -> 0 | P76: =P$12/O$12*O76 -> 0 | R76: =R$12/Q$12*Q76 -> 0 | T76: =T$12/S$12*S76 -> 0 | V76: =V$12/U$12*U76 -> 0 | X76: =X$12/W$12*W76 -> 0 | Z76: =Z$12/Y$12*Y76 -> 0 | AB76: =AB$12/AA$12*AA76 -> 0 | AC76: =M76+O76+Q76+S76+U76+W76+Y76+AA76 -> 0 | AD76: =N76+P76+R76+T76+V76+X76+Z76+AB76 -> 0 | AF76: =AF$12/AE$12*AE76 -> 0 | AG76: 0.03 | AH76: =AH$12/AG$12*AG76 -> 0.68268462 | AI76: 0.03 | AJ76: =AJ$12/AI$12*AI76 -> 0.68268462 | AK76: 0.05 | AL76: =AL$12/AK$12*AK76 -> 1.1378077 | AM76: 0.1 | AN76: =AN$12/AM$12*AM76 -> 2.2756154 | AO76: =AE76+AG76+AK76+AM76+AI76 -> 0.21 | AP76: =AF76+AH76+AL76+AN76+AJ76 -> 4.7787923 | AS76: =AQ76 -> 0 | AT76: =AR76 -> 0 | AU76: =K76+AC76+AO76 -> 0.21 | AV76: =L76+AD76+AP76+AT76 -> 4.7787923 | AW76: - | AX76: =IF(AW76="●",AV76,0) -> 0
B77: 検査 | C77: 65 | D77: 検査目合わせ | E77: 投入後、最初に上がった製品の基準目合わせ | F77: 不定期（頻度高） | H77: =$H$12/$G$12*G77 -> 0 | K77: =G77+I77 -> 0 | L77: =H77+J77 -> 0 | N77: =N$12/M$12*M77 -> 0 | P77: =P$12/O$12*O77 -> 0 | R77: =R$12/Q$12*Q77 -> 0 | T77: =T$12/S$12*S77 -> 0 | V77: =V$12/U$12*U77 -> 0 | X77: =X$12/W$12*W77 -> 0 | Z77: =Z$12/Y$12*Y77 -> 0 | AA77: 0.02 | AB77: =AB$12/AA$12*AA77 -> 0.45512308 | AC77: =M77+O77+Q77+S77+U77+W77+Y77+AA77 -> 0.02 | AD77: =N77+P77+R77+T77+V77+X77+Z77+AB77 -> 0.45512308 | AF77: =AF$12/AE$12*AE77 -> 0 | AG77: 0.05 | AH77: =AH$12/AG$12*AG77 -> 1.1378077 | AI77: 0.05 | AJ77: =AJ$12/AI$12*AI77 -> 1.1378077 | AK77: 0.07 | AL77: =AL$12/AK$12*AK77 -> 1.5929308 | AM77: 0.05 | AN77: =AN$12/AM$12*AM77 -> 1.1378077 | AO77: =AE77+AG77+AK77+AM77+AI77 -> 0.22 | AP77: =AF77+AH77+AL77+AN77+AJ77 -> 5.0063538 | AS77: =AQ77 -> 0 | AT77: =AR77 -> 0 | AU77: =K77+AC77+AO77 -> 0.24 | AV77: =L77+AD77+AP77+AT77 -> 5.4614769 | AW77: - | AX77: =IF(AW77="●",AV77,0) -> 0
B78: ※3 | C78: 66 | D78: 一次検査 | E78: ライン上がり製品の縫製検査 | F78: 日次 | H78: =$H$12/$G$12*G78 -> 0 | K78: =G78+I78 -> 0 | L78: =H78+J78 -> 0 | N78: =N$12/M$12*M78 -> 0 | P78: =P$12/O$12*O78 -> 0 | R78: =R$12/Q$12*Q78 -> 0 | T78: =T$12/S$12*S78 -> 0 | V78: =V$12/U$12*U78 -> 0 | X78: =X$12/W$12*W78 -> 0 | Z78: =Z$12/Y$12*Y78 -> 0 | AA78: 0.02 | AB78: =AB$12/AA$12*AA78 -> 0.45512308 | AC78: =M78+O78+Q78+S78+U78+W78+Y78+AA78 -> 0.02 | AD78: =N78+P78+R78+T78+V78+X78+Z78+AB78 -> 0.45512308 | AF78: =AF$12/AE$12*AE78 -> 0 | AG78: 0.05 | AH78: =AH$12/AG$12*AG78 -> 1.1378077 | AI78: 0.05 | AJ78: =AJ$12/AI$12*AI78 -> 1.1378077 | AK78: 0.09 | AL78: =AL$12/AK$12*AK78 -> 2.0480538 | AM78: 0.11 | AN78: =AN$12/AM$12*AM78 -> 2.5031769 | AO78: =AE78+AG78+AK78+AM78+AI78 -> 0.3 | AP78: =AF78+AH78+AL78+AN78+AJ78 -> 6.8268462 | AS78: =AQ78 -> 0 | AT78: =AR78 -> 0 | AU78: =K78+AC78+AO78 -> 0.32 | AV78: =L78+AD78+AP78+AT78 -> 7.2819692 | AW78: - | AX78: =IF(AW78="●",AV78,0) -> 0
C79: 67 | D79: 二次検査 | E79: 仕上げ製品の外観検査 | F79: 日次 | H79: =$H$12/$G$12*G79 -> 0 | K79: =G79+I79 -> 0 | L79: =H79+J79 -> 0 | N79: =N$12/M$12*M79 -> 0 | P79: =P$12/O$12*O79 -> 0 | R79: =R$12/Q$12*Q79 -> 0 | T79: =T$12/S$12*S79 -> 0 | V79: =V$12/U$12*U79 -> 0 | X79: =X$12/W$12*W79 -> 0 | Z79: =Z$12/Y$12*Y79 -> 0 | AA79: 0.02 | AB79: =AB$12/AA$12*AA79 -> 0.45512308 | AC79: =M79+O79+Q79+S79+U79+W79+Y79+AA79 -> 0.02 | AD79: =N79+P79+R79+T79+V79+X79+Z79+AB79 -> 0.45512308 | AF79: =AF$12/AE$12*AE79 -> 0 | AG79: 0.05 | AH79: =AH$12/AG$12*AG79 -> 1.1378077 | AI79: 0.05 | AJ79: =AJ$12/AI$12*AI79 -> 1.1378077 | AK79: 0.05 | AL79: =AL$12/AK$12*AK79 -> 1.1378077 | AM79: 0.05 | AN79: =AN$12/AM$12*AM79 -> 1.1378077 | AO79: =AE79+AG79+AK79+AM79+AI79 -> 0.2 | AP79: =AF79+AH79+AL79+AN79+AJ79 -> 4.5512308 | AS79: =AQ79 -> 0 | AT79: =AR79 -> 0 | AU79: =K79+AC79+AO79 -> 0.22 | AV79: =L79+AD79+AP79+AT79 -> 5.0063538 | AW79: - | AX79: =IF(AW79="●",AV79,0) -> 0
C80: 68 | D80: 出荷前検査 | E80: 工場検品後の製品の抜取チェック | F80: 日次 | H80: =$H$12/$G$12*G80 -> 0 | K80: =G80+I80 -> 0 | L80: =H80+J80 -> 0 | N80: =N$12/M$12*M80 -> 0 | P80: =P$12/O$12*O80 -> 0 | R80: =R$12/Q$12*Q80 -> 0 | T80: =T$12/S$12*S80 -> 0 | V80: =V$12/U$12*U80 -> 0 | X80: =X$12/W$12*W80 -> 0 | Z80: =Z$12/Y$12*Y80 -> 0 | AA80: 0.02 | AB80: =AB$12/AA$12*AA80 -> 0.45512308 | AC80: =M80+O80+Q80+S80+U80+W80+Y80+AA80 -> 0.02 | AD80: =N80+P80+R80+T80+V80+X80+Z80+AB80 -> 0.45512308 | AF80: =AF$12/AE$12*AE80 -> 0 | AG80: 0.05 | AH80: =AH$12/AG$12*AG80 -> 1.1378077 | AI80: 0.05 | AJ80: =AJ$12/AI$12*AI80 -> 1.1378077 | AK80: 0.03 | AL80: =AL$12/AK$12*AK80 -> 0.68268462 | AM80: 0.03 | AN80: =AN$12/AM$12*AM80 -> 0.68268462 | AO80: =AE80+AG80+AK80+AM80+AI80 -> 0.16 | AP80: =AF80+AH80+AL80+AN80+AJ80 -> 3.6409846 | AS80: =AQ80 -> 0 | AT80: =AR80 -> 0 | AU80: =K80+AC80+AO80 -> 0.18 | AV80: =L80+AD80+AP80+AT80 -> 4.0961077 | AW80: - | AX80: =IF(AW80="●",AV80,0) -> 0
C81: 69 | D81: 下札、ﾈｰﾑ確認 | E81: 下げ札、ネーム類の印字内容のチェック | F81: 日次 | H81: =$H$12/$G$12*G81 -> 0 | K81: =G81+I81 -> 0 | L81: =H81+J81 -> 0 | N81: =N$12/M$12*M81 -> 0 | O81: 0.01 | P81: =P$12/O$12*O81 -> 0.22756154 | Q81: 0.01 | R81: =R$12/Q$12*Q81 -> 0.22756154 | S81: 0.01 | T81: =T$12/S$12*S81 -> 0.22756154 | U81: 0.01 | V81: =V$12/U$12*U81 -> 0.22756154 | W81: 0.01 | X81: =X$12/W$12*W81 -> 0.22756154 | Y81: 0.01 | Z81: =Z$12/Y$12*Y81 -> 0.22756154 | AB81: =AB$12/AA$12*AA81 -> 0 | AC81: =M81+O81+Q81+S81+U81+W81+Y81+AA81 -> 0.06 | AD81: =N81+P81+R81+T81+V81+X81+Z81+AB81 -> 1.3653692 | AF81: =AF$12/AE$12*AE81 -> 0 | AH81: =AH$12/AG$12*AG81 -> 0 | AJ81: =AJ$12/AI$12*AI81 -> 0 | AL81: =AL$12/AK$12*AK81 -> 0 | AN81: =AN$12/AM$12*AM81 -> 0 | AO81: =AE81+AG81+AK81+AM81+AI81 -> 0 | AP81: =AF81+AH81+AL81+AN81+AJ81 -> 0 | AS81: =AQ81 -> 0 | AT81: =AR81 -> 0 | AU81: =K81+AC81+AO81 -> 0.06 | AV81: =L81+AD81+AP81+AT81 -> 1.3653692 | AW81: - | AX81: =IF(AW81="●",AV81,0) -> 0
C82: 70 | D82: 客先検査 | E82: 客先検査結果の工場連絡 | F82: 不定期（頻度高） | H82: =$H$12/$G$12*G82 -> 0 | K82: =G82+I82 -> 0 | L82: =H82+J82 -> 0 | N82: =N$12/M$12*M82 -> 0 | P82: =P$12/O$12*O82 -> 0 | R82: =R$12/Q$12*Q82 -> 0 | T82: =T$12/S$12*S82 -> 0 | V82: =V$12/U$12*U82 -> 0 | X82: =X$12/W$12*W82 -> 0 | Z82: =Z$12/Y$12*Y82 -> 0 | AA82: 0.05 | AB82: =AB$12/AA$12*AA82 -> 1.1378077 | AC82: =M82+O82+Q82+S82+U82+W82+Y82+AA82 -> 0.05 | AD82: =N82+P82+R82+T82+V82+X82+Z82+AB82 -> 1.1378077 | AF82: =AF$12/AE$12*AE82 -> 0 | AG82: 0.03 | AH82: =AH$12/AG$12*AG82 -> 0.68268462 | AI82: 0.03 | AJ82: =AJ$12/AI$12*AI82 -> 0.68268462 | AK82: 0.04 | AL82: =AL$12/AK$12*AK82 -> 0.91024615 | AM82: 0.04 | AN82: =AN$12/AM$12*AM82 -> 0.91024615 | AO82: =AE82+AG82+AK82+AM82+AI82 -> 0.14 | AP82: =AF82+AH82+AL82+AN82+AJ82 -> 3.1858615 | AS82: =AQ82 -> 0 | AT82: =AR82 -> 0 | AU82: =K82+AC82+AO82 -> 0.19 | AV82: =L82+AD82+AP82+AT82 -> 4.3236692 | AW82: - | AX82: =IF(AW82="●",AV82,0) -> 0
C83: 71 | D83: 機能検査 | E83: 耐水圧・シーム製品抜き取り検査チェック | F83: 不定期（頻度中） | H83: =$H$12/$G$12*G83 -> 0 | K83: =G83+I83 -> 0 | L83: =H83+J83 -> 0 | N83: =N$12/M$12*M83 -> 0 | P83: =P$12/O$12*O83 -> 0 | R83: =R$12/Q$12*Q83 -> 0 | T83: =T$12/S$12*S83 -> 0 | V83: =V$12/U$12*U83 -> 0 | X83: =X$12/W$12*W83 -> 0 | Z83: =Z$12/Y$12*Y83 -> 0 | AA83: 0.01 | AB83: =AB$12/AA$12*AA83 -> 0.22756154 | AC83: =M83+O83+Q83+S83+U83+W83+Y83+AA83 -> 0.01 | AD83: =N83+P83+R83+T83+V83+X83+Z83+AB83 -> 0.22756154 | AF83: =AF$12/AE$12*AE83 -> 0 | AG83: 0.03 | AH83: =AH$12/AG$12*AG83 -> 0.68268462 | AI83: 0.03 | AJ83: =AJ$12/AI$12*AI83 -> 0.68268462 | AK83: 0.04 | AL83: =AL$12/AK$12*AK83 -> 0.91024615 | AM83: 0.04 | AN83: =AN$12/AM$12*AM83 -> 0.91024615 | AO83: =AE83+AG83+AK83+AM83+AI83 -> 0.14 | AP83: =AF83+AH83+AL83+AN83+AJ83 -> 3.1858615 | AS83: =AQ83 -> 0 | AT83: =AR83 -> 0 | AU83: =K83+AC83+AO83 -> 0.15 | AV83: =L83+AD83+AP83+AT83 -> 3.4134231 | AW83: - | AX83: =IF(AW83="●",AV83,0) -> 0
C84: 72 | D84: 第三者検品 | E84: 外部検査機関との品質基準・日程調整 | F84: 不定期（頻度中） | G84: 0.01 | H84: =$H$12/$G$12*G84 -> 1.8075 | K84: =G84+I84 -> 0.01 | L84: =H84+J84 -> 1.8075 | M84: 0.05 | N84: =N$12/M$12*M84 -> 1.1378077 | O84: 0.01 | P84: =P$12/O$12*O84 -> 0.22756154 | Q84: 0.01 | R84: =R$12/Q$12*Q84 -> 0.22756154 | S84: 0.01 | T84: =T$12/S$12*S84 -> 0.22756154 | U84: 0.01 | V84: =V$12/U$12*U84 -> 0.22756154 | W84: 0.01 | X84: =X$12/W$12*W84 -> 0.22756154 | Y84: 0.01 | Z84: =Z$12/Y$12*Y84 -> 0.22756154 | AB84: =AB$12/AA$12*AA84 -> 0 | AC84: =M84+O84+Q84+S84+U84+W84+Y84+AA84 -> 0.11 | AD84: =N84+P84+R84+T84+V84+X84+Z84+AB84 -> 2.5031769 | AF84: =AF$12/AE$12*AE84 -> 0 | AH84: =AH$12/AG$12*AG84 -> 0 | AJ84: =AJ$12/AI$12*AI84 -> 0 | AL84: =AL$12/AK$12*AK84 -> 0 | AN84: =AN$12/AM$12*AM84 -> 0 | AO84: =AE84+AG84+AK84+AM84+AI84 -> 0 | AP84: =AF84+AH84+AL84+AN84+AJ84 -> 0 | AS84: =AQ84 -> 0 | AT84: =AR84 -> 0 | AU84: =K84+AC84+AO84 -> 0.12 | AV84: =L84+AD84+AP84+AT84 -> 4.3106769 | AW84: - | AX84: =IF(AW84="●",AV84,0) -> 0
A85: 出荷 | B85: 出荷 | C85: 73 | D85: P/L管理 | E85: 出荷後のP/Lチェックし、減産していれば補充確認する | F85: 日次 | H85: =$H$12/$G$12*G85 -> 0 | K85: =G85+I85 -> 0 | L85: =H85+J85 -> 0 | N85: =N$12/M$12*M85 -> 0 | P85: =P$12/O$12*O85 -> 0 | R85: =R$12/Q$12*Q85 -> 0 | T85: =T$12/S$12*S85 -> 0 | V85: =V$12/U$12*U85 -> 0 | X85: =X$12/W$12*W85 -> 0 | Y85: 0.05 | Z85: =Z$12/Y$12*Y85 -> 1.1378077 | AB85: =AB$12/AA$12*AA85 -> 0 | AC85: =M85+O85+Q85+S85+U85+W85+Y85+AA85 -> 0.05 | AD85: =N85+P85+R85+T85+V85+X85+Z85+AB85 -> 1.1378077 | AF85: =AF$12/AE$12*AE85 -> 0 | AH85: =AH$12/AG$12*AG85 -> 0 | AJ85: =AJ$12/AI$12*AI85 -> 0 | AL85: =AL$12/AK$12*AK85 -> 0 | AN85: =AN$12/AM$12*AM85 -> 0 | AO85: =AE85+AG85+AK85+AM85+AI85 -> 0 | AP85: =AF85+AH85+AL85+AN85+AJ85 -> 0 | AS85: =AQ85 -> 0 | AT85: =AR85 -> 0 | AU85: =K85+AC85+AO85 -> 0.05 | AV85: =L85+AD85+AP85+AT85 -> 1.1378077 | AW85: - | AX85: =IF(AW85="●",AV85,0) -> 0
C86: 74 | D86: 出荷連絡 | E86: 出荷情報確認、P/L・C/Oを連絡(BL、IVは工場からTIへ連絡） | F86: 日次 | H86: =$H$12/$G$12*G86 -> 0 | K86: =G86+I86 -> 0 | L86: =H86+J86 -> 0 | N86: =N$12/M$12*M86 -> 0 | P86: =P$12/O$12*O86 -> 0 | R86: =R$12/Q$12*Q86 -> 0 | T86: =T$12/S$12*S86 -> 0 | V86: =V$12/U$12*U86 -> 0 | X86: =X$12/W$12*W86 -> 0 | Y86: 0.05 | Z86: =Z$12/Y$12*Y86 -> 1.1378077 | AB86: =AB$12/AA$12*AA86 -> 0 | AC86: =M86+O86+Q86+S86+U86+W86+Y86+AA86 -> 0.05 | AD86: =N86+P86+R86+T86+V86+X86+Z86+AB86 -> 1.1378077 | AF86: =AF$12/AE$12*AE86 -> 0 | AH86: =AH$12/AG$12*AG86 -> 0 | AJ86: =AJ$12/AI$12*AI86 -> 0 | AL86: =AL$12/AK$12*AK86 -> 0 | AN86: =AN$12/AM$12*AM86 -> 0 | AO86: =AE86+AG86+AK86+AM86+AI86 -> 0 | AP86: =AF86+AH86+AL86+AN86+AJ86 -> 0 | AS86: =AQ86 -> 0 | AT86: =AR86 -> 0 | AU86: =K86+AC86+AO86 -> 0.05 | AV86: =L86+AD86+AP86+AT86 -> 1.1378077 | AW86: - | AX86: =IF(AW86="●",AV86,0) -> 0
C87: 75 | D87: 日程調整 | E87: 出荷日・数量の変更依頼を工場と調整 | F87: 週次 | G87: 0.01 | H87: =$H$12/$G$12*G87 -> 1.8075 | K87: =G87+I87 -> 0.01 | L87: =H87+J87 -> 1.8075 | M87: 0.05 | N87: =N$12/M$12*M87 -> 1.1378077 | P87: =P$12/O$12*O87 -> 0 | R87: =R$12/Q$12*Q87 -> 0 | T87: =T$12/S$12*S87 -> 0 | V87: =V$12/U$12*U87 -> 0 | X87: =X$12/W$12*W87 -> 0 | Z87: =Z$12/Y$12*Y87 -> 0 | AB87: =AB$12/AA$12*AA87 -> 0 | AC87: =M87+O87+Q87+S87+U87+W87+Y87+AA87 -> 0.05 | AD87: =N87+P87+R87+T87+V87+X87+Z87+AB87 -> 1.1378077 | AF87: =AF$12/AE$12*AE87 -> 0 | AH87: =AH$12/AG$12*AG87 -> 0 | AJ87: =AJ$12/AI$12*AI87 -> 0 | AL87: =AL$12/AK$12*AK87 -> 0 | AN87: =AN$12/AM$12*AM87 -> 0 | AO87: =AE87+AG87+AK87+AM87+AI87 -> 0 | AP87: =AF87+AH87+AL87+AN87+AJ87 -> 0 | AS87: =AQ87 -> 0 | AT87: =AR87 -> 0 | AU87: =K87+AC87+AO87 -> 0.06 | AV87: =L87+AD87+AP87+AT87 -> 2.9453077 | AW87: - | AX87: =IF(AW87="●",AV87,0) -> 0
A88: 工場管理 | B88: 備品管理 | C88: 76 | D88: 消耗品管理 | E88: 工場で必要な消耗品をTIへ発注し受渡伝票を作成する | F88: 不定期（頻度低） | H88: =$H$12/$G$12*G88 -> 0 | K88: =G88+I88 -> 0 | L88: =H88+J88 -> 0 | N88: =N$12/M$12*M88 -> 0 | P88: =P$12/O$12*O88 -> 0 | R88: =R$12/Q$12*Q88 -> 0 | T88: =T$12/S$12*S88 -> 0 | V88: =V$12/U$12*U88 -> 0 | X88: =X$12/W$12*W88 -> 0 | Z88: =Z$12/Y$12*Y88 -> 0 | AB88: =AB$12/AA$12*AA88 -> 0 | AC88: =M88+O88+Q88+S88+U88+W88+Y88+AA88 -> 0 | AD88: =N88+P88+R88+T88+V88+X88+Z88+AB88 -> 0 | AF88: =AF$12/AE$12*AE88 -> 0 | AH88: =AH$12/AG$12*AG88 -> 0 | AJ88: =AJ$12/AI$12*AI88 -> 0 | AL88: =AL$12/AK$12*AK88 -> 0 | AN88: =AN$12/AM$12*AM88 -> 0 | AO88: =AE88+AG88+AK88+AM88+AI88 -> 0 | AP88: =AF88+AH88+AL88+AN88+AJ88 -> 0 | AS88: =AQ88 -> 0 | AT88: =AR88 -> 0 | AU88: =K88+AC88+AO88 -> 0 | AV88: =L88+AD88+AP88+AT88 -> 0 | AW88: - | AX88: =IF(AW88="●",AV88,0) -> 0
B89: 労務管理 | C89: 77 | D89: 出勤簿管理 | E89: 月ごとの出勤状況をまとめる | F89: 月次 | H89: =$H$12/$G$12*G89 -> 0 | K89: =G89+I89 -> 0 | L89: =H89+J89 -> 0 | N89: =N$12/M$12*M89 -> 0 | P89: =P$12/O$12*O89 -> 0 | R89: =R$12/Q$12*Q89 -> 0 | T89: =T$12/S$12*S89 -> 0 | V89: =V$12/U$12*U89 -> 0 | X89: =X$12/W$12*W89 -> 0 | Z89: =Z$12/Y$12*Y89 -> 0 | AB89: =AB$12/AA$12*AA89 -> 0 | AC89: =M89+O89+Q89+S89+U89+W89+Y89+AA89 -> 0 | AD89: =N89+P89+R89+T89+V89+X89+Z89+AB89 -> 0 | AF89: =AF$12/AE$12*AE89 -> 0 | AH89: =AH$12/AG$12*AG89 -> 0 | AJ89: =AJ$12/AI$12*AI89 -> 0 | AL89: =AL$12/AK$12*AK89 -> 0 | AN89: =AN$12/AM$12*AM89 -> 0 | AO89: =AE89+AG89+AK89+AM89+AI89 -> 0 | AP89: =AF89+AH89+AL89+AN89+AJ89 -> 0 | AS89: =AQ89 -> 0 | AT89: =AR89 -> 0 | AU89: =K89+AC89+AO89 -> 0 | AV89: =L89+AD89+AP89+AT89 -> 0 | AW89: - | AX89: =IF(AW89="●",AV89,0) -> 0
A90: その他 | B90: 日次作業 | C90: 78 | D90: 業務日報 | E90: 当日の行内容をTI東京へ報告 | F90: 日次 | G90: 0.05 | H90: =$H$12/$G$12*G90 -> 9.0375 | K90: =G90+I90 -> 0.05 | L90: =H90+J90 -> 9.0375 | M90: 0.01 | N90: =N$12/M$12*M90 -> 0.22756154 | O90: 0.01 | P90: =P$12/O$12*O90 -> 0.22756154 | Q90: 0.01 | R90: =R$12/Q$12*Q90 -> 0.22756154 | S90: 0.01 | T90: =T$12/S$12*S90 -> 0.22756154 | U90: 0.01 | V90: =V$12/U$12*U90 -> 0.22756154 | W90: 0.01 | X90: =X$12/W$12*W90 -> 0.22756154 | Y90: 0.01 | Z90: =Z$12/Y$12*Y90 -> 0.22756154 | AB90: =AB$12/AA$12*AA90 -> 0 | AC90: =M90+O90+Q90+S90+U90+W90+Y90+AA90 -> 0.07 | AD90: =N90+P90+R90+T90+V90+X90+Z90+AB90 -> 1.5929308 | AF90: =AF$12/AE$12*AE90 -> 0 | AH90: =AH$12/AG$12*AG90 -> 0 | AJ90: =AJ$12/AI$12*AI90 -> 0 | AL90: =AL$12/AK$12*AK90 -> 0 | AN90: =AN$12/AM$12*AM90 -> 0 | AO90: =AE90+AG90+AK90+AM90+AI90 -> 0 | AP90: =AF90+AH90+AL90+AN90+AJ90 -> 0 | AS90: =AQ90 -> 0 | AT90: =AR90 -> 0 | AU90: =K90+AC90+AO90 -> 0.12 | AV90: =L90+AD90+AP90+AT90 -> 10.630431 | AW90: - | AX90: =IF(AW90="●",AV90,0) -> 0
C91: 79 | D91: 進捗報告会 | E91: 前日の生産進捗・工員出欠を各工場長より確認 | F91: 日次 | G91: 0.02 | H91: =$H$12/$G$12*G91 -> 3.615 | K91: =G91+I91 -> 0.02 | L91: =H91+J91 -> 3.615 | M91: 0.05 | N91: =N$12/M$12*M91 -> 1.1378077 | O91: 0.01 | P91: =P$12/O$12*O91 -> 0.22756154 | Q91: 0.01 | R91: =R$12/Q$12*Q91 -> 0.22756154 | S91: 0.01 | T91: =T$12/S$12*S91 -> 0.22756154 | U91: 0.01 | V91: =V$12/U$12*U91 -> 0.22756154 | W91: 0.01 | X91: =X$12/W$12*W91 -> 0.22756154 | Y91: 0.01 | Z91: =Z$12/Y$12*Y91 -> 0.22756154 | AA91: 0.01 | AB91: =AB$12/AA$12*AA91 -> 0.22756154 | AC91: =M91+O91+Q91+S91+U91+W91+Y91+AA91 -> 0.12 | AD91: =N91+P91+R91+T91+V91+X91+Z91+AB91 -> 2.7307385 | AE91: 0.05 | AF91: =AF$12/AE$12*AE91 -> 1.1378077 | AG91: 0.02 | AH91: =AH$12/AG$12*AG91 -> 0.45512308 | AI91: 0.02 | AJ91: =AJ$12/AI$12*AI91 -> 0.45512308 | AK91: 0.06 | AL91: =AL$12/AK$12*AK91 -> 1.3653692 | AM91: 0.05 | AN91: =AN$12/AM$12*AM91 -> 1.1378077 | AO91: =AE91+AG91+AK91+AM91+AI91 -> 0.2 | AP91: =AF91+AH91+AL91+AN91+AJ91 -> 4.5512308 | AS91: =AQ91 -> 0 | AT91: =AR91 -> 0 | AU91: =K91+AC91+AO91 -> 0.34 | AV91: =L91+AD91+AP91+AT91 -> 10.896969 | AW91: - | AX91: =IF(AW91="●",AV91,0) -> 0
C92: 80 | D92: 技術MTG | E92: 工場技術・品管リーダーより前日のトピックスを確認 | F92: 日次 | H92: =$H$12/$G$12*G92 -> 0 | K92: =G92+I92 -> 0 | L92: =H92+J92 -> 0 | N92: =N$12/M$12*M92 -> 0 | P92: =P$12/O$12*O92 -> 0 | R92: =R$12/Q$12*Q92 -> 0 | T92: =T$12/S$12*S92 -> 0 | V92: =V$12/U$12*U92 -> 0 | X92: =X$12/W$12*W92 -> 0 | Z92: =Z$12/Y$12*Y92 -> 0 | AA92: 0.15 | AB92: =AB$12/AA$12*AA92 -> 3.4134231 | AC92: =M92+O92+Q92+S92+U92+W92+Y92+AA92 -> 0.15 | AD92: =N92+P92+R92+T92+V92+X92+Z92+AB92 -> 3.4134231 | AE92: 0.05 | AF92: =AF$12/AE$12*AE92 -> 1.1378077 | AG92: 0.02 | AH92: =AH$12/AG$12*AG92 -> 0.45512308 | AI92: 0.02 | AJ92: =AJ$12/AI$12*AI92 -> 0.45512308 | AK92: 0.04 | AL92: =AL$12/AK$12*AK92 -> 0.91024615 | AM92: 0.06 | AN92: =AN$12/AM$12*AM92 -> 1.3653692 | AO92: =AE92+AG92+AK92+AM92+AI92 -> 0.19 | AP92: =AF92+AH92+AL92+AN92+AJ92 -> 4.3236692 | AS92: =AQ92 -> 0 | AT92: =AR92 -> 0 | AU92: =K92+AC92+AO92 -> 0.34 | AV92: =L92+AD92+AP92+AT92 -> 7.7370923 | AW92: - | AX92: =IF(AW92="●",AV92,0) -> 0
C93: 81 | D93: 工場ラウンド | E93: 工場報告内容確認 | F93: 日次 | G93: 0.01 | H93: =$H$12/$G$12*G93 -> 1.8075 | K93: =G93+I93 -> 0.01 | L93: =H93+J93 -> 1.8075 | M93: 0.01 | N93: =N$12/M$12*M93 -> 0.22756154 | P93: =P$12/O$12*O93 -> 0 | R93: =R$12/Q$12*Q93 -> 0 | T93: =T$12/S$12*S93 -> 0 | V93: =V$12/U$12*U93 -> 0 | X93: =X$12/W$12*W93 -> 0 | Z93: =Z$12/Y$12*Y93 -> 0 | AA93: 0.3 | AB93: =AB$12/AA$12*AA93 -> 6.8268462 | AC93: =M93+O93+Q93+S93+U93+W93+Y93+AA93 -> 0.31 | AD93: =N93+P93+R93+T93+V93+X93+Z93+AB93 -> 7.0544077 | AF93: =AF$12/AE$12*AE93 -> 0 | AH93: =AH$12/AG$12*AG93 -> 0 | AI93: 0.15 | AJ93: =AJ$12/AI$12*AI93 -> 3.4134231 | AL93: =AL$12/AK$12*AK93 -> 0 | AN93: =AN$12/AM$12*AM93 -> 0 | AO93: =AE93+AG93+AK93+AM93+AI93 -> 0.15 | AP93: =AF93+AH93+AL93+AN93+AJ93 -> 3.4134231 | AS93: =AQ93 -> 0 | AT93: =AR93 -> 0 | AU93: =K93+AC93+AO93 -> 0.47 | AV93: =L93+AD93+AP93+AT93 -> 12.275331 | AW93: - | AX93: =IF(AW93="●",AV93,0) -> 0
C94: 82 | D94: HCMより材料引き取り | E94: 材料引き取り方法確認 | F94: 日次 | H94: =$H$12/$G$12*G94 -> 0 | K94: =G94+I94 -> 0 | L94: =H94+J94 -> 0 | N94: =N$12/M$12*M94 -> 0 | P94: =P$12/O$12*O94 -> 0 | R94: =R$12/Q$12*Q94 -> 0 | T94: =T$12/S$12*S94 -> 0 | V94: =V$12/U$12*U94 -> 0 | X94: =X$12/W$12*W94 -> 0 | Y94: 0.06 | Z94: =Z$12/Y$12*Y94 -> 1.3653692 | AB94: =AB$12/AA$12*AA94 -> 0 | AC94: =M94+O94+Q94+S94+U94+W94+Y94+AA94 -> 0.06 | AD94: =N94+P94+R94+T94+V94+X94+Z94+AB94 -> 1.3653692 | AF94: =AF$12/AE$12*AE94 -> 0 | AH94: =AH$12/AG$12*AG94 -> 0 | AJ94: =AJ$12/AI$12*AI94 -> 0 | AL94: =AL$12/AK$12*AK94 -> 0 | AN94: =AN$12/AM$12*AM94 -> 0 | AO94: =AE94+AG94+AK94+AM94+AI94 -> 0 | AP94: =AF94+AH94+AL94+AN94+AJ94 -> 0 | AS94: =AQ94 -> 0 | AT94: =AR94 -> 0 | AU94: =K94+AC94+AO94 -> 0.06 | AV94: =L94+AD94+AP94+AT94 -> 1.3653692 | AW94: - | AX94: =IF(AW94="●",AV94,0) -> 0
B95: 週次作業 | C95: 83 | D95: 生産MTG | E95: 次週以降の生産計画を工場と調整・確認 | F95: 週次 | G95: 0.15 | H95: =$H$12/$G$12*G95 -> 27.1125 | K95: =G95+I95 -> 0.15 | L95: =H95+J95 -> 27.1125 | M95: 0.12 | N95: =N$12/M$12*M95 -> 2.7307385 | O95: 0.01 | P95: =P$12/O$12*O95 -> 0.22756154 | Q95: 0.01 | R95: =R$12/Q$12*Q95 -> 0.22756154 | S95: 0.01 | T95: =T$12/S$12*S95 -> 0.22756154 | U95: 0.01 | V95: =V$12/U$12*U95 -> 0.22756154 | W95: 0.01 | X95: =X$12/W$12*W95 -> 0.22756154 | Y95: 0.01 | Z95: =Z$12/Y$12*Y95 -> 0.22756154 | AB95: =AB$12/AA$12*AA95 -> 0 | AC95: =M95+O95+Q95+S95+U95+W95+Y95+AA95 -> 0.18 | AD95: =N95+P95+R95+T95+V95+X95+Z95+AB95 -> 4.0961077 | AF95: =AF$12/AE$12*AE95 -> 0 | AH95: =AH$12/AG$12*AG95 -> 0 | AJ95: =AJ$12/AI$12*AI95 -> 0 | AL95: =AL$12/AK$12*AK95 -> 0 | AN95: =AN$12/AM$12*AM95 -> 0 | AO95: =AE95+AG95+AK95+AM95+AI95 -> 0 | AP95: =AF95+AH95+AL95+AN95+AJ95 -> 0 | AS95: =AQ95 -> 0 | AT95: =AR95 -> 0 | AU95: =K95+AC95+AO95 -> 0.33 | AV95: =L95+AD95+AP95+AT95 -> 31.208608 | AW95: - | AX95: =IF(AW95="●",AV95,0) -> 0
C96: 84 | D96: サンプルMTG | E96: 2府先までのサンプル班計画を調整・確認 | F96: 週次 | H96: =$H$12/$G$12*G96 -> 0 | K96: =G96+I96 -> 0 | L96: =H96+J96 -> 0 | N96: =N$12/M$12*M96 -> 0 | O96: 0.01 | P96: =P$12/O$12*O96 -> 0.22756154 | Q96: 0.01 | R96: =R$12/Q$12*Q96 -> 0.22756154 | S96: 0.01 | T96: =T$12/S$12*S96 -> 0.22756154 | U96: 0.01 | V96: =V$12/U$12*U96 -> 0.22756154 | W96: 0.01 | X96: =X$12/W$12*W96 -> 0.22756154 | Y96: 0.01 | Z96: =Z$12/Y$12*Y96 -> 0.22756154 | AB96: =AB$12/AA$12*AA96 -> 0 | AC96: =M96+O96+Q96+S96+U96+W96+Y96+AA96 -> 0.06 | AD96: =N96+P96+R96+T96+V96+X96+Z96+AB96 -> 1.3653692 | AE96: 0.05 | AF96: =AF$12/AE$12*AE96 -> 1.1378077 | AH96: =AH$12/AG$12*AG96 -> 0 | AJ96: =AJ$12/AI$12*AI96 -> 0 | AL96: =AL$12/AK$12*AK96 -> 0 | AN96: =AN$12/AM$12*AM96 -> 0 | AO96: =AE96+AG96+AK96+AM96+AI96 -> 0.05 | AP96: =AF96+AH96+AL96+AN96+AJ96 -> 1.1378077 | AS96: =AQ96 -> 0 | AT96: =AR96 -> 0 | AU96: =K96+AC96+AO96 -> 0.11 | AV96: =L96+AD96+AP96+AT96 -> 2.5031769 | AW96: - | AX96: =IF(AW96="●",AV96,0) -> 0
C97: 85 | D97: 業務週報 | E97: 当週の行内容をTI東京へ報告 | H97: =$H$12/$G$12*G97 -> 0 | K97: =G97+I97 -> 0 | L97: =H97+J97 -> 0 | M97: 0.01 | N97: =N$12/M$12*M97 -> 0.22756154 | O97: 0.01 | P97: =P$12/O$12*O97 -> 0.22756154 | Q97: 0.01 | R97: =R$12/Q$12*Q97 -> 0.22756154 | S97: 0.01 | T97: =T$12/S$12*S97 -> 0.22756154 | U97: 0.01 | V97: =V$12/U$12*U97 -> 0.22756154 | W97: 0.01 | X97: =X$12/W$12*W97 -> 0.22756154 | Y97: 0.01 | Z97: =Z$12/Y$12*Y97 -> 0.22756154 | AB97: =AB$12/AA$12*AA97 -> 0 | AC97: =M97+O97+Q97+S97+U97+W97+Y97+AA97 -> 0.07 | AD97: =N97+P97+R97+T97+V97+X97+Z97+AB97 -> 1.5929308 | AF97: =AF$12/AE$12*AE97 -> 0 | AH97: =AH$12/AG$12*AG97 -> 0 | AJ97: =AJ$12/AI$12*AI97 -> 0 | AL97: =AL$12/AK$12*AK97 -> 0 | AN97: =AN$12/AM$12*AM97 -> 0 | AO97: =AE97+AG97+AK97+AM97+AI97 -> 0 | AP97: =AF97+AH97+AL97+AN97+AJ97 -> 0 | AS97: =AQ97 -> 0 | AT97: =AR97 -> 0 | AU97: =K97+AC97+AO97 -> 0.07 | AV97: =L97+AD97+AP97+AT97 -> 1.5929308 | AW97: - | AX97: =IF(AW97="●",AV97,0) -> 0
C98: 86 | D98: 計画修正連絡 | E98: 生産管理課へ計画修正案・空きライン・問題点を連絡 | F98: 週次 | G98: 0.05 | H98: =$H$12/$G$12*G98 -> 9.0375 | K98: =G98+I98 -> 0.05 | L98: =H98+J98 -> 9.0375 | M98: 0.05 | N98: =N$12/M$12*M98 -> 1.1378077 | P98: =P$12/O$12*O98 -> 0 | R98: =R$12/Q$12*Q98 -> 0 | T98: =T$12/S$12*S98 -> 0 | V98: =V$12/U$12*U98 -> 0 | X98: =X$12/W$12*W98 -> 0 | Z98: =Z$12/Y$12*Y98 -> 0 | AB98: =AB$12/AA$12*AA98 -> 0 | AC98: =M98+O98+Q98+S98+U98+W98+Y98+AA98 -> 0.05 | AD98: =N98+P98+R98+T98+V98+X98+Z98+AB98 -> 1.1378077 | AF98: =AF$12/AE$12*AE98 -> 0 | AH98: =AH$12/AG$12*AG98 -> 0 | AJ98: =AJ$12/AI$12*AI98 -> 0 | AL98: =AL$12/AK$12*AK98 -> 0 | AN98: =AN$12/AM$12*AM98 -> 0 | AO98: =AE98+AG98+AK98+AM98+AI98 -> 0 | AP98: =AF98+AH98+AL98+AN98+AJ98 -> 0 | AS98: =AQ98 -> 0 | AT98: =AR98 -> 0 | AU98: =K98+AC98+AO98 -> 0.1 | AV98: =L98+AD98+AP98+AT98 -> 10.175308 | AW98: - | AX98: =IF(AW98="●",AV98,0) -> 0
C99: 87 | D99: プランテーブル修正 | E99: 生産管理課へ修正計画を盛り込んだプランテーブルを送付 | F99: 週次 | G99: 0.05 | H99: =$H$12/$G$12*G99 -> 9.0375 | K99: =G99+I99 -> 0.05 | L99: =H99+J99 -> 9.0375 | M99: 0.05 | N99: =N$12/M$12*M99 -> 1.1378077 | P99: =P$12/O$12*O99 -> 0 | R99: =R$12/Q$12*Q99 -> 0 | T99: =T$12/S$12*S99 -> 0 | V99: =V$12/U$12*U99 -> 0 | X99: =X$12/W$12*W99 -> 0 | Z99: =Z$12/Y$12*Y99 -> 0 | AB99: =AB$12/AA$12*AA99 -> 0 | AC99: =M99+O99+Q99+S99+U99+W99+Y99+AA99 -> 0.05 | AD99: =N99+P99+R99+T99+V99+X99+Z99+AB99 -> 1.1378077 | AF99: =AF$12/AE$12*AE99 -> 0 | AH99: =AH$12/AG$12*AG99 -> 0 | AJ99: =AJ$12/AI$12*AI99 -> 0 | AL99: =AL$12/AK$12*AK99 -> 0 | AN99: =AN$12/AM$12*AM99 -> 0 | AO99: =AE99+AG99+AK99+AM99+AI99 -> 0 | AP99: =AF99+AH99+AL99+AN99+AJ99 -> 0 | AS99: =AQ99 -> 0 | AT99: =AR99 -> 0 | AU99: =K99+AC99+AO99 -> 0.1 | AV99: =L99+AD99+AP99+AT99 -> 10.175308 | AW99: - | AX99: =IF(AW99="●",AV99,0) -> 0
C100: 88 | D100: Update修正内容確認 | E100: 計画修正されたUpdateとプランテーブルの照合 | F100: 週次 | G100: 0.05 | H100: =$H$12/$G$12*G100 -> 9.0375 | K100: =G100+I100 -> 0.05 | L100: =H100+J100 -> 9.0375 | M100: 0.04 | N100: =N$12/M$12*M100 -> 0.91024615 | P100: =P$12/O$12*O100 -> 0 | R100: =R$12/Q$12*Q100 -> 0 | T100: =T$12/S$12*S100 -> 0 | V100: =V$12/U$12*U100 -> 0 | X100: =X$12/W$12*W100 -> 0 | Z100: =Z$12/Y$12*Y100 -> 0 | AB100: =AB$12/AA$12*AA100 -> 0 | AC100: =M100+O100+Q100+S100+U100+W100+Y100+AA100 -> 0.04 | AD100: =N100+P100+R100+T100+V100+X100+Z100+AB100 -> 0.91024615 | AF100: =AF$12/AE$12*AE100 -> 0 | AH100: =AH$12/AG$12*AG100 -> 0 | AJ100: =AJ$12/AI$12*AI100 -> 0 | AL100: =AL$12/AK$12*AK100 -> 0 | AN100: =AN$12/AM$12*AM100 -> 0 | AO100: =AE100+AG100+AK100+AM100+AI100 -> 0 | AP100: =AF100+AH100+AL100+AN100+AJ100 -> 0 | AS100: =AQ100 -> 0 | AT100: =AR100 -> 0 | AU100: =K100+AC100+AO100 -> 0.09 | AV100: =L100+AD100+AP100+AT100 -> 9.9477462 | AW100: - | AX100: =IF(AW100="●",AV100,0) -> 0
...

Sheet 参考b_BTNB(2024年度) 
M1: 工数 | O1: 金額（千USD）※１ | AU1: 45320
A2: (予算ヒアリング補足資料からの編集版） | O2: 一人当たり | R2: 小計 | W2: =W3/11 -> 30.533636 | AV2: Toray International Vietnam Co., Ltd
G3: 日本人管理者 | M3: =K13 -> 1 | O3: 180.75 | R3: =M3*O3 -> 180.75 | W3: 335.87
G4: ナショナルスタッフ/管理グループ | M4: =Y13 -> 6 | O4: =W2 -> 30.533636 | R4: =M4*O4 -> 183.20182
A5: BTNB TIVNスタッフ業務分析表/2024年度業務委託料配分 | G5: ナショナルスタッフ/技術グループ | M5: =AM13 -> 5 | O5: =W2 -> 30.533636 | R5: =M5*O5 -> 152.66818 | U5: ※1：資料「(1)②TIVN業務委託費用配分」より抜粋
G6: TIVN本社ﾏﾈｰｼﾞﾒﾝﾄ※2 | M6: 1 | O6: =R6 -> 91.5 | R6: 91.5 | U6: ※2：出張アテンドや配車手配 | AC6: 91.5
G7: 合計 | M7: =SUM(M3:N6) -> 13 | O7: - | R7: =SUM(R3:T6) -> 608.12 | U7: → | V7: =R7/12 -> 50.676667 | W7: /月 | X7: ≒ | Y7: =V7*1000*135 -> 6841350 | AA7: /月(\135/USD換算）
AV8: 単位/千USD
L9: ＊進捗管理スタッフは日本営業の現地サポート役と位置付けており、来客対応から各々が全てをブランド括りで業務処理をしている、
G10: 日本人管理者 | M10: 管理グループ | AA10: 技術グループ | AO10: TIVN本社ﾏﾈｰｼﾞﾒﾝﾄ(出張･配車手配） | AS10: 総計
G11: Naito | K11: 計 | M11: Thong | O11: Tuong | Q11: Nhi | S11: T_Van | U11: Tuan | W11: Trinh | Y11: 計 | AA11: H_Van | AC11: Chau | AE11: Minh | AG11: Thu | AI11: Hoa | AK11: NEW STAFF | AM11: 計 | AO11: - | AQ11: 計
G12: 工数 | H12: 金額 | I12: 工数 | J12: 金額 | K12: 工数 | L12: 金額 | M12: 工数 | N12: 金額 | O12: 工数 | P12: 金額 | Q12: 工数 | R12: 金額 | S12: 工数 | T12: 金額 | U12: 工数 | V12: 金額 | W12: 工数 | X12: 金額 | Y12: 工数 | Z12: 金額 | AA12: 工数 | AB12: 金額 | AC12: 工数 | AD12: 金額 | AE12: 工数 | AF12: 金額 | AG12: 工数 | AH12: 金額 | AI12: 工数 | AJ12: 金額 | AK12: 工数 | AL12: 金額 | AM12: 工数 | AN12: 金額 | AO12: 工数 | AP12: 金額 | AQ12: 工数 | AR12: 金額 | AS12: 工数 | AT12: 金額 | AU12: 該否 | AV12: 課税価格参入金額
A13: 分類 | B13: 工程 | D13: 作業 | E13: 作業内容 | F13: 発生頻度 | G13: 1 | H13: =O3 -> 180.75 | K13: =G13+I13 -> 1 | L13: =H13+J13 -> 180.75 | M13: 1 | N13: =O4 -> 30.533636 | O13: 1 | P13: =O4 -> 30.533636 | Q13: 1 | R13: =O4 -> 30.533636 | S13: 1 | T13: =O4 -> 30.533636 | U13: 1 | V13: =O4 -> 30.533636 | W13: 1 | X13: =O4 -> 30.533636 | Y13: =M13+O13+Q13+S13+U13+W13 -> 6 | Z13: =N13+P13+R13+T13+V13+X13 -> 183.20182 | AA13: 1 | AB13: =O5 -> 30.533636 | AC13: 1 | AD13: =O5 -> 30.533636 | AE13: 1 | AF13: =O5 -> 30.533636 | AG13: 1 | AH13: =O5 -> 30.533636 | AI13: 1 | AJ13: =O5 -> 30.533636 | AK13: 1 | AL13: =O5 -> 30.533636 | AM13: =AA13+AC13+AE13+AG13+AK13 -> 5 | AN13: =AB13+AD13+AF13+AH13+AL13 -> 152.66818 | AO13: 1 | AP13: =O6 -> 91.5 | AQ13: =AO13 -> 1 | AR13: =AP13 -> 91.5 | AS13: =K13+Y13+AM13+AQ13 -> 13 | AT13: =L13+Z13+AN13+AR13 -> 608.12
A14: 総括 | B14: 契約管理 | C14: 1 | D14: Debit Note | E14: Debit Note確認、実績踏まえ更新交渉 | F14: 月次 | G14: 0.01 | H14: =H$13/G$13*G14 -> 1.8075 | K14: =G14+I14 -> 0.01 | L14: =H14+J14 -> 1.8075 | M14: 0.02 | N14: =N$13/M$13*M14 -> 0.61067273 | P14: =P$13/O$13*O14 -> 0 | R14: =R$13/Q$13*Q14 -> 0 | T14: =T$13/S$13*S14 -> 0 | V14: =V$13/U$13*U14 -> 0 | X14: =X$13/W$13*W14 -> 0 | Y14: =M14+O14+Q14+S14+U14+W14 -> 0.02 | Z14: =N14+P14+R14+T14+V14+X14 -> 0.61067273 | AB14: =AB$13/AA$13*AA14 -> 0 | AD14: =AD$13/AC$13*AC14 -> 0 | AF14: =AF$13/AE$13*AE14 -> 0 | AH14: =AH$13/AG$13*AG14 -> 0 | AJ14: =AJ$13/AI$13*AI14 -> 0 | AL14: =AL$13/AK$13*AK14 -> 0 | AM14: =AA14+AC14+AE14+AG14+AK14 -> 0 | AN14: =AB14+AD14+AF14+AH14+AL14 -> 0 | AP14: =AP$13/AO$13*AO14 -> 0 | AQ14: =AO14 -> 0 | AR14: =AP14 -> 0 | AS14: =K14+Y14+AM14+AQ14 -> 0.03 | AT14: =L14+Z14+AN14+AR14 -> 2.4181727 | AU14: - | AV14: =IF(AU14="●",AT14,0) -> 0 | AX14: ●
B15: 交渉 | C15: 2 | D15: 出勤管理 | E15: 月ごとの出勤状況をまとめる | F15: 月次 | G15: 0.01 | H15: =H$13/G$13*G15 -> 1.8075 | K15: =G15+I15 -> 0.01 | L15: =H15+J15 -> 1.8075 | M15: 0.02 | N15: =N$13/M$13*M15 -> 0.61067273 | P15: =P$13/O$13*O15 -> 0 | R15: =R$13/Q$13*Q15 -> 0 | T15: =T$13/S$13*S15 -> 0 | V15: =V$13/U$13*U15 -> 0 | X15: =X$13/W$13*W15 -> 0 | Y15: =M15+O15+Q15+S15+U15+W15 -> 0.02 | Z15: =N15+P15+R15+T15+V15+X15 -> 0.61067273 | AB15: =AB$13/AA$13*AA15 -> 0 | AD15: =AD$13/AC$13*AC15 -> 0 | AF15: =AF$13/AE$13*AE15 -> 0 | AH15: =AH$13/AG$13*AG15 -> 0 | AJ15: =AJ$13/AI$13*AI15 -> 0 | AL15: =AL$13/AK$13*AK15 -> 0 | AM15: =AA15+AC15+AE15+AG15+AK15 -> 0 | AN15: =AB15+AD15+AF15+AH15+AL15 -> 0 | AP15: =AP$13/AO$13*AO15 -> 0 | AQ15: =AO15 -> 0 | AR15: =AP15 -> 0 | AS15: =K15+Y15+AM15+AQ15 -> 0.03 | AT15: =L15+Z15+AN15+AR15 -> 2.4181727 | AU15: - | AV15: =IF(AU15="●",AT15,0) -> 0 | AX15: -
C16: 3 | D16: 期中変更対応 | E16: 工場からの業務内容変更要請対応 | F16: 不定期（頻度低） | G16: 0.01 | H16: =H$13/G$13*G16 -> 1.8075 | K16: =G16+I16 -> 0.01 | L16: =H16+J16 -> 1.8075 | M16: 0.02 | N16: =N$13/M$13*M16 -> 0.61067273 | O16: 0.01 | P16: =P$13/O$13*O16 -> 0.30533636 | Q16: 0.01 | R16: =R$13/Q$13*Q16 -> 0.30533636 | S16: 0.01 | T16: =T$13/S$13*S16 -> 0.30533636 | U16: 0.01 | V16: =V$13/U$13*U16 -> 0.30533636 | W16: 0.01 | X16: =X$13/W$13*W16 -> 0.30533636 | Y16: =M16+O16+Q16+S16+U16+W16 -> 0.07 | Z16: =N16+P16+R16+T16+V16+X16 -> 2.1373545 | AB16: =AB$13/AA$13*AA16 -> 0 | AD16: =AD$13/AC$13*AC16 -> 0 | AF16: =AF$13/AE$13*AE16 -> 0 | AH16: =AH$13/AG$13*AG16 -> 0 | AJ16: =AJ$13/AI$13*AI16 -> 0 | AL16: =AL$13/AK$13*AK16 -> 0 | AM16: =AA16+AC16+AE16+AG16+AK16 -> 0 | AN16: =AB16+AD16+AF16+AH16+AL16 -> 0 | AP16: =AP$13/AO$13*AO16 -> 0 | AQ16: =AO16 -> 0 | AR16: =AP16 -> 0 | AS16: =K16+Y16+AM16+AQ16 -> 0.08 | AT16: =L16+Z16+AN16+AR16 -> 3.9448545 | AU16: - | AV16: =IF(AU16="●",AT16,0) -> 0
C17: 4 | D17: 生産計画調整 | E17: 工場との生産計画調整・決定 | F17: 週次 | G17: 0.4 | H17: =H$13/G$13*G17 -> 72.3 | K17: =G17+I17 -> 0.4 | L17: =H17+J17 -> 72.3 | M17: 0.02 | N17: =N$13/M$13*M17 -> 0.61067273 | P17: =P$13/O$13*O17 -> 0 | R17: =R$13/Q$13*Q17 -> 0 | T17: =T$13/S$13*S17 -> 0 | V17: =V$13/U$13*U17 -> 0 | X17: =X$13/W$13*W17 -> 0 | Y17: =M17+O17+Q17+S17+U17+W17 -> 0.02 | Z17: =N17+P17+R17+T17+V17+X17 -> 0.61067273 | AB17: =AB$13/AA$13*AA17 -> 0 | AD17: =AD$13/AC$13*AC17 -> 0 | AF17: =AF$13/AE$13*AE17 -> 0 | AH17: =AH$13/AG$13*AG17 -> 0 | AJ17: =AJ$13/AI$13*AI17 -> 0 | AL17: =AL$13/AK$13*AK17 -> 0 | AM17: =AA17+AC17+AE17+AG17+AK17 -> 0 | AN17: =AB17+AD17+AF17+AH17+AL17 -> 0 | AP17: =AP$13/AO$13*AO17 -> 0 | AQ17: =AO17 -> 0 | AR17: =AP17 -> 0 | AS17: =K17+Y17+AM17+AQ17 -> 0.42 | AT17: =L17+Z17+AN17+AR17 -> 72.910673 | AU17: - | AV17: =IF(AU17="●",AT17,0) -> 0
C18: 5 | D18: Air代負担交渉 | F18: 不定期（頻度低） | H18: =H$13/G$13*G18 -> 0 | K18: =G18+I18 -> 0 | L18: =H18+J18 -> 0 | M18: 0.01 | N18: =N$13/M$13*M18 -> 0.30533636 | O18: 0.01 | P18: =P$13/O$13*O18 -> 0.30533636 | Q18: 0.01 | R18: =R$13/Q$13*Q18 -> 0.30533636 | S18: 0.01 | T18: =T$13/S$13*S18 -> 0.30533636 | U18: 0.01 | V18: =V$13/U$13*U18 -> 0.30533636 | W18: 0 | X18: =X$13/W$13*W18 -> 0 | Y18: =M18+O18+Q18+S18+U18+W18 -> 0.05 | Z18: =N18+P18+R18+T18+V18+X18 -> 1.5266818 | AB18: =AB$13/AA$13*AA18 -> 0 | AD18: =AD$13/AC$13*AC18 -> 0 | AF18: =AF$13/AE$13*AE18 -> 0 | AH18: =AH$13/AG$13*AG18 -> 0 | AJ18: =AJ$13/AI$13*AI18 -> 0 | AL18: =AL$13/AK$13*AK18 -> 0 | AM18: =AA18+AC18+AE18+AG18+AK18 -> 0 | AN18: =AB18+AD18+AF18+AH18+AL18 -> 0 | AP18: =AP$13/AO$13*AO18 -> 0 | AQ18: =AO18 -> 0 | AR18: =AP18 -> 0 | AS18: =K18+Y18+AM18+AQ18 -> 0.05 | AT18: =L18+Z18+AN18+AR18 -> 1.5266818 | AU18: - | AV18: =IF(AU18="●",AT18,0) -> 0
C19: 6 | D19: 外注工賃交渉 | F19: 不定期（頻度低） | H19: =H$13/G$13*G19 -> 0 | K19: =G19+I19 -> 0 | L19: =H19+J19 -> 0 | M19: 0.01 | N19: =N$13/M$13*M19 -> 0.30533636 | O19: 0.01 | P19: =P$13/O$13*O19 -> 0.30533636 | Q19: 0.01 | R19: =R$13/Q$13*Q19 -> 0.30533636 | S19: 0.01 | T19: =T$13/S$13*S19 -> 0.30533636 | U19: 0.01 | V19: =V$13/U$13*U19 -> 0.30533636 | W19: 0 | X19: =X$13/W$13*W19 -> 0 | Y19: =M19+O19+Q19+S19+U19+W19 -> 0.05 | Z19: =N19+P19+R19+T19+V19+X19 -> 1.5266818 | AB19: =AB$13/AA$13*AA19 -> 0 | AD19: =AD$13/AC$13*AC19 -> 0 | AF19: =AF$13/AE$13*AE19 -> 0 | AH19: =AH$13/AG$13*AG19 -> 0 | AJ19: =AJ$13/AI$13*AI19 -> 0 | AL19: =AL$13/AK$13*AK19 -> 0 | AM19: =AA19+AC19+AE19+AG19+AK19 -> 0 | AN19: =AB19+AD19+AF19+AH19+AL19 -> 0 | AP19: =AP$13/AO$13*AO19 -> 0 | AQ19: =AO19 -> 0 | AR19: =AP19 -> 0 | AS19: =K19+Y19+AM19+AQ19 -> 0.05 | AT19: =L19+Z19+AN19+AR19 -> 1.5266818 | AU19: - | AV19: =IF(AU19="●",AT19,0) -> 0
B20: AUDIT | C20: 7 | D20: 事前準備 | E20: 提出書類、工場指導 | F20: 不定期（頻度低） | H20: =H$13/G$13*G20 -> 0 | K20: =G20+I20 -> 0 | L20: =H20+J20 -> 0 | M20: 0.01 | N20: =N$13/M$13*M20 -> 0.30533636 | O20: 0.01 | P20: =P$13/O$13*O20 -> 0.30533636 | Q20: 0.01 | R20: =R$13/Q$13*Q20 -> 0.30533636 | S20: 0.01 | T20: =T$13/S$13*S20 -> 0.30533636 | U20: 0.01 | V20: =V$13/U$13*U20 -> 0.30533636 | W20: 0.01 | X20: =X$13/W$13*W20 -> 0.30533636 | Y20: =M20+O20+Q20+S20+U20+W20 -> 0.06 | Z20: =N20+P20+R20+T20+V20+X20 -> 1.8320182 | AB20: =AB$13/AA$13*AA20 -> 0 | AD20: =AD$13/AC$13*AC20 -> 0 | AF20: =AF$13/AE$13*AE20 -> 0 | AH20: =AH$13/AG$13*AG20 -> 0 | AJ20: =AJ$13/AI$13*AI20 -> 0 | AL20: =AL$13/AK$13*AK20 -> 0 | AM20: =AA20+AC20+AE20+AG20+AK20 -> 0 | AN20: =AB20+AD20+AF20+AH20+AL20 -> 0 | AP20: =AP$13/AO$13*AO20 -> 0 | AQ20: =AO20 -> 0 | AR20: =AP20 -> 0 | AS20: =K20+Y20+AM20+AQ20 -> 0.06 | AT20: =L20+Z20+AN20+AR20 -> 1.8320182 | AU20: - | AV20: =IF(AU20="●",AT20,0) -> 0
B21: ※１ | C21: 8 | D21: 当日対応 | F21: 不定期（頻度低） | H21: =H$13/G$13*G21 -> 0 | K21: =G21+I21 -> 0 | L21: =H21+J21 -> 0 | M21: 0.01 | N21: =N$13/M$13*M21 -> 0.30533636 | O21: 0.01 | P21: =P$13/O$13*O21 -> 0.30533636 | Q21: 0.01 | R21: =R$13/Q$13*Q21 -> 0.30533636 | S21: 0.01 | T21: =T$13/S$13*S21 -> 0.30533636 | U21: 0.01 | V21: =V$13/U$13*U21 -> 0.30533636 | W21: 0.01 | X21: =X$13/W$13*W21 -> 0.30533636 | Y21: =M21+O21+Q21+S21+U21+W21 -> 0.06 | Z21: =N21+P21+R21+T21+V21+X21 -> 1.8320182 | AB21: =AB$13/AA$13*AA21 -> 0 | AD21: =AD$13/AC$13*AC21 -> 0 | AF21: =AF$13/AE$13*AE21 -> 0 | AH21: =AH$13/AG$13*AG21 -> 0 | AJ21: =AJ$13/AI$13*AI21 -> 0 | AL21: =AL$13/AK$13*AK21 -> 0 | AM21: =AA21+AC21+AE21+AG21+AK21 -> 0 | AN21: =AB21+AD21+AF21+AH21+AL21 -> 0 | AP21: =AP$13/AO$13*AO21 -> 0 | AQ21: =AO21 -> 0 | AR21: =AP21 -> 0 | AS21: =K21+Y21+AM21+AQ21 -> 0.06 | AT21: =L21+Z21+AN21+AR21 -> 1.8320182 | AU21: - | AV21: =IF(AU21="●",AT21,0) -> 0
B22: 来客、 | C22: 9 | D22: 移動 | E22: 車、ホテル手配 | F22: 不定期（頻度高） | H22: =H$13/G$13*G22 -> 0 | K22: =G22+I22 -> 0 | L22: =H22+J22 -> 0 | M22: 0 | N22: =N$13/M$13*M22 -> 0 | O22: 0.01 | P22: =P$13/O$13*O22 -> 0.30533636 | Q22: 0.01 | R22: =R$13/Q$13*Q22 -> 0.30533636 | S22: 0.01 | T22: =T$13/S$13*S22 -> 0.30533636 | U22: 0.01 | V22: =V$13/U$13*U22 -> 0.30533636 | W22: 0.01 | X22: =X$13/W$13*W22 -> 0.30533636 | Y22: =M22+O22+Q22+S22+U22+W22 -> 0.05 | Z22: =N22+P22+R22+T22+V22+X22 -> 1.5266818 | AB22: =AB$13/AA$13*AA22 -> 0 | AD22: =AD$13/AC$13*AC22 -> 0 | AF22: =AF$13/AE$13*AE22 -> 0 | AH22: =AH$13/AG$13*AG22 -> 0 | AJ22: =AJ$13/AI$13*AI22 -> 0 | AL22: =AL$13/AK$13*AK22 -> 0 | AM22: =AA22+AC22+AE22+AG22+AK22 -> 0 | AN22: =AB22+AD22+AF22+AH22+AL22 -> 0 | AO22: 0.5 | AP22: =AP$13/AO$13*AO22 -> 45.75 | AQ22: =AO22 -> 0.5 | AR22: =AP22 -> 45.75 | AS22: =K22+Y22+AM22+AQ22 -> 0.55 | AT22: =L22+Z22+AN22+AR22 -> 47.276682 | AU22: - | AV22: =IF(AU22="●",AT22,0) -> 0
B23: 出張対応 | C23: 10 | D23: 工場アテンド | E23: 案内、食事 | F23: 不定期（頻度低） | H23: =H$13/G$13*G23 -> 0 | K23: =G23+I23 -> 0 | L23: =H23+J23 -> 0 | M23: 0.02 | N23: =N$13/M$13*M23 -> 0.61067273 | O23: 0.01 | P23: =P$13/O$13*O23 -> 0.30533636 | Q23: 0.01 | R23: =R$13/Q$13*Q23 -> 0.30533636 | S23: 0.01 | T23: =T$13/S$13*S23 -> 0.30533636 | U23: 0.01 | V23: =V$13/U$13*U23 -> 0.30533636 | W23: 0.01 | X23: =X$13/W$13*W23 -> 0.30533636 | Y23: =M23+O23+Q23+S23+U23+W23 -> 0.07 | Z23: =N23+P23+R23+T23+V23+X23 -> 2.1373545 | AB23: =AB$13/AA$13*AA23 -> 0 | AD23: =AD$13/AC$13*AC23 -> 0 | AF23: =AF$13/AE$13*AE23 -> 0 | AH23: =AH$13/AG$13*AG23 -> 0 | AJ23: =AJ$13/AI$13*AI23 -> 0 | AL23: =AL$13/AK$13*AK23 -> 0 | AM23: =AA23+AC23+AE23+AG23+AK23 -> 0 | AN23: =AB23+AD23+AF23+AH23+AL23 -> 0 | AO23: 0.5 | AP23: =AP$13/AO$13*AO23 -> 45.75 | AQ23: =AO23 -> 0.5 | AR23: =AP23 -> 45.75 | AS23: =K23+Y23+AM23+AQ23 -> 0.57 | AT23: =L23+Z23+AN23+AR23 -> 47.887355 | AU23: - | AV23: =IF(AU23="●",AT23,0) -> 0
C24: 11 | D24: 安全管理 | E24: 行程把握、緊急時対応 | F24: 不定期（頻度高） | H24: =H$13/G$13*G24 -> 0 | K24: =G24+I24 -> 0 | L24: =H24+J24 -> 0 | M24: 0.01 | N24: =N$13/M$13*M24 -> 0.30533636 | O24: 0.01 | P24: =P$13/O$13*O24 -> 0.30533636 | Q24: 0.01 | R24: =R$13/Q$13*Q24 -> 0.30533636 | S24: 0.01 | T24: =T$13/S$13*S24 -> 0.30533636 | U24: 0.01 | V24: =V$13/U$13*U24 -> 0.30533636 | W24: 0.01 | X24: =X$13/W$13*W24 -> 0.30533636 | Y24: =M24+O24+Q24+S24+U24+W24 -> 0.06 | Z24: =N24+P24+R24+T24+V24+X24 -> 1.8320182 | AB24: =AB$13/AA$13*AA24 -> 0 | AD24: =AD$13/AC$13*AC24 -> 0 | AF24: =AF$13/AE$13*AE24 -> 0 | AH24: =AH$13/AG$13*AG24 -> 0 | AJ24: =AJ$13/AI$13*AI24 -> 0 | AL24: =AL$13/AK$13*AK24 -> 0 | AM24: =AA24+AC24+AE24+AG24+AK24 -> 0 | AN24: =AB24+AD24+AF24+AH24+AL24 -> 0 | AP24: =AP$13/AO$13*AO24 -> 0 | AQ24: =AO24 -> 0 | AR24: =AP24 -> 0 | AS24: =K24+Y24+AM24+AQ24 -> 0.06 | AT24: =L24+Z24+AN24+AR24 -> 1.8320182 | AU24: - | AV24: =IF(AU24="●",AT24,0) -> 0
A25: 企画 | B25: 開発 | C25: 12 | D25: 商品開発 | E25: 新規素材、加工技術調査、サンプル試作 | F25: 不定期（頻度中） | H25: =H$13/G$13*G25 -> 0 | K25: =G25+I25 -> 0 | L25: =H25+J25 -> 0 | M25: 0 | N25: =N$13/M$13*M25 -> 0 | P25: =P$13/O$13*O25 -> 0 | R25: =R$13/Q$13*Q25 -> 0 | T25: =T$13/S$13*S25 -> 0 | V25: =V$13/U$13*U25 -> 0 | X25: =X$13/W$13*W25 -> 0 | Y25: =M25+O25+Q25+S25+U25+W25 -> 0 | Z25: =N25+P25+R25+T25+V25+X25 -> 0 | AB25: =AB$13/AA$13*AA25 -> 0 | AD25: =AD$13/AC$13*AC25 -> 0 | AF25: =AF$13/AE$13*AE25 -> 0 | AH25: =AH$13/AG$13*AG25 -> 0 | AJ25: =AJ$13/AI$13*AI25 -> 0 | AK25: 0.01 | AL25: =AL$13/AK$13*AK25 -> 0.30533636 | AM25: =AA25+AC25+AE25+AG25+AK25 -> 0.01 | AN25: =AB25+AD25+AF25+AH25+AL25 -> 0.30533636 | AP25: =AP$13/AO$13*AO25 -> 0 | AQ25: =AO25 -> 0 | AR25: =AP25 -> 0 | AS25: =K25+Y25+AM25+AQ25 -> 0.01 | AT25: =L25+Z25+AN25+AR25 -> 0.30533636 | AU25: ● | AV25: =IF(AU25="●",AT25,0) -> 0.30533636
C26: 13 | D26: 加工技術 | E26: パターン自動機設計、パターンシマ改善提案 | F26: 不定期（頻度中） | H26: =H$13/G$13*G26 -> 0 | K26: =G26+I26 -> 0 | L26: =H26+J26 -> 0 | N26: =N$13/M$13*M26 -> 0 | P26: =P$13/O$13*O26 -> 0 | R26: =R$13/Q$13*Q26 -> 0 | T26: =T$13/S$13*S26 -> 0 | V26: =V$13/U$13*U26 -> 0 | X26: =X$13/W$13*W26 -> 0 | Y26: =M26+O26+Q26+S26+U26+W26 -> 0 | Z26: =N26+P26+R26+T26+V26+X26 -> 0 | AA26: 0.01 | AB26: =AB$13/AA$13*AA26 -> 0.30533636 | AC26: 0.01 | AD26: =AD$13/AC$13*AC26 -> 0.30533636 | AE26: 0.01 | AF26: =AF$13/AE$13*AE26 -> 0.30533636 | AG26: 0.01 | AH26: =AH$13/AG$13*AG26 -> 0.30533636 | AJ26: =AJ$13/AI$13*AI26 -> 0 | AK26: 0.01 | AL26: =AL$13/AK$13*AK26 -> 0.30533636 | AM26: =AA26+AC26+AE26+AG26+AK26 -> 0.05 | AN26: =AB26+AD26+AF26+AH26+AL26 -> 1.5266818 | AP26: =AP$13/AO$13*AO26 -> 0 | AQ26: =AO26 -> 0 | AR26: =AP26 -> 0 | AS26: =K26+Y26+AM26+AQ26 -> 0.05 | AT26: =L26+Z26+AN26+AR26 -> 1.5266818 | AU26: ● | AV26: =IF(AU26="●",AT26,0) -> 1.5266818
C27: 14 | D27: 生産技術 | E27: 生産ラインのレイアウト設定提案 | F27: 不定期（頻度低） | H27: =H$13/G$13*G27 -> 0 | K27: =G27+I27 -> 0 | L27: =H27+J27 -> 0 | M27: 0.01 | N27: =N$13/M$13*M27 -> 0.30533636 | P27: =P$13/O$13*O27 -> 0 | R27: =R$13/Q$13*Q27 -> 0 | T27: =T$13/S$13*S27 -> 0 | V27: =V$13/U$13*U27 -> 0 | X27: =X$13/W$13*W27 -> 0 | Y27: =M27+O27+Q27+S27+U27+W27 -> 0.01 | Z27: =N27+P27+R27+T27+V27+X27 -> 0.30533636 | AA27: 0.01 | AB27: =AB$13/AA$13*AA27 -> 0.30533636 | AC27: 0.01 | AD27: =AD$13/AC$13*AC27 -> 0.30533636 | AE27: 0.01 | AF27: =AF$13/AE$13*AE27 -> 0.30533636 | AG27: 0.01 | AH27: =AH$13/AG$13*AG27 -> 0.30533636 | AJ27: =AJ$13/AI$13*AI27 -> 0 | AK27: 0.01 | AL27: =AL$13/AK$13*AK27 -> 0.30533636 | AM27: =AA27+AC27+AE27+AG27+AK27 -> 0.05 | AN27: =AB27+AD27+AF27+AH27+AL27 -> 1.5266818 | AP27: =AP$13/AO$13*AO27 -> 0 | AQ27: =AO27 -> 0 | AR27: =AP27 -> 0 | AS27: =K27+Y27+AM27+AQ27 -> 0.06 | AT27: =L27+Z27+AN27+AR27 -> 1.8320182 | AU27: ● | AV27: =IF(AU27="●",AT27,0) -> 1.8320182
C28: 15 | D28: 管理技術 | E28: 工程分析、進捗ばらつき、QC管理手法 | F28: 不定期（頻度中） | H28: =H$13/G$13*G28 -> 0 | K28: =G28+I28 -> 0 | L28: =H28+J28 -> 0 | M28: 0.01 | N28: =N$13/M$13*M28 -> 0.30533636 | P28: =P$13/O$13*O28 -> 0 | R28: =R$13/Q$13*Q28 -> 0 | T28: =T$13/S$13*S28 -> 0 | V28: =V$13/U$13*U28 -> 0 | X28: =X$13/W$13*W28 -> 0 | Y28: =M28+O28+Q28+S28+U28+W28 -> 0.01 | Z28: =N28+P28+R28+T28+V28+X28 -> 0.30533636 | AB28: =AB$13/AA$13*AA28 -> 0 | AD28: =AD$13/AC$13*AC28 -> 0 | AF28: =AF$13/AE$13*AE28 -> 0 | AH28: =AH$13/AG$13*AG28 -> 0 | AJ28: =AJ$13/AI$13*AI28 -> 0 | AK28: 0.07 | AL28: =AL$13/AK$13*AK28 -> 2.1373545 | AM28: =AA28+AC28+AE28+AG28+AK28 -> 0.07 | AN28: =AB28+AD28+AF28+AH28+AL28 -> 2.1373545 | AP28: =AP$13/AO$13*AO28 -> 0 | AQ28: =AO28 -> 0 | AR28: =AP28 -> 0 | AS28: =K28+Y28+AM28+AQ28 -> 0.08 | AT28: =L28+Z28+AN28+AR28 -> 2.4426909 | AU28: - | AV28: =IF(AU28="●",AT28,0) -> 0
C29: 16 | D29: 評価技術 | E29: 機能性評価、商品評価、物性試験等 | F29: 不定期（頻度中） | H29: =H$13/G$13*G29 -> 0 | K29: =G29+I29 -> 0 | L29: =H29+J29 -> 0 | M29: 0.01 | N29: =N$13/M$13*M29 -> 0.30533636 | P29: =P$13/O$13*O29 -> 0 | R29: =R$13/Q$13*Q29 -> 0 | T29: =T$13/S$13*S29 -> 0 | V29: =V$13/U$13*U29 -> 0 | X29: =X$13/W$13*W29 -> 0 | Y29: =M29+O29+Q29+S29+U29+W29 -> 0.01 | Z29: =N29+P29+R29+T29+V29+X29 -> 0.30533636 | AB29: =AB$13/AA$13*AA29 -> 0 | AD29: =AD$13/AC$13*AC29 -> 0 | AF29: =AF$13/AE$13*AE29 -> 0 | AH29: =AH$13/AG$13*AG29 -> 0 | AJ29: =AJ$13/AI$13*AI29 -> 0 | AK29: 0.01 | AL29: =AL$13/AK$13*AK29 -> 0.30533636 | AM29: =AA29+AC29+AE29+AG29+AK29 -> 0.01 | AN29: =AB29+AD29+AF29+AH29+AL29 -> 0.30533636 | AP29: =AP$13/AO$13*AO29 -> 0 | AQ29: =AO29 -> 0 | AR29: =AP29 -> 0 | AS29: =K29+Y29+AM29+AQ29 -> 0.02 | AT29: =L29+Z29+AN29+AR29 -> 0.61067273 | AU29: ● | AV29: =IF(AU29="●",AT29,0) -> 0.61067273
A30: 前段取り | B30: 生産計画 | C30: 17 | D30: プランテーブル | E30: 長期生産計画 | F30: 週次 | G30: 0.05 | H30: =H$13/G$13*G30 -> 9.0375 | K30: =G30+I30 -> 0.05 | L30: =H30+J30 -> 9.0375 | M30: 0.02 | N30: =N$13/M$13*M30 -> 0.61067273 | P30: =P$13/O$13*O30 -> 0 | R30: =R$13/Q$13*Q30 -> 0 | T30: =T$13/S$13*S30 -> 0 | V30: =V$13/U$13*U30 -> 0 | X30: =X$13/W$13*W30 -> 0 | Y30: =M30+O30+Q30+S30+U30+W30 -> 0.02 | Z30: =N30+P30+R30+T30+V30+X30 -> 0.61067273 | AB30: =AB$13/AA$13*AA30 -> 0 | AD30: =AD$13/AC$13*AC30 -> 0 | AF30: =AF$13/AE$13*AE30 -> 0 | AH30: =AH$13/AG$13*AG30 -> 0 | AJ30: =AJ$13/AI$13*AI30 -> 0 | AL30: =AL$13/AK$13*AK30 -> 0 | AM30: =AA30+AC30+AE30+AG30+AK30 -> 0 | AN30: =AB30+AD30+AF30+AH30+AL30 -> 0 | AP30: =AP$13/AO$13*AO30 -> 0 | AQ30: =AO30 -> 0 | AR30: =AP30 -> 0 | AS30: =K30+Y30+AM30+AQ30 -> 0.07 | AT30: =L30+Z30+AN30+AR30 -> 9.6481727 | AU30: - | AV30: =IF(AU30="●",AT30,0) -> 0
C31: 18 | D31: 明細連絡 | E31: SKU明細を工場へ連絡する | F31: 日次 | H31: =H$13/G$13*G31 -> 0 | K31: =G31+I31 -> 0 | L31: =H31+J31 -> 0 | M31: 0.01 | N31: =N$13/M$13*M31 -> 0.30533636 | O31: 0.01 | P31: =P$13/O$13*O31 -> 0.30533636 | Q31: 0.01 | R31: =R$13/Q$13*Q31 -> 0.30533636 | S31: 0.01 | T31: =T$13/S$13*S31 -> 0.30533636 | U31: 0.01 | V31: =V$13/U$13*U31 -> 0.30533636 | W31: 0.01 | X31: =X$13/W$13*W31 -> 0.30533636 | Y31: =M31+O31+Q31+S31+U31+W31 -> 0.06 | Z31: =N31+P31+R31+T31+V31+X31 -> 1.8320182 | AB31: =AB$13/AA$13*AA31 -> 0 | AD31: =AD$13/AC$13*AC31 -> 0 | AF31: =AF$13/AE$13*AE31 -> 0 | AH31: =AH$13/AG$13*AG31 -> 0 | AJ31: =AJ$13/AI$13*AI31 -> 0 | AL31: =AL$13/AK$13*AK31 -> 0 | AM31: =AA31+AC31+AE31+AG31+AK31 -> 0 | AN31: =AB31+AD31+AF31+AH31+AL31 -> 0 | AP31: =AP$13/AO$13*AO31 -> 0 | AQ31: =AO31 -> 0 | AR31: =AP31 -> 0 | AS31: =K31+Y31+AM31+AQ31 -> 0.06 | AT31: =L31+Z31+AN31+AR31 -> 1.8320182 | AU31: - | AV31: =IF(AU31="●",AT31,0) -> 0
C32: 19 | D32: 工場生産計画 | E32: 中期生産計画 | F32: 週次 | G32: 0.05 | H32: =H$13/G$13*G32 -> 9.0375 | K32: =G32+I32 -> 0.05 | L32: =H32+J32 -> 9.0375 | M32: 0.01 | N32: =N$13/M$13*M32 -> 0.30533636 | O32: 0.01 | P32: =P$13/O$13*O32 -> 0.30533636 | R32: =R$13/Q$13*Q32 -> 0 | T32: =T$13/S$13*S32 -> 0 | V32: =V$13/U$13*U32 -> 0 | X32: =X$13/W$13*W32 -> 0 | Y32: =M32+O32+Q32+S32+U32+W32 -> 0.02 | Z32: =N32+P32+R32+T32+V32+X32 -> 0.61067273 | AB32: =AB$13/AA$13*AA32 -> 0 | AD32: =AD$13/AC$13*AC32 -> 0 | AF32: =AF$13/AE$13*AE32 -> 0 | AH32: =AH$13/AG$13*AG32 -> 0 | AJ32: =AJ$13/AI$13*AI32 -> 0 | AL32: =AL$13/AK$13*AK32 -> 0 | AM32: =AA32+AC32+AE32+AG32+AK32 -> 0 | AN32: =AB32+AD32+AF32+AH32+AL32 -> 0 | AP32: =AP$13/AO$13*AO32 -> 0 | AQ32: =AO32 -> 0 | AR32: =AP32 -> 0 | AS32: =K32+Y32+AM32+AQ32 -> 0.07 | AT32: =L32+Z32+AN32+AR32 -> 9.6481727 | AU32: - | AV32: =IF(AU32="●",AT32,0) -> 0
C33: 20 | D33: 資材進捗 | E33: 材料の進捗状況を確認し工場へ報告する | F33: 日次 | H33: =H$13/G$13*G33 -> 0 | K33: =G33+I33 -> 0 | L33: =H33+J33 -> 0 | M33: 0 | N33: =N$13/M$13*M33 -> 0 | O33: 0.01 | P33: =P$13/O$13*O33 -> 0.30533636 | Q33: 0.01 | R33: =R$13/Q$13*Q33 -> 0.30533636 | S33: 0.01 | T33: =T$13/S$13*S33 -> 0.30533636 | U33: 0.01 | V33: =V$13/U$13*U33 -> 0.30533636 | W33: 0.01 | X33: =X$13/W$13*W33 -> 0.30533636 | Y33: =M33+O33+Q33+S33+U33+W33 -> 0.05 | Z33: =N33+P33+R33+T33+V33+X33 -> 1.5266818 | AB33: =AB$13/AA$13*AA33 -> 0 | AD33: =AD$13/AC$13*AC33 -> 0 | AF33: =AF$13/AE$13*AE33 -> 0 | AH33: =AH$13/AG$13*AG33 -> 0 | AJ33: =AJ$13/AI$13*AI33 -> 0 | AL33: =AL$13/AK$13*AK33 -> 0 | AM33: =AA33+AC33+AE33+AG33+AK33 -> 0 | AN33: =AB33+AD33+AF33+AH33+AL33 -> 0 | AP33: =AP$13/AO$13*AO33 -> 0 | AQ33: =AO33 -> 0 | AR33: =AP33 -> 0 | AS33: =K33+Y33+AM33+AQ33 -> 0.05 | AT33: =L33+Z33+AN33+AR33 -> 1.5266818 | AU33: - | AV33: =IF(AU33="●",AT33,0) -> 0
C34: 21 | D34: 注意連絡 | E34: 特別に注視する内容を工場へ連絡 | F34: 週次 | H34: =H$13/G$13*G34 -> 0 | K34: =G34+I34 -> 0 | L34: =H34+J34 -> 0 | M34: 0.01 | N34: =N$13/M$13*M34 -> 0.30533636 | O34: 0.01 | P34: =P$13/O$13*O34 -> 0.30533636 | Q34: 0.01 | R34: =R$13/Q$13*Q34 -> 0.30533636 | S34: 0.01 | T34: =T$13/S$13*S34 -> 0.30533636 | U34: 0.01 | V34: =V$13/U$13*U34 -> 0.30533636 | W34: 0.01 | X34: =X$13/W$13*W34 -> 0.30533636 | Y34: =M34+O34+Q34+S34+U34+W34 -> 0.06 | Z34: =N34+P34+R34+T34+V34+X34 -> 1.8320182 | AA34: 0.02 | AB34: =AB$13/AA$13*AA34 -> 0.61067273 | AC34: 0.04 | AD34: =AD$13/AC$13*AC34 -> 1.2213455 | AE34: 0.02 | AF34: =AF$13/AE$13*AE34 -> 0.61067273 | AG34: 0.02 | AH34: =AH$13/AG$13*AG34 -> 0.61067273 | AI34: 0.02 | AJ34: =AJ$13/AI$13*AI34 -> 0.61067273 | AL34: =AL$13/AK$13*AK34 -> 0 | AM34: =AA34+AC34+AE34+AG34+AK34 -> 0.1 | AN34: =AB34+AD34+AF34+AH34+AL34 -> 3.0533636 | AP34: =AP$13/AO$13*AO34 -> 0 | AQ34: =AO34 -> 0 | AR34: =AP34 -> 0 | AS34: =K34+Y34+AM34+AQ34 -> 0.16 | AT34: =L34+Z34+AN34+AR34 -> 4.8853818 | AU34: - | AV34: =IF(AU34="●",AT34,0) -> 0
B35: サンプル | C35: 22 | D35: 受注 | E35: 営業オーダー受注。サンプル管理表への記入 | F35: 日次 | H35: =H$13/G$13*G35 -> 0 | K35: =G35+I35 -> 0 | L35: =H35+J35 -> 0 | M35: 0.01 | N35: =N$13/M$13*M35 -> 0.30533636 | O35: 0.01 | P35: =P$13/O$13*O35 -> 0.30533636 | Q35: 0.01 | R35: =R$13/Q$13*Q35 -> 0.30533636 | S35: 0.01 | T35: =T$13/S$13*S35 -> 0.30533636 | U35: 0.01 | V35: =V$13/U$13*U35 -> 0.30533636 | W35: 0.01 | X35: =X$13/W$13*W35 -> 0.30533636 | Y35: =M35+O35+Q35+S35+U35+W35 -> 0.06 | Z35: =N35+P35+R35+T35+V35+X35 -> 1.8320182 | AB35: =AB$13/AA$13*AA35 -> 0 | AD35: =AD$13/AC$13*AC35 -> 0 | AF35: =AF$13/AE$13*AE35 -> 0 | AH35: =AH$13/AG$13*AG35 -> 0 | AJ35: =AJ$13/AI$13*AI35 -> 0 | AL35: =AL$13/AK$13*AK35 -> 0 | AM35: =AA35+AC35+AE35+AG35+AK35 -> 0 | AN35: =AB35+AD35+AF35+AH35+AL35 -> 0 | AP35: =AP$13/AO$13*AO35 -> 0 | AQ35: =AO35 -> 0 | AR35: =AP35 -> 0 | AS35: =K35+Y35+AM35+AQ35 -> 0.06 | AT35: =L35+Z35+AN35+AR35 -> 1.8320182 | AU35: - | AV35: =IF(AU35="●",AT35,0) -> 0
C36: 23 | D36: 工場指示 | E36: 日本からのサンプル依頼を工場へ連絡 | F36: 日次 | H36: =H$13/G$13*G36 -> 0 | K36: =G36+I36 -> 0 | L36: =H36+J36 -> 0 | M36: 0.01 | N36: =N$13/M$13*M36 -> 0.30533636 | O36: 0.01 | P36: =P$13/O$13*O36 -> 0.30533636 | Q36: 0.01 | R36: =R$13/Q$13*Q36 -> 0.30533636 | S36: 0.01 | T36: =T$13/S$13*S36 -> 0.30533636 | U36: 0.01 | V36: =V$13/U$13*U36 -> 0.30533636 | W36: 0.01 | X36: =X$13/W$13*W36 -> 0.30533636 | Y36: =M36+O36+Q36+S36+U36+W36 -> 0.06 | Z36: =N36+P36+R36+T36+V36+X36 -> 1.8320182 | AB36: =AB$13/AA$13*AA36 -> 0 | AD36: =AD$13/AC$13*AC36 -> 0 | AF36: =AF$13/AE$13*AE36 -> 0 | AH36: =AH$13/AG$13*AG36 -> 0 | AJ36: =AJ$13/AI$13*AI36 -> 0 | AL36: =AL$13/AK$13*AK36 -> 0 | AM36: =AA36+AC36+AE36+AG36+AK36 -> 0 | AN36: =AB36+AD36+AF36+AH36+AL36 -> 0 | AP36: =AP$13/AO$13*AO36 -> 0 | AQ36: =AO36 -> 0 | AR36: =AP36 -> 0 | AS36: =K36+Y36+AM36+AQ36 -> 0.06 | AT36: =L36+Z36+AN36+AR36 -> 1.8320182 | AU36: - | AV36: =IF(AU36="●",AT36,0) -> 0
C37: 24 | D37: 納期回答 | E37: 工場スケジューリング、納期回答 | F37: 日次 | H37: =H$13/G$13*G37 -> 0 | K37: =G37+I37 -> 0 | L37: =H37+J37 -> 0 | M37: 0.01 | N37: =N$13/M$13*M37 -> 0.30533636 | O37: 0.01 | P37: =P$13/O$13*O37 -> 0.30533636 | Q37: 0.01 | R37: =R$13/Q$13*Q37 -> 0.30533636 | S37: 0.01 | T37: =T$13/S$13*S37 -> 0.30533636 | U37: 0.01 | V37: =V$13/U$13*U37 -> 0.30533636 | W37: 0.01 | X37: =X$13/W$13*W37 -> 0.30533636 | Y37: =M37+O37+Q37+S37+U37+W37 -> 0.06 | Z37: =N37+P37+R37+T37+V37+X37 -> 1.8320182 | AB37: =AB$13/AA$13*AA37 -> 0 | AD37: =AD$13/AC$13*AC37 -> 0 | AF37: =AF$13/AE$13*AE37 -> 0 | AH37: =AH$13/AG$13*AG37 -> 0 | AJ37: =AJ$13/AI$13*AI37 -> 0 | AL37: =AL$13/AK$13*AK37 -> 0 | AM37: =AA37+AC37+AE37+AG37+AK37 -> 0 | AN37: =AB37+AD37+AF37+AH37+AL37 -> 0 | AP37: =AP$13/AO$13*AO37 -> 0 | AQ37: =AO37 -> 0 | AR37: =AP37 -> 0 | AS37: =K37+Y37+AM37+AQ37 -> 0.06 | AT37: =L37+Z37+AN37+AR37 -> 1.8320182 | AU37: - | AV37: =IF(AU37="●",AT37,0) -> 0
C38: 25 | D38: 仕様 | E38: 仕様書の受領、翻訳 | F38: 日次 | H38: =H$13/G$13*G38 -> 0 | K38: =G38+I38 -> 0 | L38: =H38+J38 -> 0 | M38: 0.07 | N38: =N$13/M$13*M38 -> 2.1373545 | O38: 0.26 | P38: =P$13/O$13*O38 -> 7.9387455 | Q38: 0.25 | R38: =R$13/Q$13*Q38 -> 7.6334091 | S38: 0.2 | T38: =T$13/S$13*S38 -> 6.1067273 | U38: 0.25 | V38: =V$13/U$13*U38 -> 7.6334091 | W38: 0.19 | X38: =X$13/W$13*W38 -> 5.8013909 | Y38: =M38+O38+Q38+S38+U38+W38 -> 1.22 | Z38: =N38+P38+R38+T38+V38+X38 -> 37.251036 | AB38: =AB$13/AA$13*AA38 -> 0 | AD38: =AD$13/AC$13*AC38 -> 0 | AF38: =AF$13/AE$13*AE38 -> 0 | AH38: =AH$13/AG$13*AG38 -> 0 | AJ38: =AJ$13/AI$13*AI38 -> 0 | AL38: =AL$13/AK$13*AK38 -> 0 | AM38: =AA38+AC38+AE38+AG38+AK38 -> 0 | AN38: =AB38+AD38+AF38+AH38+AL38 -> 0 | AP38: =AP$13/AO$13*AO38 -> 0 | AQ38: =AO38 -> 0 | AR38: =AP38 -> 0 | AS38: =K38+Y38+AM38+AQ38 -> 1.22 | AT38: =L38+Z38+AN38+AR38 -> 37.251036 | AU38: - | AV38: =IF(AU38="●",AT38,0) -> 0
C39: 26 | D39: パターンチェック | E39: パターンの受領、寸法チェック | F39: 日次 | H39: =H$13/G$13*G39 -> 0 | K39: =G39+I39 -> 0 | L39: =H39+J39 -> 0 | N39: =N$13/M$13*M39 -> 0 | P39: =P$13/O$13*O39 -> 0 | R39: =R$13/Q$13*Q39 -> 0 | T39: =T$13/S$13*S39 -> 0 | V39: =V$13/U$13*U39 -> 0 | X39: =X$13/W$13*W39 -> 0 | Y39: =M39+O39+Q39+S39+U39+W39 -> 0 | Z39: =N39+P39+R39+T39+V39+X39 -> 0 | AA39: 0.01 | AB39: =AB$13/AA$13*AA39 -> 0.30533636 | AC39: 0.01 | AD39: =AD$13/AC$13*AC39 -> 0.30533636 | AE39: 0.01 | AF39: =AF$13/AE$13*AE39 -> 0.30533636 | AG39: 0.02 | AH39: =AH$13/AG$13*AG39 -> 0.61067273 | AI39: 0.01 | AJ39: =AJ$13/AI$13*AI39 -> 0.30533636 | AK39: 0.03 | AL39: =AL$13/AK$13*AK39 -> 0.91600909 | AM39: =AA39+AC39+AE39+AG39+AK39 -> 0.08 | AN39: =AB39+AD39+AF39+AH39+AL39 -> 2.4426909 | AP39: =AP$13/AO$13*AO39 -> 0 | AQ39: =AO39 -> 0 | AR39: =AP39 -> 0 | AS39: =K39+Y39+AM39+AQ39 -> 0.08 | AT39: =L39+Z39+AN39+AR39 -> 2.4426909 | AU39: - | AV39: =IF(AU39="●",AT39,0) -> 0
C40: 27 | D40: 用尺計算 | E40: 工場の作成したマーカー図のチェック、修正依頼 | F40: 日次 | H40: =H$13/G$13*G40 -> 0 | K40: =G40+I40 -> 0 | L40: =H40+J40 -> 0 | N40: =N$13/M$13*M40 -> 0 | O40: 0.01 | P40: =P$13/O$13*O40 -> 0.30533636 | Q40: 0.01 | R40: =R$13/Q$13*Q40 -> 0.30533636 | S40: 0.01 | T40: =T$13/S$13*S40 -> 0.30533636 | U40: 0.01 | V40: =V$13/U$13*U40 -> 0.30533636 | W40: 0.01 | X40: =X$13/W$13*W40 -> 0.30533636 | Y40: =M40+O40+Q40+S40+U40+W40 -> 0.05 | Z40: =N40+P40+R40+T40+V40+X40 -> 1.5266818 | AA40: 0.01 | AB40: =AB$13/AA$13*AA40 -> 0.30533636 | AC40: 0.01 | AD40: =AD$13/AC$13*AC40 -> 0.30533636 | AE40: 0.01 | AF40: =AF$13/AE$13*AE40 -> 0.30533636 | AG40: 0.02 | AH40: =AH$13/AG$13*AG40 -> 0.61067273 | AI40: 0.01 | AJ40: =AJ$13/AI$13*AI40 -> 0.30533636 | AK40: 0.01 | AL40: =AL$13/AK$13*AK40 -> 0.30533636 | AM40: =AA40+AC40+AE40+AG40+AK40 -> 0.06 | AN40: =AB40+AD40+AF40+AH40+AL40 -> 1.8320182 | AP40: =AP$13/AO$13*AO40 -> 0 | AQ40: =AO40 -> 0 | AR40: =AP40 -> 0 | AS40: =K40+Y40+AM40+AQ40 -> 0.11 | AT40: =L40+Z40+AN40+AR40 -> 3.3587 | AU40: - | AV40: =IF(AU40="●",AT40,0) -> 0
C41: 28 | D41: 資材不足確認 | E41: 不足資材を確認してTIへ連絡する | F41: 日次 | H41: =H$13/G$13*G41 -> 0 | K41: =G41+I41 -> 0 | L41: =H41+J41 -> 0 | M41: 0.01 | N41: =N$13/M$13*M41 -> 0.30533636 | O41: 0.01 | P41: =P$13/O$13*O41 -> 0.30533636 | Q41: 0.01 | R41: =R$13/Q$13*Q41 -> 0.30533636 | S41: 0.08 | T41: =T$13/S$13*S41 -> 2.4426909 | U41: 0.04 | V41: =V$13/U$13*U41 -> 1.2213455 | W41: 0.08 | X41: =X$13/W$13*W41 -> 2.4426909 | Y41: =M41+O41+Q41+S41+U41+W41 -> 0.23 | Z41: =N41+P41+R41+T41+V41+X41 -> 7.0227364 | AB41: =AB$13/AA$13*AA41 -> 0 | AD41: =AD$13/AC$13*AC41 -> 0 | AF41: =AF$13/AE$13*AE41 -> 0 | AH41: =AH$13/AG$13*AG41 -> 0 | AJ41: =AJ$13/AI$13*AI41 -> 0 | AL41: =AL$13/AK$13*AK41 -> 0 | AM41: =AA41+AC41+AE41+AG41+AK41 -> 0 | AN41: =AB41+AD41+AF41+AH41+AL41 -> 0 | AP41: =AP$13/AO$13*AO41 -> 0 | AQ41: =AO41 -> 0 | AR41: =AP41 -> 0 | AS41: =K41+Y41+AM41+AQ41 -> 0.23 | AT41: =L41+Z41+AN41+AR41 -> 7.0227364 | AU41: - | AV41: =IF(AU41="●",AT41,0) -> 0
C42: 29 | D42: 進捗フォロー | E42: サンプルラインへの進捗フォロー | F42: 週3回程度 | H42: =H$13/G$13*G42 -> 0 | K42: =G42+I42 -> 0 | L42: =H42+J42 -> 0 | M42: 0.02 | N42: =N$13/M$13*M42 -> 0.61067273 | O42: 0.01 | P42: =P$13/O$13*O42 -> 0.30533636 | Q42: 0.03 | R42: =R$13/Q$13*Q42 -> 0.91600909 | S42: 0.02 | T42: =T$13/S$13*S42 -> 0.61067273 | U42: 0.02 | V42: =V$13/U$13*U42 -> 0.61067273 | W42: 0.02 | X42: =X$13/W$13*W42 -> 0.61067273 | Y42: =M42+O42+Q42+S42+U42+W42 -> 0.12 | Z42: =N42+P42+R42+T42+V42+X42 -> 3.6640364 | AB42: =AB$13/AA$13*AA42 -> 0 | AD42: =AD$13/AC$13*AC42 -> 0 | AF42: =AF$13/AE$13*AE42 -> 0 | AH42: =AH$13/AG$13*AG42 -> 0 | AJ42: =AJ$13/AI$13*AI42 -> 0 | AK42: 0.01 | AL42: =AL$13/AK$13*AK42 -> 0.30533636 | AM42: =AA42+AC42+AE42+AG42+AK42 -> 0.01 | AN42: =AB42+AD42+AF42+AH42+AL42 -> 0.30533636 | AP42: =AP$13/AO$13*AO42 -> 0 | AQ42: =AO42 -> 0 | AR42: =AP42 -> 0 | AS42: =K42+Y42+AM42+AQ42 -> 0.13 | AT42: =L42+Z42+AN42+AR42 -> 3.9693727 | AU42: - | AV42: =IF(AU42="●",AT42,0) -> 0
C43: 30 | D43: 諸確認 | E43: サンプル班からの問合せ・質問対応 | F43: 週3回程度 | H43: =H$13/G$13*G43 -> 0 | K43: =G43+I43 -> 0 | L43: =H43+J43 -> 0 | M43: 0 | N43: =N$13/M$13*M43 -> 0 | O43: 0.01 | P43: =P$13/O$13*O43 -> 0.30533636 | Q43: 0.01 | R43: =R$13/Q$13*Q43 -> 0.30533636 | S43: 0.01 | T43: =T$13/S$13*S43 -> 0.30533636 | U43: 0.01 | V43: =V$13/U$13*U43 -> 0.30533636 | W43: 0.01 | X43: =X$13/W$13*W43 -> 0.30533636 | Y43: =M43+O43+Q43+S43+U43+W43 -> 0.05 | Z43: =N43+P43+R43+T43+V43+X43 -> 1.5266818 | AB43: =AB$13/AA$13*AA43 -> 0 | AD43: =AD$13/AC$13*AC43 -> 0 | AF43: =AF$13/AE$13*AE43 -> 0 | AH43: =AH$13/AG$13*AG43 -> 0 | AJ43: =AJ$13/AI$13*AI43 -> 0 | AK43: 0.03 | AL43: =AL$13/AK$13*AK43 -> 0.91600909 | AM43: =AA43+AC43+AE43+AG43+AK43 -> 0.03 | AN43: =AB43+AD43+AF43+AH43+AL43 -> 0.91600909 | AP43: =AP$13/AO$13*AO43 -> 0 | AQ43: =AO43 -> 0 | AR43: =AP43 -> 0 | AS43: =K43+Y43+AM43+AQ43 -> 0.08 | AT43: =L43+Z43+AN43+AR43 -> 2.4426909 | AU43: - | AV43: =IF(AU43="●",AT43,0) -> 0
C44: 31 | D44: 問題抽出・改善提案 | E44: 仕様・素材に不具合があればアラート・改善提案する。 | F44: 不定期（頻度中） | H44: =H$13/G$13*G44 -> 0 | K44: =G44+I44 -> 0 | L44: =H44+J44 -> 0 | M44: 0.01 | N44: =N$13/M$13*M44 -> 0.30533636 | O44: 0.01 | P44: =P$13/O$13*O44 -> 0.30533636 | Q44: 0.01 | R44: =R$13/Q$13*Q44 -> 0.30533636 | S44: 0.01 | T44: =T$13/S$13*S44 -> 0.30533636 | U44: 0.01 | V44: =V$13/U$13*U44 -> 0.30533636 | W44: 0.01 | X44: =X$13/W$13*W44 -> 0.30533636 | Y44: =M44+O44+Q44+S44+U44+W44 -> 0.06 | Z44: =N44+P44+R44+T44+V44+X44 -> 1.8320182 | AA44: 0.1 | AB44: =AB$13/AA$13*AA44 -> 3.0533636 | AC44: 0.12 | AD44: =AD$13/AC$13*AC44 -> 3.6640364 | AE44: 0.08 | AF44: =AF$13/AE$13*AE44 -> 2.4426909 | AG44: 0.07 | AH44: =AH$13/AG$13*AG44 -> 2.1373545 | AI44: 0.1 | AJ44: =AJ$13/AI$13*AI44 -> 3.0533636 | AK44: 0.04 | AL44: =AL$13/AK$13*AK44 -> 1.2213455 | AM44: =AA44+AC44+AE44+AG44+AK44 -> 0.41 | AN44: =AB44+AD44+AF44+AH44+AL44 -> 12.518791 | AP44: =AP$13/AO$13*AO44 -> 0 | AQ44: =AO44 -> 0 | AR44: =AP44 -> 0 | AS44: =K44+Y44+AM44+AQ44 -> 0.47 | AT44: =L44+Z44+AN44+AR44 -> 14.350809 | AU44: - | AV44: =IF(AU44="●",AT44,0) -> 0
C45: 32 | D45: コメント連絡 | E45: サンプルコメント・採寸表の記入と連絡 | F45: 日次 | H45: =H$13/G$13*G45 -> 0 | K45: =G45+I45 -> 0 | L45: =H45+J45 -> 0 | M45: 0 | N45: =N$13/M$13*M45 -> 0 | O45: 0.02 | P45: =P$13/O$13*O45 -> 0.61067273 | Q45: 0.01 | R45: =R$13/Q$13*Q45 -> 0.30533636 | S45: 0.01 | T45: =T$13/S$13*S45 -> 0.30533636 | U45: 0.01 | V45: =V$13/U$13*U45 -> 0.30533636 | W45: 0.01 | X45: =X$13/W$13*W45 -> 0.30533636 | Y45: =M45+O45+Q45+S45+U45+W45 -> 0.06 | Z45: =N45+P45+R45+T45+V45+X45 -> 1.8320182 | AA45: 0.17 | AB45: =AB$13/AA$13*AA45 -> 5.1907182 | AC45: 0.1 | AD45: =AD$13/AC$13*AC45 -> 3.0533636 | AE45: 0.14 | AF45: =AF$13/AE$13*AE45 -> 4.2747091 | AG45: 0.15 | AH45: =AH$13/AG$13*AG45 -> 4.5800455 | AI45: 0.1 | AJ45: =AJ$13/AI$13*AI45 -> 3.0533636 | AK45: 0.03 | AL45: =AL$13/AK$13*AK45 -> 0.91600909 | AM45: =AA45+AC45+AE45+AG45+AK45 -> 0.59 | AN45: =AB45+AD45+AF45+AH45+AL45 -> 18.014845 | AP45: =AP$13/AO$13*AO45 -> 0 | AQ45: =AO45 -> 0 | AR45: =AP45 -> 0 | AS45: =K45+Y45+AM45+AQ45 -> 0.65 | AT45: =L45+Z45+AN45+AR45 -> 19.846864 | AU45: - | AV45: =IF(AU45="●",AT45,0) -> 0
C46: 33 | D46: 二次加工 | E46: 外部工場の見本に関してバルクでの問題点を確認・連絡 | F46: 不定期（頻度低） | H46: =H$13/G$13*G46 -> 0 | K46: =G46+I46 -> 0 | L46: =H46+J46 -> 0 | M46: 0 | N46: =N$13/M$13*M46 -> 0 | O46: 0.01 | P46: =P$13/O$13*O46 -> 0.30533636 | Q46: 0.01 | R46: =R$13/Q$13*Q46 -> 0.30533636 | S46: 0.01 | T46: =T$13/S$13*S46 -> 0.30533636 | U46: 0.01 | V46: =V$13/U$13*U46 -> 0.30533636 | W46: 0.01 | X46: =X$13/W$13*W46 -> 0.30533636 | Y46: =M46+O46+Q46+S46+U46+W46 -> 0.05 | Z46: =N46+P46+R46+T46+V46+X46 -> 1.5266818 | AB46: =AB$13/AA$13*AA46 -> 0 | AD46: =AD$13/AC$13*AC46 -> 0 | AF46: =AF$13/AE$13*AE46 -> 0 | AH46: =AH$13/AG$13*AG46 -> 0 | AJ46: =AJ$13/AI$13*AI46 -> 0 | AL46: =AL$13/AK$13*AK46 -> 0 | AM46: =AA46+AC46+AE46+AG46+AK46 -> 0 | AN46: =AB46+AD46+AF46+AH46+AL46 -> 0 | AP46: =AP$13/AO$13*AO46 -> 0 | AQ46: =AO46 -> 0 | AR46: =AP46 -> 0 | AS46: =K46+Y46+AM46+AQ46 -> 0.05 | AT46: =L46+Z46+AN46+AR46 -> 1.5266818 | AU46: - | AV46: =IF(AU46="●",AT46,0) -> 0
C47: 34 | D47: 出荷連絡 | E47: 出荷明細、送り状NoをTIへ連絡する | F47: 日次 | H47: =H$13/G$13*G47 -> 0 | K47: =G47+I47 -> 0 | L47: =H47+J47 -> 0 | M47: 0 | N47: =N$13/M$13*M47 -> 0 | O47: 0.01 | P47: =P$13/O$13*O47 -> 0.30533636 | Q47: 0.01 | R47: =R$13/Q$13*Q47 -> 0.30533636 | S47: 0.01 | T47: =T$13/S$13*S47 -> 0.30533636 | U47: 0.01 | V47: =V$13/U$13*U47 -> 0.30533636 | W47: 0.01 | X47: =X$13/W$13*W47 -> 0.30533636 | Y47: =M47+O47+Q47+S47+U47+W47 -> 0.05 | Z47: =N47+P47+R47+T47+V47+X47 -> 1.5266818 | AB47: =AB$13/AA$13*AA47 -> 0 | AD47: =AD$13/AC$13*AC47 -> 0 | AF47: =AF$13/AE$13*AE47 -> 0 | AH47: =AH$13/AG$13*AG47 -> 0 | AJ47: =AJ$13/AI$13*AI47 -> 0 | AL47: =AL$13/AK$13*AK47 -> 0 | AM47: =AA47+AC47+AE47+AG47+AK47 -> 0 | AN47: =AB47+AD47+AF47+AH47+AL47 -> 0 | AP47: =AP$13/AO$13*AO47 -> 0 | AQ47: =AO47 -> 0 | AR47: =AP47 -> 0 | AS47: =K47+Y47+AM47+AQ47 -> 0.05 | AT47: =L47+Z47+AN47+AR47 -> 1.5266818 | AU47: - | AV47: =IF(AU47="●",AT47,0) -> 0
C48: 35 | D48: 発送 | E48: サンプル発送 | F48: 日次 | H48: =H$13/G$13*G48 -> 0 | K48: =G48+I48 -> 0 | L48: =H48+J48 -> 0 | M48: 0 | N48: =N$13/M$13*M48 -> 0 | O48: 0.01 | P48: =P$13/O$13*O48 -> 0.30533636 | Q48: 0.01 | R48: =R$13/Q$13*Q48 -> 0.30533636 | S48: 0.01 | T48: =T$13/S$13*S48 -> 0.30533636 | U48: 0.01 | V48: =V$13/U$13*U48 -> 0.30533636 | W48: 0.01 | X48: =X$13/W$13*W48 -> 0.30533636 | Y48: =M48+O48+Q48+S48+U48+W48 -> 0.05 | Z48: =N48+P48+R48+T48+V48+X48 -> 1.5266818 | AB48: =AB$13/AA$13*AA48 -> 0 | AD48: =AD$13/AC$13*AC48 -> 0 | AF48: =AF$13/AE$13*AE48 -> 0 | AH48: =AH$13/AG$13*AG48 -> 0 | AJ48: =AJ$13/AI$13*AI48 -> 0 | AL48: =AL$13/AK$13*AK48 -> 0 | AM48: =AA48+AC48+AE48+AG48+AK48 -> 0 | AN48: =AB48+AD48+AF48+AH48+AL48 -> 0 | AP48: =AP$13/AO$13*AO48 -> 0 | AQ48: =AO48 -> 0 | AR48: =AP48 -> 0 | AS48: =K48+Y48+AM48+AQ48 -> 0.05 | AT48: =L48+Z48+AN48+AR48 -> 1.5266818 | AU48: ● | AV48: =IF(AU48="●",AT48,0) -> 1.5266818
C49: 36 | D49: 生産条件設定 | E49: 接着・シーム条件検討。機能性検査・記録 | F49: 日次 | H49: =H$13/G$13*G49 -> 0 | K49: =G49+I49 -> 0 | L49: =H49+J49 -> 0 | M49: 0.01 | N49: =N$13/M$13*M49 -> 0.30533636 | O49: 0.01 | P49: =P$13/O$13*O49 -> 0.30533636 | Q49: 0 | R49: =R$13/Q$13*Q49 -> 0 | S49: 0.01 | T49: =T$13/S$13*S49 -> 0.30533636 | U49: 0.01 | V49: =V$13/U$13*U49 -> 0.30533636 | W49: 0.01 | X49: =X$13/W$13*W49 -> 0.30533636 | Y49: =M49+O49+Q49+S49+U49+W49 -> 0.05 | Z49: =N49+P49+R49+T49+V49+X49 -> 1.5266818 | AA49: 0.01 | AB49: =AB$13/AA$13*AA49 -> 0.30533636 | AC49: 0.01 | AD49: =AD$13/AC$13*AC49 -> 0.30533636 | AE49: 0.01 | AF49: =AF$13/AE$13*AE49 -> 0.30533636 | AG49: 0.01 | AH49: =AH$13/AG$13*AG49 -> 0.30533636 | AI49: 0.01 | AJ49: =AJ$13/AI$13*AI49 -> 0.30533636 | AL49: =AL$13/AK$13*AK49 -> 0 | AM49: =AA49+AC49+AE49+AG49+AK49 -> 0.04 | AN49: =AB49+AD49+AF49+AH49+AL49 -> 1.2213455 | AP49: =AP$13/AO$13*AO49 -> 0 | AQ49: =AO49 -> 0 | AR49: =AP49 -> 0 | AS49: =K49+Y49+AM49+AQ49 -> 0.09 | AT49: =L49+Z49+AN49+AR49 -> 2.7480273 | AU49: - | AV49: =IF(AU49="●",AT49,0) -> 0
C50: 37 | D50: 工程分析 | E50: 生産能力・コスト試算 | F50: 不定期（頻度低） | H50: =H$13/G$13*G50 -> 0 | K50: =G50+I50 -> 0 | L50: =H50+J50 -> 0 | M50: 0.02 | N50: =N$13/M$13*M50 -> 0.61067273 | O50: 0.01 | P50: =P$13/O$13*O50 -> 0.30533636 | R50: =R$13/Q$13*Q50 -> 0 | T50: =T$13/S$13*S50 -> 0 | V50: =V$13/U$13*U50 -> 0 | X50: =X$13/W$13*W50 -> 0 | Y50: =M50+O50+Q50+S50+U50+W50 -> 0.03 | Z50: =N50+P50+R50+T50+V50+X50 -> 0.91600909 | AA50: 0.01 | AB50: =AB$13/AA$13*AA50 -> 0.30533636 | AC50: 0.01 | AD50: =AD$13/AC$13*AC50 -> 0.30533636 | AE50: 0.01 | AF50: =AF$13/AE$13*AE50 -> 0.30533636 | AG50: 0.01 | AH50: =AH$13/AG$13*AG50 -> 0.30533636 | AI50: 0.01 | AJ50: =AJ$13/AI$13*AI50 -> 0.30533636 | AK50: 0.02 | AL50: =AL$13/AK$13*AK50 -> 0.61067273 | AM50: =AA50+AC50+AE50+AG50+AK50 -> 0.06 | AN50: =AB50+AD50+AF50+AH50+AL50 -> 1.8320182 | AP50: =AP$13/AO$13*AO50 -> 0 | AQ50: =AO50 -> 0 | AR50: =AP50 -> 0 | AS50: =K50+Y50+AM50+AQ50 -> 0.09 | AT50: =L50+Z50+AN50+AR50 -> 2.7480273 | AU50: - | AV50: =IF(AU50="●",AT50,0) -> 0
C51: 38 | D51: 元見本管理 | E51: 元見本台帳を作成し入出庫を管理する | F51: 不定期（頻度中） | H51: =H$13/G$13*G51 -> 0 | K51: =G51+I51 -> 0 | L51: =H51+J51 -> 0 | M51: 0 | N51: =N$13/M$13*M51 -> 0 | O51: 0.01 | P51: =P$13/O$13*O51 -> 0.30533636 | Q51: 0.01 | R51: =R$13/Q$13*Q51 -> 0.30533636 | S51: 0.01 | T51: =T$13/S$13*S51 -> 0.30533636 | U51: 0.01 | V51: =V$13/U$13*U51 -> 0.30533636 | W51: 0.01 | X51: =X$13/W$13*W51 -> 0.30533636 | Y51: =M51+O51+Q51+S51+U51+W51 -> 0.05 | Z51: =N51+P51+R51+T51+V51+X51 -> 1.5266818 | AA51: 0.01 | AB51: =AB$13/AA$13*AA51 -> 0.30533636 | AC51: 0.01 | AD51: =AD$13/AC$13*AC51 -> 0.30533636 | AE51: 0.01 | AF51: =AF$13/AE$13*AE51 -> 0.30533636 | AG51: 0.01 | AH51: =AH$13/AG$13*AG51 -> 0.30533636 | AI51: 0.01 | AJ51: =AJ$13/AI$13*AI51 -> 0.30533636 | AL51: =AL$13/AK$13*AK51 -> 0 | AM51: =AA51+AC51+AE51+AG51+AK51 -> 0.04 | AN51: =AB51+AD51+AF51+AH51+AL51 -> 1.2213455 | AP51: =AP$13/AO$13*AO51 -> 0 | AQ51: =AO51 -> 0 | AR51: =AP51 -> 0 | AS51: =K51+Y51+AM51+AQ51 -> 0.09 | AT51: =L51+Z51+AN51+AR51 -> 2.7480273 | AU51: - | AV51: =IF(AU51="●",AT51,0) -> 0
B52: 仕様書 | C52: 39 | D52: ファイル作成 | E52: 仕様書をプリントアウトしブランド・シーズン別にファイルを作成 | F52: 不定期（頻度中） | H52: =H$13/G$13*G52 -> 0 | K52: =G52+I52 -> 0 | L52: =H52+J52 -> 0 | N52: =N$13/M$13*M52 -> 0 | P52: =P$13/O$13*O52 -> 0 | R52: =R$13/Q$13*Q52 -> 0 | T52: =T$13/S$13*S52 -> 0 | V52: =V$13/U$13*U52 -> 0 | X52: =X$13/W$13*W52 -> 0 | Y52: =M52+O52+Q52+S52+U52+W52 -> 0 | Z52: =N52+P52+R52+T52+V52+X52 -> 0 | AA52: 0.01 | AB52: =AB$13/AA$13*AA52 -> 0.30533636 | AC52: 0.01 | AD52: =AD$13/AC$13*AC52 -> 0.30533636 | AE52: 0.01 | AF52: =AF$13/AE$13*AE52 -> 0.30533636 | AG52: 0.01 | AH52: =AH$13/AG$13*AG52 -> 0.30533636 | AI52: 0.01 | AJ52: =AJ$13/AI$13*AI52 -> 0.30533636 | AL52: =AL$13/AK$13*AK52 -> 0 | AM52: =AA52+AC52+AE52+AG52+AK52 -> 0.04 | AN52: =AB52+AD52+AF52+AH52+AL52 -> 1.2213455 | AP52: =AP$13/AO$13*AO52 -> 0 | AQ52: =AO52 -> 0 | AR52: =AP52 -> 0 | AS52: =K52+Y52+AM52+AQ52 -> 0.04 | AT52: =L52+Z52+AN52+AR52 -> 1.2213455 | AU52: - | AV52: =IF(AU52="●",AT52,0) -> 0
C53: 40 | D53: 翻訳 | E53: ベトナム語への翻訳 | F53: 日次 | H53: =H$13/G$13*G53 -> 0 | K53: =G53+I53 -> 0 | L53: =H53+J53 -> 0 | M53: 0.03 | N53: =N$13/M$13*M53 -> 0.91600909 | O53: 0.05 | P53: =P$13/O$13*O53 -> 1.5266818 | Q53: 0.06 | R53: =R$13/Q$13*Q53 -> 1.8320182 | S53: 0.05 | T53: =T$13/S$13*S53 -> 1.5266818 | U53: 0.05 | V53: =V$13/U$13*U53 -> 1.5266818 | W53: 0.05 | X53: =X$13/W$13*W53 -> 1.5266818 | Y53: =M53+O53+Q53+S53+U53+W53 -> 0.29 | Z53: =N53+P53+R53+T53+V53+X53 -> 8.8547545 | AB53: =AB$13/AA$13*AA53 -> 0 | AD53: =AD$13/AC$13*AC53 -> 0 | AF53: =AF$13/AE$13*AE53 -> 0 | AH53: =AH$13/AG$13*AG53 -> 0 | AJ53: =AJ$13/AI$13*AI53 -> 0 | AL53: =AL$13/AK$13*AK53 -> 0 | AM53: =AA53+AC53+AE53+AG53+AK53 -> 0 | AN53: =AB53+AD53+AF53+AH53+AL53 -> 0 | AP53: =AP$13/AO$13*AO53 -> 0 | AQ53: =AO53 -> 0 | AR53: =AP53 -> 0 | AS53: =K53+Y53+AM53+AQ53 -> 0.29 | AT53: =L53+Z53+AN53+AR53 -> 8.8547545 | AU53: - | AV53: =IF(AU53="●",AT53,0) -> 0
C54: 41 | D54: チェック | E54: パターンや元見本と違ったり問題があった場合、TIへ連絡する | F54: 日次 | H54: =H$13/G$13*G54 -> 0 | K54: =G54+I54 -> 0 | L54: =H54+J54 -> 0 | M54: 0 | N54: =N$13/M$13*M54 -> 0 | O54: 0.02 | P54: =P$13/O$13*O54 -> 0.61067273 | Q54: 0.03 | R54: =R$13/Q$13*Q54 -> 0.91600909 | S54: 0.02 | T54: =T$13/S$13*S54 -> 0.61067273 | U54: 0.02 | V54: =V$13/U$13*U54 -> 0.61067273 | W54: 0.02 | X54: =X$13/W$13*W54 -> 0.61067273 | Y54: =M54+O54+Q54+S54+U54+W54 -> 0.11 | Z54: =N54+P54+R54+T54+V54+X54 -> 3.3587 | AA54: 0.05 | AB54: =AB$13/AA$13*AA54 -> 1.5266818 | AC54: 0.05 | AD54: =AD$13/AC$13*AC54 -> 1.5266818 | AE54: 0.07 | AF54: =AF$13/AE$13*AE54 -> 2.1373545 | AG54: 0.05 | AH54: =AH$13/AG$13*AG54 -> 1.5266818 | AI54: 0.05 | AJ54: =AJ$13/AI$13*AI54 -> 1.5266818 | AK54: 0.08 | AL54: =AL$13/AK$13*AK54 -> 2.4426909 | AM54: =AA54+AC54+AE54+AG54+AK54 -> 0.3 | AN54: =AB54+AD54+AF54+AH54+AL54 -> 9.1600909 | AP54: =AP$13/AO$13*AO54 -> 0 | AQ54: =AO54 -> 0 | AR54: =AP54 -> 0 | AS54: =K54+Y54+AM54+AQ54 -> 0.41 | AT54: =L54+Z54+AN54+AR54 -> 12.518791 | AU54: - | AV54: =IF(AU54="●",AT54,0) -> 0
C55: 42 | D55: 修正連絡 | E55: 修正があれば修正仕様書を翻訳し工場へ連絡する | F55: 不定期（頻度高） | H55: =H$13/G$13*G55 -> 0 | K55: =G55+I55 -> 0 | L55: =H55+J55 -> 0 | M55: 0 | N55: =N$13/M$13*M55 -> 0 | O55: 0.01 | P55: =P$13/O$13*O55 -> 0.30533636 | Q55: 0.01 | R55: =R$13/Q$13*Q55 -> 0.30533636 | S55: 0.02 | T55: =T$13/S$13*S55 -> 0.61067273 | U55: 0.02 | V55: =V$13/U$13*U55 -> 0.61067273 | W55: 0.02 | X55: =X$13/W$13*W55 -> 0.61067273 | Y55: =M55+O55+Q55+S55+U55+W55 -> 0.08 | Z55: =N55+P55+R55+T55+V55+X55 -> 2.4426909 | AA55: 0.01 | AB55: =AB$13/AA$13*AA55 -> 0.30533636 | AC55: 0.01 | AD55: =AD$13/AC$13*AC55 -> 0.30533636 | AE55: 0.01 | AF55: =AF$13/AE$13*AE55 -> 0.30533636 | AG55: 0.01 | AH55: =AH$13/AG$13*AG55 -> 0.30533636 | AI55: 0.01 | AJ55: =AJ$13/AI$13*AI55 -> 0.30533636 | AL55: =AL$13/AK$13*AK55 -> 0 | AM55: =AA55+AC55+AE55+AG55+AK55 -> 0.04 | AN55: =AB55+AD55+AF55+AH55+AL55 -> 1.2213455 | AP55: =AP$13/AO$13*AO55 -> 0 | AQ55: =AO55 -> 0 | AR55: =AP55 -> 0 | AS55: =K55+Y55+AM55+AQ55 -> 0.12 | AT55: =L55+Z55+AN55+AR55 -> 3.6640364 | AU55: - | AV55: =IF(AU55="●",AT55,0) -> 0
B56: パターン | C56: 43 | D56: パターン連絡 | E56: パターンデータを工場に転送する | F56: 不定期（頻度高） | H56: =H$13/G$13*G56 -> 0 | K56: =G56+I56 -> 0 | L56: =H56+J56 -> 0 | M56: 0 | N56: =N$13/M$13*M56 -> 0 | O56: 0.01 | P56: =P$13/O$13*O56 -> 0.30533636 | Q56: 0.01 | R56: =R$13/Q$13*Q56 -> 0.30533636 | S56: 0.01 | T56: =T$13/S$13*S56 -> 0.30533636 | U56: 0.01 | V56: =V$13/U$13*U56 -> 0.30533636 | W56: 0.01 | X56: =X$13/W$13*W56 -> 0.30533636 | Y56: =M56+O56+Q56+S56+U56+W56 -> 0.05 | Z56: =N56+P56+R56+T56+V56+X56 -> 1.5266818 | AB56: =AB$13/AA$13*AA56 -> 0 | AD56: =AD$13/AC$13*AC56 -> 0 | AF56: =AF$13/AE$13*AE56 -> 0 | AH56: =AH$13/AG$13*AG56 -> 0 | AJ56: =AJ$13/AI$13*AI56 -> 0 | AL56: =AL$13/AK$13*AK56 -> 0 | AM56: =AA56+AC56+AE56+AG56+AK56 -> 0 | AN56: =AB56+AD56+AF56+AH56+AL56 -> 0 | AP56: =AP$13/AO$13*AO56 -> 0 | AQ56: =AO56 -> 0 | AR56: =AP56 -> 0 | AS56: =K56+Y56+AM56+AQ56 -> 0.05 | AT56: =L56+Z56+AN56+AR56 -> 1.5266818 | AU56: - | AV56: =IF(AU56="●",AT56,0) -> 0
C57: 44 | D57: チェック | E57: 仕様書と違ったり問題があった場合、TIへ連絡する | F57: 不定期（頻度中） | H57: =H$13/G$13*G57 -> 0 | K57: =G57+I57 -> 0 | L57: =H57+J57 -> 0 | M57: 0 | N57: =N$13/M$13*M57 -> 0 | O57: 0.01 | P57: =P$13/O$13*O57 -> 0.30533636 | Q57: 0.03 | R57: =R$13/Q$13*Q57 -> 0.91600909 | S57: 0.01 | T57: =T$13/S$13*S57 -> 0.30533636 | U57: 0.01 | V57: =V$13/U$13*U57 -> 0.30533636 | W57: 0.01 | X57: =X$13/W$13*W57 -> 0.30533636 | Y57: =M57+O57+Q57+S57+U57+W57 -> 0.07 | Z57: =N57+P57+R57+T57+V57+X57 -> 2.1373545 | AA57: 0.05 | AB57: =AB$13/AA$13*AA57 -> 1.5266818 | AC57: 0.05 | AD57: =AD$13/AC$13*AC57 -> 1.5266818 | AE57: 0.05 | AF57: =AF$13/AE$13*AE57 -> 1.5266818 | AG57: 0.05 | AH57: =AH$13/AG$13*AG57 -> 1.5266818 | AI57: 0.05 | AJ57: =AJ$13/AI$13*AI57 -> 1.5266818 | AK57: 0.08 | AL57: =AL$13/AK$13*AK57 -> 2.4426909 | AM57: =AA57+AC57+AE57+AG57+AK57 -> 0.28 | AN57: =AB57+AD57+AF57+AH57+AL57 -> 8.5494182 | AP57: =AP$13/AO$13*AO57 -> 0 | AQ57: =AO57 -> 0 | AR57: =AP57 -> 0 | AS57: =K57+Y57+AM57+AQ57 -> 0.35 | AT57: =L57+Z57+AN57+AR57 -> 10.686773 | AU57: - | AV57: =IF(AU57="●",AT57,0) -> 0
C58: 45 | D58: 修正 | E58: 一部不具合を工場で修正するように指示 | F58: 不定期（頻度中） | H58: =H$13/G$13*G58 -> 0 | K58: =G58+I58 -> 0 | L58: =H58+J58 -> 0 | N58: =N$13/M$13*M58 -> 0 | P58: =P$13/O$13*O58 -> 0 | R58: =R$13/Q$13*Q58 -> 0 | T58: =T$13/S$13*S58 -> 0 | V58: =V$13/U$13*U58 -> 0 | X58: =X$13/W$13*W58 -> 0 | Y58: =M58+O58+Q58+S58+U58+W58 -> 0 | Z58: =N58+P58+R58+T58+V58+X58 -> 0 | AA58: 0.01 | AB58: =AB$13/AA$13*AA58 -> 0.30533636 | AC58: 0.01 | AD58: =AD$13/AC$13*AC58 -> 0.30533636 | AE58: 0.01 | AF58: =AF$13/AE$13*AE58 -> 0.30533636 | AG58: 0.01 | AH58: =AH$13/AG$13*AG58 -> 0.30533636 | AI58: 0.01 | AJ58: =AJ$13/AI$13*AI58 -> 0.30533636 | AK58: 0.04 | AL58: =AL$13/AK$13*AK58 -> 1.2213455 | AM58: =AA58+AC58+AE58+AG58+AK58 -> 0.08 | AN58: =AB58+AD58+AF58+AH58+AL58 -> 2.4426909 | AP58: =AP$13/AO$13*AO58 -> 0 | AQ58: =AO58 -> 0 | AR58: =AP58 -> 0 | AS58: =K58+Y58+AM58+AQ58 -> 0.08 | AT58: =L58+Z58+AN58+AR58 -> 2.4426909 | AU58: - | AV58: =IF(AU58="●",AT58,0) -> 0
B59: 資材管理 | C59: 46 | D59: 資材着荷確認 | E59: BL、P/L、DHL No などを工場へ連絡する | F59: 日次 | H59: =H$13/G$13*G59 -> 0 | K59: =G59+I59 -> 0 | L59: =H59+J59 -> 0 | M59: 0 | N59: =N$13/M$13*M59 -> 0 | O59: 0.01 | P59: =P$13/O$13*O59 -> 0.30533636 | Q59: 0.01 | R59: =R$13/Q$13*Q59 -> 0.30533636 | S59: 0.01 | T59: =T$13/S$13*S59 -> 0.30533636 | U59: 0.01 | V59: =V$13/U$13*U59 -> 0.30533636 | W59: 0.01 | X59: =X$13/W$13*W59 -> 0.30533636 | Y59: =M59+O59+Q59+S59+U59+W59 -> 0.05 | Z59: =N59+P59+R59+T59+V59+X59 -> 1.5266818 | AB59: =AB$13/AA$13*AA59 -> 0 | AD59: =AD$13/AC$13*AC59 -> 0 | AF59: =AF$13/AE$13*AE59 -> 0 | AH59: =AH$13/AG$13*AG59 -> 0 | AJ59: =AJ$13/AI$13*AI59 -> 0 | AL59: =AL$13/AK$13*AK59 -> 0 | AM59: =AA59+AC59+AE59+AG59+AK59 -> 0 | AN59: =AB59+AD59+AF59+AH59+AL59 -> 0 | AP59: =AP$13/AO$13*AO59 -> 0 | AQ59: =AO59 -> 0 | AR59: =AP59 -> 0 | AS59: =K59+Y59+AM59+AQ59 -> 0.05 | AT59: =L59+Z59+AN59+AR59 -> 1.5266818 | AU59: - | AV59: =IF(AU59="●",AT59,0) -> 0
C60: 47 | D60: 資材不足確認 | E60: 工場からのバランスシートをもとにTIへ不足連絡をする | F60: 日次 | H60: =H$13/G$13*G60 -> 0 | K60: =G60+I60 -> 0 | L60: =H60+J60 -> 0 | M60: 0.01 | N60: =N$13/M$13*M60 -> 0.30533636 | O60: 0.03 | P60: =P$13/O$13*O60 -> 0.91600909 | Q60: 0.02 | R60: =R$13/Q$13*Q60 -> 0.61067273 | S60: 0.02 | T60: =T$13/S$13*S60 -> 0.61067273 | U60: 0.02 | V60: =V$13/U$13*U60 -> 0.61067273 | W60: 0.02 | X60: =X$13/W$13*W60 -> 0.61067273 | Y60: =M60+O60+Q60+S60+U60+W60 -> 0.12 | Z60: =N60+P60+R60+T60+V60+X60 -> 3.6640364 | AB60: =AB$13/AA$13*AA60 -> 0 | AD60: =AD$13/AC$13*AC60 -> 0 | AF60: =AF$13/AE$13*AE60 -> 0 | AH60: =AH$13/AG$13*AG60 -> 0 | AJ60: =AJ$13/AI$13*AI60 -> 0 | AL60: =AL$13/AK$13*AK60 -> 0 | AM60: =AA60+AC60+AE60+AG60+AK60 -> 0 | AN60: =AB60+AD60+AF60+AH60+AL60 -> 0 | AP60: =AP$13/AO$13*AO60 -> 0 | AQ60: =AO60 -> 0 | AR60: =AP60 -> 0 | AS60: =K60+Y60+AM60+AQ60 -> 0.12 | AT60: =L60+Z60+AN60+AR60 -> 3.6640364 | AU60: - | AV60: =IF(AU60="●",AT60,0) -> 0
C61: 48 | D61: 生地不良確認 | E61: 工場から検反報告をもらい不良内容をTIへ確認する | F61: 日次 | H61: =H$13/G$13*G61 -> 0 | K61: =G61+I61 -> 0 | L61: =H61+J61 -> 0 | M61: 0.01 | N61: =N$13/M$13*M61 -> 0.30533636 | O61: 0.03 | P61: =P$13/O$13*O61 -> 0.91600909 | Q61: 0.03 | R61: =R$13/Q$13*Q61 -> 0.91600909 | S61: 0.01 | T61: =T$13/S$13*S61 -> 0.30533636 | U61: 0.01 | V61: =V$13/U$13*U61 -> 0.30533636 | W61: 0.01 | X61: =X$13/W$13*W61 -> 0.30533636 | Y61: =M61+O61+Q61+S61+U61+W61 -> 0.1 | Z61: =N61+P61+R61+T61+V61+X61 -> 3.0533636 | AA61: 0.01 | AB61: =AB$13/AA$13*AA61 -> 0.30533636 | AC61: 0.01 | AD61: =AD$13/AC$13*AC61 -> 0.30533636 | AE61: 0.01 | AF61: =AF$13/AE$13*AE61 -> 0.30533636 | AG61: 0.01 | AH61: =AH$13/AG$13*AG61 -> 0.30533636 | AI61: 0.01 | AJ61: =AJ$13/AI$13*AI61 -> 0.30533636 | AK61: 0.05 | AL61: =AL$13/AK$13*AK61 -> 1.5266818 | AM61: =AA61+AC61+AE61+AG61+AK61 -> 0.09 | AN61: =AB61+AD61+AF61+AH61+AL61 -> 2.7480273 | AP61: =AP$13/AO$13*AO61 -> 0 | AQ61: =AO61 -> 0 | AR61: =AP61 -> 0 | AS61: =K61+Y61+AM61+AQ61 -> 0.19 | AT61: =L61+Z61+AN61+AR61 -> 5.8013909 | AU61: - | AV61: =IF(AU61="●",AT61,0) -> 0
A62: 本生産 | B62: 裁断 | C62: 49 | D62: 明細確認 | E62: 工場が作成した裁断明細を入手しチェックする | F62: 日次 | H62: =H$13/G$13*G62 -> 0 | K62: =G62+I62 -> 0 | L62: =H62+J62 -> 0 | M62: 0.01 | N62: =N$13/M$13*M62 -> 0.30533636 | O62: 0.01 | P62: =P$13/O$13*O62 -> 0.30533636 | Q62: 0.01 | R62: =R$13/Q$13*Q62 -> 0.30533636 | S62: 0.01 | T62: =T$13/S$13*S62 -> 0.30533636 | U62: 0.01 | V62: =V$13/U$13*U62 -> 0.30533636 | W62: 0.01 | X62: =X$13/W$13*W62 -> 0.30533636 | Y62: =M62+O62+Q62+S62+U62+W62 -> 0.06 | Z62: =N62+P62+R62+T62+V62+X62 -> 1.8320182 | AB62: =AB$13/AA$13*AA62 -> 0 | AD62: =AD$13/AC$13*AC62 -> 0 | AF62: =AF$13/AE$13*AE62 -> 0 | AH62: =AH$13/AG$13*AG62 -> 0 | AJ62: =AJ$13/AI$13*AI62 -> 0 | AL62: =AL$13/AK$13*AK62 -> 0 | AM62: =AA62+AC62+AE62+AG62+AK62 -> 0 | AN62: =AB62+AD62+AF62+AH62+AL62 -> 0 | AP62: =AP$13/AO$13*AO62 -> 0 | AQ62: =AO62 -> 0 | AR62: =AP62 -> 0 | AS62: =K62+Y62+AM62+AQ62 -> 0.06 | AT62: =L62+Z62+AN62+AR62 -> 1.8320182 | AU62: - | AV62: =IF(AU62="●",AT62,0) -> 0
C63: 50 | D63: 要尺確認 | E63: サンプル要尺を確認してTIへ連絡する | F63: 日次 | H63: =H$13/G$13*G63 -> 0 | K63: =G63+I63 -> 0 | L63: =H63+J63 -> 0 | M63: 0.01 | N63: =N$13/M$13*M63 -> 0.30533636 | O63: 0.01 | P63: =P$13/O$13*O63 -> 0.30533636 | Q63: 0.01 | R63: =R$13/Q$13*Q63 -> 0.30533636 | S63: 0.01 | T63: =T$13/S$13*S63 -> 0.30533636 | U63: 0.01 | V63: =V$13/U$13*U63 -> 0.30533636 | W63: 0.01 | X63: =X$13/W$13*W63 -> 0.30533636 | Y63: =M63+O63+Q63+S63+U63+W63 -> 0.06 | Z63: =N63+P63+R63+T63+V63+X63 -> 1.8320182 | AA63: 0.01 | AB63: =AB$13/AA$13*AA63 -> 0.30533636 | AC63: 0.01 | AD63: =AD$13/AC$13*AC63 -> 0.30533636 | AE63: 0.01 | AF63: =AF$13/AE$13*AE63 -> 0.30533636 | AG63: 0.01 | AH63: =AH$13/AG$13*AG63 -> 0.30533636 | AI63: 0.01 | AJ63: =AJ$13/AI$13*AI63 -> 0.30533636 | AL63: =AL$13/AK$13*AK63 -> 0 | AM63: =AA63+AC63+AE63+AG63+AK63 -> 0.04 | AN63: =AB63+AD63+AF63+AH63+AL63 -> 1.2213455 | AP63: =AP$13/AO$13*AO63 -> 0 | AQ63: =AO63 -> 0 | AR63: =AP63 -> 0 | AS63: =K63+Y63+AM63+AQ63 -> 0.1 | AT63: =L63+Z63+AN63+AR63 -> 3.0533636 | AU63: - | AV63: =IF(AU63="●",AT63,0) -> 0
C64: 51 | D64: トラブル対応 | E64: 色違い・収縮等のトラブル発生時の対応 | F64: 不定期（頻度高） | H64: =H$13/G$13*G64 -> 0 | K64: =G64+I64 -> 0 | L64: =H64+J64 -> 0 | M64: 0.01 | N64: =N$13/M$13*M64 -> 0.30533636 | O64: 0.01 | P64: =P$13/O$13*O64 -> 0.30533636 | Q64: 0.02 | R64: =R$13/Q$13*Q64 -> 0.61067273 | S64: 0.02 | T64: =T$13/S$13*S64 -> 0.61067273 | U64: 0.02 | V64: =V$13/U$13*U64 -> 0.61067273 | W64: 0.02 | X64: =X$13/W$13*W64 -> 0.61067273 | Y64: =M64+O64+Q64+S64+U64+W64 -> 0.1 | Z64: =N64+P64+R64+T64+V64+X64 -> 3.0533636 | AA64: 0.02 | AB64: =AB$13/AA$13*AA64 -> 0.61067273 | AC64: 0.02 | AD64: =AD$13/AC$13*AC64 -> 0.61067273 | AE64: 0.02 | AF64: =AF$13/AE$13*AE64 -> 0.61067273 | AG64: 0.02 | AH64: =AH$13/AG$13*AG64 -> 0.61067273 | AI64: 0.02 | AJ64: =AJ$13/AI$13*AI64 -> 0.61067273 | AK64: 0.08 | AL64: =AL$13/AK$13*AK64 -> 2.4426909 | AM64: =AA64+AC64+AE64+AG64+AK64 -> 0.16 | AN64: =AB64+AD64+AF64+AH64+AL64 -> 4.8853818 | AP64: =AP$13/AO$13*AO64 -> 0 | AQ64: =AO64 -> 0 | AR64: =AP64 -> 0 | AS64: =K64+Y64+AM64+AQ64 -> 0.26 | AT64: =L64+Z64+AN64+AR64 -> 7.9387455 | AU64: - | AV64: =IF(AU64="●",AT64,0) -> 0
B65: 二次加工 | C65: 52 | D65: 刺繍 | E65: 刺繍データを入手し、刺繍屋に連絡する | F65: 不定期（頻度中） | H65: =H$13/G$13*G65 -> 0 | K65: =G65+I65 -> 0 | L65: =H65+J65 -> 0 | M65: 0 | N65: =N$13/M$13*M65 -> 0 | O65: 0.01 | P65: =P$13/O$13*O65 -> 0.30533636 | Q65: 0.01 | R65: =R$13/Q$13*Q65 -> 0.30533636 | S65: 0.01 | T65: =T$13/S$13*S65 -> 0.30533636 | U65: 0.01 | V65: =V$13/U$13*U65 -> 0.30533636 | W65: 0.01 | X65: =X$13/W$13*W65 -> 0.30533636 | Y65: =M65+O65+Q65+S65+U65+W65 -> 0.05 | Z65: =N65+P65+R65+T65+V65+X65 -> 1.5266818 | AB65: =AB$13/AA$13*AA65 -> 0 | AD65: =AD$13/AC$13*AC65 -> 0 | AF65: =AF$13/AE$13*AE65 -> 0 | AH65: =AH$13/AG$13*AG65 -> 0 | AJ65: =AJ$13/AI$13*AI65 -> 0 | AL65: =AL$13/AK$13*AK65 -> 0 | AM65: =AA65+AC65+AE65+AG65+AK65 -> 0 | AN65: =AB65+AD65+AF65+AH65+AL65 -> 0 | AP65: =AP$13/AO$13*AO65 -> 0 | AQ65: =AO65 -> 0 | AR65: =AP65 -> 0 | AS65: =K65+Y65+AM65+AQ65 -> 0.05 | AT65: =L65+Z65+AN65+AR65 -> 1.5266818 | AU65: - | AV65: =IF(AU65="●",AT65,0) -> 0
B66: ※2 | C66: 53 | D66: プリント | E66: プリントデータを入手し、プリント屋に連絡する | F66: 不定期（頻度中） | H66: =H$13/G$13*G66 -> 0 | K66: =G66+I66 -> 0 | L66: =H66+J66 -> 0 | M66: 0 | N66: =N$13/M$13*M66 -> 0 | O66: 0.01 | P66: =P$13/O$13*O66 -> 0.30533636 | Q66: 0.01 | R66: =R$13/Q$13*Q66 -> 0.30533636 | S66: 0.01 | T66: =T$13/S$13*S66 -> 0.30533636 | U66: 0.01 | V66: =V$13/U$13*U66 -> 0.30533636 | W66: 0.01 | X66: =X$13/W$13*W66 -> 0.30533636 | Y66: =M66+O66+Q66+S66+U66+W66 -> 0.05 | Z66: =N66+P66+R66+T66+V66+X66 -> 1.5266818 | AB66: =AB$13/AA$13*AA66 -> 0 | AD66: =AD$13/AC$13*AC66 -> 0 | AF66: =AF$13/AE$13*AE66 -> 0 | AH66: =AH$13/AG$13*AG66 -> 0 | AJ66: =AJ$13/AI$13*AI66 -> 0 | AL66: =AL$13/AK$13*AK66 -> 0 | AM66: =AA66+AC66+AE66+AG66+AK66 -> 0 | AN66: =AB66+AD66+AF66+AH66+AL66 -> 0 | AP66: =AP$13/AO$13*AO66 -> 0 | AQ66: =AO66 -> 0 | AR66: =AP66 -> 0 | AS66: =K66+Y66+AM66+AQ66 -> 0.05 | AT66: =L66+Z66+AN66+AR66 -> 1.5266818 | AU66: - | AV66: =IF(AU66="●",AT66,0) -> 0
C67: 54 | D67: キルト | E67: 依頼内容のバルク展開可否判断 | F67: 不定期（頻度低） | H67: =H$13/G$13*G67 -> 0 | K67: =G67+I67 -> 0 | L67: =H67+J67 -> 0 | M67: 0 | N67: =N$13/M$13*M67 -> 0 | O67: 0.01 | P67: =P$13/O$13*O67 -> 0.30533636 | Q67: 0.01 | R67: =R$13/Q$13*Q67 -> 0.30533636 | S67: 0.01 | T67: =T$13/S$13*S67 -> 0.30533636 | U67: 0.01 | V67: =V$13/U$13*U67 -> 0.30533636 | W67: 0.01 | X67: =X$13/W$13*W67 -> 0.30533636 | Y67: =M67+O67+Q67+S67+U67+W67 -> 0.05 | Z67: =N67+P67+R67+T67+V67+X67 -> 1.5266818 | AA67: 0.01 | AB67: =AB$13/AA$13*AA67 -> 0.30533636 | AC67: 0.01 | AD67: =AD$13/AC$13*AC67 -> 0.30533636 | AE67: 0.01 | AF67: =AF$13/AE$13*AE67 -> 0.30533636 | AG67: 0.01 | AH67: =AH$13/AG$13*AG67 -> 0.30533636 | AI67: 0.01 | AJ67: =AJ$13/AI$13*AI67 -> 0.30533636 | AK67: 0.01 | AL67: =AL$13/AK$13*AK67 -> 0.30533636 | AM67: =AA67+AC67+AE67+AG67+AK67 -> 0.05 | AN67: =AB67+AD67+AF67+AH67+AL67 -> 1.5266818 | AP67: =AP$13/AO$13*AO67 -> 0 | AQ67: =AO67 -> 0 | AR67: =AP67 -> 0 | AS67: =K67+Y67+AM67+AQ67 -> 0.1 | AT67: =L67+Z67+AN67+AR67 -> 3.0533636 | AU67: - | AV67: =IF(AU67="●",AT67,0) -> 0
C68: 55 | D68: 品位確認・評価 | E68: 現物確認、客先個別試験 | F68: 不定期（頻度低） | H68: =H$13/G$13*G68 -> 0 | K68: =G68+I68 -> 0 | L68: =H68+J68 -> 0 | M68: 0.01 | N68: =N$13/M$13*M68 -> 0.30533636 | O68: 0.01 | P68: =P$13/O$13*O68 -> 0.30533636 | Q68: 0.01 | R68: =R$13/Q$13*Q68 -> 0.30533636 | S68: 0.01 | T68: =T$13/S$13*S68 -> 0.30533636 | U68: 0.01 | V68: =V$13/U$13*U68 -> 0.30533636 | W68: 0.01 | X68: =X$13/W$13*W68 -> 0.30533636 | Y68: =M68+O68+Q68+S68+U68+W68 -> 0.06 | Z68: =N68+P68+R68+T68+V68+X68 -> 1.8320182 | AA68: 0.01 | AB68: =AB$13/AA$13*AA68 -> 0.30533636 | AC68: 0.01 | AD68: =AD$13/AC$13*AC68 -> 0.30533636 | AE68: 0.01 | AF68: =AF$13/AE$13*AE68 -> 0.30533636 | AG68: 0.01 | AH68: =AH$13/AG$13*AG68 -> 0.30533636 | AI68: 0.01 | AJ68: =AJ$13/AI$13*AI68 -> 0.30533636 | AK68: 0.01 | AL68: =AL$13/AK$13*AK68 -> 0.30533636 | AM68: =AA68+AC68+AE68+AG68+AK68 -> 0.05 | AN68: =AB68+AD68+AF68+AH68+AL68 -> 1.5266818 | AP68: =AP$13/AO$13*AO68 -> 0 | AQ68: =AO68 -> 0 | AR68: =AP68 -> 0 | AS68: =K68+Y68+AM68+AQ68 -> 0.11 | AT68: =L68+Z68+AN68+AR68 -> 3.3587 | AU68: - | AV68: =IF(AU68="●",AT68,0) -> 0
B69: 生産 | C69: 56 | D69: 仕様確認 | E69: TIとの量産品の仕様確認 | F69: 日次 | H69: =H$13/G$13*G69 -> 0 | K69: =G69+I69 -> 0 | L69: =H69+J69 -> 0 | M69: 0.01 | N69: =N$13/M$13*M69 -> 0.30533636 | O69: 0.01 | P69: =P$13/O$13*O69 -> 0.30533636 | Q69: 0.01 | R69: =R$13/Q$13*Q69 -> 0.30533636 | S69: 0.02 | T69: =T$13/S$13*S69 -> 0.61067273 | U69: 0.02 | V69: =V$13/U$13*U69 -> 0.61067273 | W69: 0.02 | X69: =X$13/W$13*W69 -> 0.61067273 | Y69: =M69+O69+Q69+S69+U69+W69 -> 0.09 | Z69: =N69+P69+R69+T69+V69+X69 -> 2.7480273 | AA69: 0.01 | AB69: =AB$13/AA$13*AA69 -> 0.30533636 | AC69: 0.01 | AD69: =AD$13/AC$13*AC69 -> 0.30533636 | AE69: 0.01 | AF69: =AF$13/AE$13*AE69 -> 0.30533636 | AG69: 0.01 | AH69: =AH$13/AG$13*AG69 -> 0.30533636 | AI69: 0.01 | AJ69: =AJ$13/AI$13*AI69 -> 0.30533636 | AK69: 0.1 | AL69: =AL$13/AK$13*AK69 -> 3.0533636 | AM69: =AA69+AC69+AE69+AG69+AK69 -> 0.14 | AN69: =AB69+AD69+AF69+AH69+AL69 -> 4.2747091 | AP69: =AP$13/AO$13*AO69 -> 0 | AQ69: =AO69 -> 0 | AR69: =AP69 -> 0 | AS69: =K69+Y69+AM69+AQ69 -> 0.23 | AT69: =L69+Z69+AN69+AR69 -> 7.0227364 | AU69: - | AV69: =IF(AU69="●",AT69,0) -> 0
C70: 57 | D70: 資材不足確認 | E70: 不足資材を確認してTIへ連絡する | F70: 日次 | H70: =H$13/G$13*G70 -> 0 | K70: =G70+I70 -> 0 | L70: =H70+J70 -> 0 | M70: 0.01 | N70: =N$13/M$13*M70 -> 0.30533636 | O70: 0.01 | P70: =P$13/O$13*O70 -> 0.30533636 | Q70: 0.01 | R70: =R$13/Q$13*Q70 -> 0.30533636 | S70: 0.02 | T70: =T$13/S$13*S70 -> 0.61067273 | U70: 0.02 | V70: =V$13/U$13*U70 -> 0.61067273 | W70: 0.02 | X70: =X$13/W$13*W70 -> 0.61067273 | Y70: =M70+O70+Q70+S70+U70+W70 -> 0.09 | Z70: =N70+P70+R70+T70+V70+X70 -> 2.7480273 | AB70: =AB$13/AA$13*AA70 -> 0 | AD70: =AD$13/AC$13*AC70 -> 0 | AF70: =AF$13/AE$13*AE70 -> 0 | AH70: =AH$13/AG$13*AG70 -> 0 | AJ70: =AJ$13/AI$13*AI70 -> 0 | AL70: =AL$13/AK$13*AK70 -> 0 | AM70: =AA70+AC70+AE70+AG70+AK70 -> 0 | AN70: =AB70+AD70+AF70+AH70+AL70 -> 0 | AP70: =AP$13/AO$13*AO70 -> 0 | AQ70: =AO70 -> 0 | AR70: =AP70 -> 0 | AS70: =K70+Y70+AM70+AQ70 -> 0.09 | AT70: =L70+Z70+AN70+AR70 -> 2.7480273 | AU70: ● | AV70: =IF(AU70="●",AT70,0) -> 2.7480273
C71: 58 | D71: 縫製指導 | E71: 現場での縫製指導 | F71: 日次 | H71: =H$13/G$13*G71 -> 0 | K71: =G71+I71 -> 0 | L71: =H71+J71 -> 0 | N71: =N$13/M$13*M71 -> 0 | P71: =P$13/O$13*O71 -> 0 | R71: =R$13/Q$13*Q71 -> 0 | T71: =T$13/S$13*S71 -> 0 | V71: =V$13/U$13*U71 -> 0 | X71: =X$13/W$13*W71 -> 0 | Y71: =M71+O71+Q71+S71+U71+W71 -> 0 | Z71: =N71+P71+R71+T71+V71+X71 -> 0 | AA71: 0.19 | AB71: =AB$13/AA$13*AA71 -> 5.8013909 | AC71: 0.2 | AD71: =AD$13/AC$13*AC71 -> 6.1067273 | AE71: 0.19 | AF71: =AF$13/AE$13*AE71 -> 5.8013909 | AG71: 0.19 | AH71: =AH$13/AG$13*AG71 -> 5.8013909 | AI71: 0.17 | AJ71: =AJ$13/AI$13*AI71 -> 5.1907182 | AK71: 0.01 | AL71: =AL$13/AK$13*AK71 -> 0.30533636 | AM71: =AA71+AC71+AE71+AG71+AK71 -> 0.78 | AN71: =AB71+AD71+AF71+AH71+AL71 -> 23.816236 | AP71: =AP$13/AO$13*AO71 -> 0 | AQ71: =AO71 -> 0 | AR71: =AP71 -> 0 | AS71: =K71+Y71+AM71+AQ71 -> 0.78 | AT71: =L71+Z71+AN71+AR71 -> 23.816236 | AU71: - | AV71: =IF(AU71="●",AT71,0) -> 0
C72: 59 | D72: シーム・溶着指導 | E72: 現場での縫製指導 | F72: 日次 | H72: =H$13/G$13*G72 -> 0 | K72: =G72+I72 -> 0 | L72: =H72+J72 -> 0 | M72: 0.01 | N72: =N$13/M$13*M72 -> 0.30533636 | P72: =P$13/O$13*O72 -> 0 | R72: =R$13/Q$13*Q72 -> 0 | T72: =T$13/S$13*S72 -> 0 | V72: =V$13/U$13*U72 -> 0 | X72: =X$13/W$13*W72 -> 0 | Y72: =M72+O72+Q72+S72+U72+W72 -> 0.01 | Z72: =N72+P72+R72+T72+V72+X72 -> 0.30533636 | AA72: 0.01 | AB72: =AB$13/AA$13*AA72 -> 0.30533636 | AC72: 0.01 | AD72: =AD$13/AC$13*AC72 -> 0.30533636 | AE72: 0.01 | AF72: =AF$13/AE$13*AE72 -> 0.30533636 | AG72: 0.01 | AH72: =AH$13/AG$13*AG72 -> 0.30533636 | AI72: 0.01 | AJ72: =AJ$13/AI$13*AI72 -> 0.30533636 | AK72: 0.04 | AL72: =AL$13/AK$13*AK72 -> 1.2213455 | AM72: =AA72+AC72+AE72+AG72+AK72 -> 0.08 | AN72: =AB72+AD72+AF72+AH72+AL72 -> 2.4426909 | AP72: =AP$13/AO$13*AO72 -> 0 | AQ72: =AO72 -> 0 | AR72: =AP72 -> 0 | AS72: =K72+Y72+AM72+AQ72 -> 0.09 | AT72: =L72+Z72+AN72+AR72 -> 2.7480273 | AU72: - | AV72: =IF(AU72="●",AT72,0) -> 0
C73: 60 | D73: 納期管理 | E73: 生産日報、進捗の確認 | F73: 日次 | G73: 0.03 | H73: =H$13/G$13*G73 -> 5.4225 | K73: =G73+I73 -> 0.03 | L73: =H73+J73 -> 5.4225 | M73: 0.01 | N73: =N$13/M$13*M73 -> 0.30533636 | O73: 0.01 | P73: =P$13/O$13*O73 -> 0.30533636 | Q73: 0.01 | R73: =R$13/Q$13*Q73 -> 0.30533636 | S73: 0.01 | T73: =T$13/S$13*S73 -> 0.30533636 | U73: 0.01 | V73: =V$13/U$13*U73 -> 0.30533636 | W73: 0.01 | X73: =X$13/W$13*W73 -> 0.30533636 | Y73: =M73+O73+Q73+S73+U73+W73 -> 0.06 | Z73: =N73+P73+R73+T73+V73+X73 -> 1.8320182 | AA73: 0.01 | AB73: =AB$13/AA$13*AA73 -> 0.30533636 | AC73: 0.01 | AD73: =AD$13/AC$13*AC73 -> 0.30533636 | AE73: 0.01 | AF73: =AF$13/AE$13*AE73 -> 0.30533636 | AG73: 0.01 | AH73: =AH$13/AG$13*AG73 -> 0.30533636 | AI73: 0.01 | AJ73: =AJ$13/AI$13*AI73 -> 0.30533636 | AK73: 0.01 | AL73: =AL$13/AK$13*AK73 -> 0.30533636 | AM73: =AA73+AC73+AE73+AG73+AK73 -> 0.05 | AN73: =AB73+AD73+AF73+AH73+AL73 -> 1.5266818 | AP73: =AP$13/AO$13*AO73 -> 0 | AQ73: =AO73 -> 0 | AR73: =AP73 -> 0 | AS73: =K73+Y73+AM73+AQ73 -> 0.14 | AT73: =L73+Z73+AN73+AR73 -> 8.7812 | AU73: - | AV73: =IF(AU73="●",AT73,0) -> 0
C74: 61 | D74: トラブルシュート | E74: 各種トラブル対応(段取り、計画、工程、品質) | F74: 不定期（頻度高） | H74: =H$13/G$13*G74 -> 0 | K74: =G74+I74 -> 0 | L74: =H74+J74 -> 0 | M74: 0.01 | N74: =N$13/M$13*M74 -> 0.30533636 | O74: 0.01 | P74: =P$13/O$13*O74 -> 0.30533636 | Q74: 0.01 | R74: =R$13/Q$13*Q74 -> 0.30533636 | S74: 0.01 | T74: =T$13/S$13*S74 -> 0.30533636 | U74: 0.01 | V74: =V$13/U$13*U74 -> 0.30533636 | W74: 0.01 | X74: =X$13/W$13*W74 -> 0.30533636 | Y74: =M74+O74+Q74+S74+U74+W74 -> 0.06 | Z74: =N74+P74+R74+T74+V74+X74 -> 1.8320182 | AA74: 0.03 | AB74: =AB$13/AA$13*AA74 -> 0.91600909 | AC74: 0.04 | AD74: =AD$13/AC$13*AC74 -> 1.2213455 | AE74: 0.04 | AF74: =AF$13/AE$13*AE74 -> 1.2213455 | AG74: 0.04 | AH74: =AH$13/AG$13*AG74 -> 1.2213455 | AI74: 0.04 | AJ74: =AJ$13/AI$13*AI74 -> 1.2213455 | AK74: 0.05 | AL74: =AL$13/AK$13*AK74 -> 1.5266818 | AM74: =AA74+AC74+AE74+AG74+AK74 -> 0.2 | AN74: =AB74+AD74+AF74+AH74+AL74 -> 6.1067273 | AP74: =AP$13/AO$13*AO74 -> 0 | AQ74: =AO74 -> 0 | AR74: =AP74 -> 0 | AS74: =K74+Y74+AM74+AQ74 -> 0.26 | AT74: =L74+Z74+AN74+AR74 -> 7.9387455 | AU74: - | AV74: =IF(AU74="●",AT74,0) -> 0
C75: 62 | D75: 生産結果記録 | E75: 問題・対策内容の記録と類似生産への水平展開 | F75: 不定期（頻度中） | H75: =H$13/G$13*G75 -> 0 | K75: =G75+I75 -> 0 | L75: =H75+J75 -> 0 | M75: 0.01 | N75: =N$13/M$13*M75 -> 0.30533636 | O75: 0.01 | P75: =P$13/O$13*O75 -> 0.30533636 | Q75: 0.01 | R75: =R$13/Q$13*Q75 -> 0.30533636 | S75: 0.01 | T75: =T$13/S$13*S75 -> 0.30533636 | U75: 0.01 | V75: =V$13/U$13*U75 -> 0.30533636 | W75: 0.01 | X75: =X$13/W$13*W75 -> 0.30533636 | Y75: =M75+O75+Q75+S75+U75+W75 -> 0.06 | Z75: =N75+P75+R75+T75+V75+X75 -> 1.8320182 | AA75: 0.01 | AB75: =AB$13/AA$13*AA75 -> 0.30533636 | AC75: 0.01 | AD75: =AD$13/AC$13*AC75 -> 0.30533636 | AE75: 0.01 | AF75: =AF$13/AE$13*AE75 -> 0.30533636 | AG75: 0.01 | AH75: =AH$13/AG$13*AG75 -> 0.30533636 | AI75: 0.01 | AJ75: =AJ$13/AI$13*AI75 -> 0.30533636 | AK75: 0.01 | AL75: =AL$13/AK$13*AK75 -> 0.30533636 | AM75: =AA75+AC75+AE75+AG75+AK75 -> 0.05 | AN75: =AB75+AD75+AF75+AH75+AL75 -> 1.5266818 | AP75: =AP$13/AO$13*AO75 -> 0 | AQ75: =AO75 -> 0 | AR75: =AP75 -> 0 | AS75: =K75+Y75+AM75+AQ75 -> 0.11 | AT75: =L75+Z75+AN75+AR75 -> 3.3587 | AU75: - | AV75: =IF(AU75="●",AT75,0) -> 0
C76: 63 | D76: 技術者MTG | E76: 工場の投入前MTGに参加し注意事項の確認 | F76: 日次 | H76: =H$13/G$13*G76 -> 0 | K76: =G76+I76 -> 0 | L76: =H76+J76 -> 0 | M76: 0.03 | N76: =N$13/M$13*M76 -> 0.91600909 | O76: 0.01 | P76: =P$13/O$13*O76 -> 0.30533636 | Q76: 0.01 | R76: =R$13/Q$13*Q76 -> 0.30533636 | S76: 0.01 | T76: =T$13/S$13*S76 -> 0.30533636 | U76: 0.01 | V76: =V$13/U$13*U76 -> 0.30533636 | W76: 0.01 | X76: =X$13/W$13*W76 -> 0.30533636 | Y76: =M76+O76+Q76+S76+U76+W76 -> 0.08 | Z76: =N76+P76+R76+T76+V76+X76 -> 2.4426909 | AA76: 0.01 | AB76: =AB$13/AA$13*AA76 -> 0.30533636 | AC76: 0.01 | AD76: =AD$13/AC$13*AC76 -> 0.30533636 | AE76: 0.01 | AF76: =AF$13/AE$13*AE76 -> 0.30533636 | AG76: 0.01 | AH76: =AH$13/AG$13*AG76 -> 0.30533636 | AI76: 0.01 | AJ76: =AJ$13/AI$13*AI76 -> 0.30533636 | AK76: 0.03 | AL76: =AL$13/AK$13*AK76 -> 0.91600909 | AM76: =AA76+AC76+AE76+AG76+AK76 -> 0.07 | AN76: =AB76+AD76+AF76+AH76+AL76 -> 2.1373545 | AP76: =AP$13/AO$13*AO76 -> 0 | AQ76: =AO76 -> 0 | AR76: =AP76 -> 0 | AS76: =K76+Y76+AM76+AQ76 -> 0.15 | AT76: =L76+Z76+AN76+AR76 -> 4.5800455 | AU76: - | AV76: =IF(AU76="●",AT76,0) -> 0
B77: 検査 | C77: 64 | D77: 検査目合わせ | E77: 投入後、最初に上がった製品の基準目合わせ | F77: 不定期（頻度高） | H77: =H$13/G$13*G77 -> 0 | K77: =G77+I77 -> 0 | L77: =H77+J77 -> 0 | N77: =N$13/M$13*M77 -> 0 | P77: =P$13/O$13*O77 -> 0 | R77: =R$13/Q$13*Q77 -> 0 | T77: =T$13/S$13*S77 -> 0 | V77: =V$13/U$13*U77 -> 0 | X77: =X$13/W$13*W77 -> 0 | Y77: =M77+O77+Q77+S77+U77+W77 -> 0 | Z77: =N77+P77+R77+T77+V77+X77 -> 0 | AA77: 0.03 | AB77: =AB$13/AA$13*AA77 -> 0.91600909 | AC77: 0.03 | AD77: =AD$13/AC$13*AC77 -> 0.91600909 | AE77: 0.03 | AF77: =AF$13/AE$13*AE77 -> 0.91600909 | AG77: 0.03 | AH77: =AH$13/AG$13*AG77 -> 0.91600909 | AI77: 0.03 | AJ77: =AJ$13/AI$13*AI77 -> 0.91600909 | AK77: 0.05 | AL77: =AL$13/AK$13*AK77 -> 1.5266818 | AM77: =AA77+AC77+AE77+AG77+AK77 -> 0.17 | AN77: =AB77+AD77+AF77+AH77+AL77 -> 5.1907182 | AP77: =AP$13/AO$13*AO77 -> 0 | AQ77: =AO77 -> 0 | AR77: =AP77 -> 0 | AS77: =K77+Y77+AM77+AQ77 -> 0.17 | AT77: =L77+Z77+AN77+AR77 -> 5.1907182 | AU77: - | AV77: =IF(AU77="●",AT77,0) -> 0
B78: ※3 | C78: 65 | D78: 一次検査 | E78: ライン上がり製品の縫製検査 | F78: 日次 | H78: =H$13/G$13*G78 -> 0 | K78: =G78+I78 -> 0 | L78: =H78+J78 -> 0 | N78: =N$13/M$13*M78 -> 0 | P78: =P$13/O$13*O78 -> 0 | R78: =R$13/Q$13*Q78 -> 0 | T78: =T$13/S$13*S78 -> 0 | V78: =V$13/U$13*U78 -> 0 | X78: =X$13/W$13*W78 -> 0 | Y78: =M78+O78+Q78+S78+U78+W78 -> 0 | Z78: =N78+P78+R78+T78+V78+X78 -> 0 | AA78: 0.01 | AB78: =AB$13/AA$13*AA78 -> 0.30533636 | AC78: 0.01 | AD78: =AD$13/AC$13*AC78 -> 0.30533636 | AE78: 0.01 | AF78: =AF$13/AE$13*AE78 -> 0.30533636 | AG78: 0.02 | AH78: =AH$13/AG$13*AG78 -> 0.61067273 | AI78: 0.03 | AJ78: =AJ$13/AI$13*AI78 -> 0.91600909 | AK78: 0.01 | AL78: =AL$13/AK$13*AK78 -> 0.30533636 | AM78: =AA78+AC78+AE78+AG78+AK78 -> 0.06 | AN78: =AB78+AD78+AF78+AH78+AL78 -> 1.8320182 | AP78: =AP$13/AO$13*AO78 -> 0 | AQ78: =AO78 -> 0 | AR78: =AP78 -> 0 | AS78: =K78+Y78+AM78+AQ78 -> 0.06 | AT78: =L78+Z78+AN78+AR78 -> 1.8320182 | AU78: - | AV78: =IF(AU78="●",AT78,0) -> 0
C79: 66 | D79: 二次検査 | E79: 仕上げ製品の外観検査 | F79: 日次 | H79: =H$13/G$13*G79 -> 0 | K79: =G79+I79 -> 0 | L79: =H79+J79 -> 0 | N79: =N$13/M$13*M79 -> 0 | P79: =P$13/O$13*O79 -> 0 | R79: =R$13/Q$13*Q79 -> 0 | T79: =T$13/S$13*S79 -> 0 | V79: =V$13/U$13*U79 -> 0 | X79: =X$13/W$13*W79 -> 0 | Y79: =M79+O79+Q79+S79+U79+W79 -> 0 | Z79: =N79+P79+R79+T79+V79+X79 -> 0 | AA79: 0.01 | AB79: =AB$13/AA$13*AA79 -> 0.30533636 | AC79: 0.01 | AD79: =AD$13/AC$13*AC79 -> 0.30533636 | AE79: 0.01 | AF79: =AF$13/AE$13*AE79 -> 0.30533636 | AG79: 0.01 | AH79: =AH$13/AG$13*AG79 -> 0.30533636 | AI79: 0.03 | AJ79: =AJ$13/AI$13*AI79 -> 0.91600909 | AK79: 0.01 | AL79: =AL$13/AK$13*AK79 -> 0.30533636 | AM79: =AA79+AC79+AE79+AG79+AK79 -> 0.05 | AN79: =AB79+AD79+AF79+AH79+AL79 -> 1.5266818 | AP79: =AP$13/AO$13*AO79 -> 0 | AQ79: =AO79 -> 0 | AR79: =AP79 -> 0 | AS79: =K79+Y79+AM79+AQ79 -> 0.05 | AT79: =L79+Z79+AN79+AR79 -> 1.5266818 | AU79: - | AV79: =IF(AU79="●",AT79,0) -> 0
C80: 67 | D80: 出荷前検査 | E80: 工場検品後の製品の抜取チェック | F80: 日次 | H80: =H$13/G$13*G80 -> 0 | K80: =G80+I80 -> 0 | L80: =H80+J80 -> 0 | N80: =N$13/M$13*M80 -> 0 | P80: =P$13/O$13*O80 -> 0 | R80: =R$13/Q$13*Q80 -> 0 | T80: =T$13/S$13*S80 -> 0 | V80: =V$13/U$13*U80 -> 0 | X80: =X$13/W$13*W80 -> 0 | Y80: =M80+O80+Q80+S80+U80+W80 -> 0 | Z80: =N80+P80+R80+T80+V80+X80 -> 0 | AA80: 0.01 | AB80: =AB$13/AA$13*AA80 -> 0.30533636 | AC80: 0.01 | AD80: =AD$13/AC$13*AC80 -> 0.30533636 | AE80: 0.02 | AF80: =AF$13/AE$13*AE80 -> 0.61067273 | AG80: 0.01 | AH80: =AH$13/AG$13*AG80 -> 0.30533636 | AI80: 0.02 | AJ80: =AJ$13/AI$13*AI80 -> 0.61067273 | AK80: 0.01 | AL80: =AL$13/AK$13*AK80 -> 0.30533636 | AM80: =AA80+AC80+AE80+AG80+AK80 -> 0.06 | AN80: =AB80+AD80+AF80+AH80+AL80 -> 1.8320182 | AP80: =AP$13/AO$13*AO80 -> 0 | AQ80: =AO80 -> 0 | AR80: =AP80 -> 0 | AS80: =K80+Y80+AM80+AQ80 -> 0.06 | AT80: =L80+Z80+AN80+AR80 -> 1.8320182 | AU80: - | AV80: =IF(AU80="●",AT80,0) -> 0
C81: 68 | D81: 下札、ﾈｰﾑ確認 | E81: 下げ札、ネーム類の印字内容のチェック | F81: 日次 | H81: =H$13/G$13*G81 -> 0 | K81: =G81+I81 -> 0 | L81: =H81+J81 -> 0 | N81: =N$13/M$13*M81 -> 0 | P81: =P$13/O$13*O81 -> 0 | R81: =R$13/Q$13*Q81 -> 0 | T81: =T$13/S$13*S81 -> 0 | V81: =V$13/U$13*U81 -> 0 | X81: =X$13/W$13*W81 -> 0 | Y81: =M81+O81+Q81+S81+U81+W81 -> 0 | Z81: =N81+P81+R81+T81+V81+X81 -> 0 | AA81: 0.01 | AB81: =AB$13/AA$13*AA81 -> 0.30533636 | AC81: 0.01 | AD81: =AD$13/AC$13*AC81 -> 0.30533636 | AE81: 0.01 | AF81: =AF$13/AE$13*AE81 -> 0.30533636 | AG81: 0.01 | AH81: =AH$13/AG$13*AG81 -> 0.30533636 | AI81: 0.01 | AJ81: =AJ$13/AI$13*AI81 -> 0.30533636 | AL81: =AL$13/AK$13*AK81 -> 0 | AM81: =AA81+AC81+AE81+AG81+AK81 -> 0.04 | AN81: =AB81+AD81+AF81+AH81+AL81 -> 1.2213455 | AP81: =AP$13/AO$13*AO81 -> 0 | AQ81: =AO81 -> 0 | AR81: =AP81 -> 0 | AS81: =K81+Y81+AM81+AQ81 -> 0.04 | AT81: =L81+Z81+AN81+AR81 -> 1.2213455 | AU81: - | AV81: =IF(AU81="●",AT81,0) -> 0
C82: 69 | D82: 客先検査 | E82: 客先検査結果の工場連絡 | F82: 不定期（頻度高） | H82: =H$13/G$13*G82 -> 0 | K82: =G82+I82 -> 0 | L82: =H82+J82 -> 0 | N82: =N$13/M$13*M82 -> 0 | P82: =P$13/O$13*O82 -> 0 | R82: =R$13/Q$13*Q82 -> 0 | T82: =T$13/S$13*S82 -> 0 | V82: =V$13/U$13*U82 -> 0 | X82: =X$13/W$13*W82 -> 0 | Y82: =M82+O82+Q82+S82+U82+W82 -> 0 | Z82: =N82+P82+R82+T82+V82+X82 -> 0 | AA82: 0.01 | AB82: =AB$13/AA$13*AA82 -> 0.30533636 | AC82: 0.01 | AD82: =AD$13/AC$13*AC82 -> 0.30533636 | AE82: 0.01 | AF82: =AF$13/AE$13*AE82 -> 0.30533636 | AG82: 0.01 | AH82: =AH$13/AG$13*AG82 -> 0.30533636 | AI82: 0.01 | AJ82: =AJ$13/AI$13*AI82 -> 0.30533636 | AL82: =AL$13/AK$13*AK82 -> 0 | AM82: =AA82+AC82+AE82+AG82+AK82 -> 0.04 | AN82: =AB82+AD82+AF82+AH82+AL82 -> 1.2213455 | AP82: =AP$13/AO$13*AO82 -> 0 | AQ82: =AO82 -> 0 | AR82: =AP82 -> 0 | AS82: =K82+Y82+AM82+AQ82 -> 0.04 | AT82: =L82+Z82+AN82+AR82 -> 1.2213455 | AU82: - | AV82: =IF(AU82="●",AT82,0) -> 0
C83: 70 | D83: 機能検査 | E83: 耐水圧・シーム製品抜き取り検査チェック | F83: 不定期（頻度中） | H83: =H$13/G$13*G83 -> 0 | K83: =G83+I83 -> 0 | L83: =H83+J83 -> 0 | N83: =N$13/M$13*M83 -> 0 | P83: =P$13/O$13*O83 -> 0 | R83: =R$13/Q$13*Q83 -> 0 | T83: =T$13/S$13*S83 -> 0 | V83: =V$13/U$13*U83 -> 0 | X83: =X$13/W$13*W83 -> 0 | Y83: =M83+O83+Q83+S83+U83+W83 -> 0 | Z83: =N83+P83+R83+T83+V83+X83 -> 0 | AA83: 0.01 | AB83: =AB$13/AA$13*AA83 -> 0.30533636 | AC83: 0.01 | AD83: =AD$13/AC$13*AC83 -> 0.30533636 | AE83: 0.01 | AF83: =AF$13/AE$13*AE83 -> 0.30533636 | AG83: 0.01 | AH83: =AH$13/AG$13*AG83 -> 0.30533636 | AI83: 0.01 | AJ83: =AJ$13/AI$13*AI83 -> 0.30533636 | AK83: 0.01 | AL83: =AL$13/AK$13*AK83 -> 0.30533636 | AM83: =AA83+AC83+AE83+AG83+AK83 -> 0.05 | AN83: =AB83+AD83+AF83+AH83+AL83 -> 1.5266818 | AP83: =AP$13/AO$13*AO83 -> 0 | AQ83: =AO83 -> 0 | AR83: =AP83 -> 0 | AS83: =K83+Y83+AM83+AQ83 -> 0.05 | AT83: =L83+Z83+AN83+AR83 -> 1.5266818 | AU83: - | AV83: =IF(AU83="●",AT83,0) -> 0
C84: 71 | D84: 第三者検品 | E84: 外部検査機関との品質基準・日程調整 | F84: 不定期（頻度中） | H84: =H$13/G$13*G84 -> 0 | K84: =G84+I84 -> 0 | L84: =H84+J84 -> 0 | N84: =N$13/M$13*M84 -> 0 | P84: =P$13/O$13*O84 -> 0 | R84: =R$13/Q$13*Q84 -> 0 | T84: =T$13/S$13*S84 -> 0 | V84: =V$13/U$13*U84 -> 0 | X84: =X$13/W$13*W84 -> 0 | Y84: =M84+O84+Q84+S84+U84+W84 -> 0 | Z84: =N84+P84+R84+T84+V84+X84 -> 0 | AA84: 0.01 | AB84: =AB$13/AA$13*AA84 -> 0.30533636 | AC84: 0.01 | AD84: =AD$13/AC$13*AC84 -> 0.30533636 | AE84: 0.02 | AF84: =AF$13/AE$13*AE84 -> 0.61067273 | AG84: 0.02 | AH84: =AH$13/AG$13*AG84 -> 0.61067273 | AI84: 0.01 | AJ84: =AJ$13/AI$13*AI84 -> 0.30533636 | AL84: =AL$13/AK$13*AK84 -> 0 | AM84: =AA84+AC84+AE84+AG84+AK84 -> 0.06 | AN84: =AB84+AD84+AF84+AH84+AL84 -> 1.8320182 | AP84: =AP$13/AO$13*AO84 -> 0 | AQ84: =AO84 -> 0 | AR84: =AP84 -> 0 | AS84: =K84+Y84+AM84+AQ84 -> 0.06 | AT84: =L84+Z84+AN84+AR84 -> 1.8320182 | AU84: - | AV84: =IF(AU84="●",AT84,0) -> 0
A85: 出荷 | B85: 出荷 | C85: 72 | D85: P/L管理 | E85: 出荷後のP/Lチェックし、減産していれば補充確認する | F85: 日次 | H85: =H$13/G$13*G85 -> 0 | K85: =G85+I85 -> 0 | L85: =H85+J85 -> 0 | M85: 0 | N85: =N$13/M$13*M85 -> 0 | O85: 0.01 | P85: =P$13/O$13*O85 -> 0.30533636 | Q85: 0.01 | R85: =R$13/Q$13*Q85 -> 0.30533636 | S85: 0.01 | T85: =T$13/S$13*S85 -> 0.30533636 | U85: 0.01 | V85: =V$13/U$13*U85 -> 0.30533636 | W85: 0.01 | X85: =X$13/W$13*W85 -> 0.30533636 | Y85: =M85+O85+Q85+S85+U85+W85 -> 0.05 | Z85: =N85+P85+R85+T85+V85+X85 -> 1.5266818 | AB85: =AB$13/AA$13*AA85 -> 0 | AD85: =AD$13/AC$13*AC85 -> 0 | AF85: =AF$13/AE$13*AE85 -> 0 | AH85: =AH$13/AG$13*AG85 -> 0 | AJ85: =AJ$13/AI$13*AI85 -> 0 | AL85: =AL$13/AK$13*AK85 -> 0 | AM85: =AA85+AC85+AE85+AG85+AK85 -> 0 | AN85: =AB85+AD85+AF85+AH85+AL85 -> 0 | AP85: =AP$13/AO$13*AO85 -> 0 | AQ85: =AO85 -> 0 | AR85: =AP85 -> 0 | AS85: =K85+Y85+AM85+AQ85 -> 0.05 | AT85: =L85+Z85+AN85+AR85 -> 1.5266818 | AU85: - | AV85: =IF(AU85="●",AT85,0) -> 0
C86: 73 | D86: 出荷連絡 | E86: 出荷情報確認、P/L・C/Oを連絡(BL、IVは工場からTIへ連絡） | F86: 日次 | H86: =H$13/G$13*G86 -> 0 | K86: =G86+I86 -> 0 | L86: =H86+J86 -> 0 | M86: 0 | N86: =N$13/M$13*M86 -> 0 | O86: 0.01 | P86: =P$13/O$13*O86 -> 0.30533636 | Q86: 0.01 | R86: =R$13/Q$13*Q86 -> 0.30533636 | S86: 0.01 | T86: =T$13/S$13*S86 -> 0.30533636 | U86: 0.01 | V86: =V$13/U$13*U86 -> 0.30533636 | W86: 0.01 | X86: =X$13/W$13*W86 -> 0.30533636 | Y86: =M86+O86+Q86+S86+U86+W86 -> 0.05 | Z86: =N86+P86+R86+T86+V86+X86 -> 1.5266818 | AB86: =AB$13/AA$13*AA86 -> 0 | AD86: =AD$13/AC$13*AC86 -> 0 | AF86: =AF$13/AE$13*AE86 -> 0 | AH86: =AH$13/AG$13*AG86 -> 0 | AJ86: =AJ$13/AI$13*AI86 -> 0 | AL86: =AL$13/AK$13*AK86 -> 0 | AM86: =AA86+AC86+AE86+AG86+AK86 -> 0 | AN86: =AB86+AD86+AF86+AH86+AL86 -> 0 | AP86: =AP$13/AO$13*AO86 -> 0 | AQ86: =AO86 -> 0 | AR86: =AP86 -> 0 | AS86: =K86+Y86+AM86+AQ86 -> 0.05 | AT86: =L86+Z86+AN86+AR86 -> 1.5266818 | AU86: - | AV86: =IF(AU86="●",AT86,0) -> 0
C87: 74 | D87: 日程調整 | E87: 出荷日・数量の変更依頼を工場と調整 | F87: 週次 | G87: 0.1 | H87: =H$13/G$13*G87 -> 18.075 | K87: =G87+I87 -> 0.1 | L87: =H87+J87 -> 18.075 | M87: 0 | N87: =N$13/M$13*M87 -> 0 | O87: 0.02 | P87: =P$13/O$13*O87 -> 0.61067273 | Q87: 0.01 | R87: =R$13/Q$13*Q87 -> 0.30533636 | S87: 0.01 | T87: =T$13/S$13*S87 -> 0.30533636 | U87: 0.01 | V87: =V$13/U$13*U87 -> 0.30533636 | W87: 0.01 | X87: =X$13/W$13*W87 -> 0.30533636 | Y87: =M87+O87+Q87+S87+U87+W87 -> 0.06 | Z87: =N87+P87+R87+T87+V87+X87 -> 1.8320182 | AB87: =AB$13/AA$13*AA87 -> 0 | AD87: =AD$13/AC$13*AC87 -> 0 | AF87: =AF$13/AE$13*AE87 -> 0 | AH87: =AH$13/AG$13*AG87 -> 0 | AJ87: =AJ$13/AI$13*AI87 -> 0 | AL87: =AL$13/AK$13*AK87 -> 0 | AM87: =AA87+AC87+AE87+AG87+AK87 -> 0 | AN87: =AB87+AD87+AF87+AH87+AL87 -> 0 | AP87: =AP$13/AO$13*AO87 -> 0 | AQ87: =AO87 -> 0 | AR87: =AP87 -> 0 | AS87: =K87+Y87+AM87+AQ87 -> 0.16 | AT87: =L87+Z87+AN87+AR87 -> 19.907018 | AU87: - | AV87: =IF(AU87="●",AT87,0) -> 0
A88: 工場管理 | B88: 備品管理 | C88: 75 | D88: 消耗品管理 | E88: 工場で必要な消耗品をTIへ発注し受渡伝票を作成する | F88: 不定期（頻度低） | H88: =H$13/G$13*G88 -> 0 | K88: =G88+I88 -> 0 | L88: =H88+J88 -> 0 | M88: 0.02 | N88: =N$13/M$13*M88 -> 0.61067273 | P88: =P$13/O$13*O88 -> 0 | R88: =R$13/Q$13*Q88 -> 0 | T88: =T$13/S$13*S88 -> 0 | V88: =V$13/U$13*U88 -> 0 | X88: =X$13/W$13*W88 -> 0 | Y88: =M88+O88+Q88+S88+U88+W88 -> 0.02 | Z88: =N88+P88+R88+T88+V88+X88 -> 0.61067273 | AB88: =AB$13/AA$13*AA88 -> 0 | AD88: =AD$13/AC$13*AC88 -> 0 | AF88: =AF$13/AE$13*AE88 -> 0 | AH88: =AH$13/AG$13*AG88 -> 0 | AJ88: =AJ$13/AI$13*AI88 -> 0 | AL88: =AL$13/AK$13*AK88 -> 0 | AM88: =AA88+AC88+AE88+AG88+AK88 -> 0 | AN88: =AB88+AD88+AF88+AH88+AL88 -> 0 | AP88: =AP$13/AO$13*AO88 -> 0 | AQ88: =AO88 -> 0 | AR88: =AP88 -> 0 | AS88: =K88+Y88+AM88+AQ88 -> 0.02 | AT88: =L88+Z88+AN88+AR88 -> 0.61067273 | AU88: - | AV88: =IF(AU88="●",AT88,0) -> 0
B89: 労務管理 | C89: 76 | D89: 出勤簿管理 | E89: 月ごとの出勤状況をまとめる | F89: 月次 | G89: 0.01 | H89: =H$13/G$13*G89 -> 1.8075 | K89: =G89+I89 -> 0.01 | L89: =H89+J89 -> 1.8075 | M89: 0.03 | N89: =N$13/M$13*M89 -> 0.91600909 | P89: =P$13/O$13*O89 -> 0 | R89: =R$13/Q$13*Q89 -> 0 | T89: =T$13/S$13*S89 -> 0 | V89: =V$13/U$13*U89 -> 0 | X89: =X$13/W$13*W89 -> 0 | Y89: =M89+O89+Q89+S89+U89+W89 -> 0.03 | Z89: =N89+P89+R89+T89+V89+X89 -> 0.91600909 | AB89: =AB$13/AA$13*AA89 -> 0 | AD89: =AD$13/AC$13*AC89 -> 0 | AF89: =AF$13/AE$13*AE89 -> 0 | AH89: =AH$13/AG$13*AG89 -> 0 | AJ89: =AJ$13/AI$13*AI89 -> 0 | AL89: =AL$13/AK$13*AK89 -> 0 | AM89: =AA89+AC89+AE89+AG89+AK89 -> 0 | AN89: =AB89+AD89+AF89+AH89+AL89 -> 0 | AP89: =AP$13/AO$13*AO89 -> 0 | AQ89: =AO89 -> 0 | AR89: =AP89 -> 0 | AS89: =K89+Y89+AM89+AQ89 -> 0.04 | AT89: =L89+Z89+AN89+AR89 -> 2.7235091 | AU89: - | AV89: =IF(AU89="●",AT89,0) -> 0
A90: その他 | B90: 日次作業 | C90: 77 | D90: 業務日報 | E90: 当日の行内容をTI東京へ報告 | F90: 日次 | H90: =H$13/G$13*G90 -> 0 | K90: =G90+I90 -> 0 | L90: =H90+J90 -> 0 | N90: =N$13/M$13*M90 -> 0 | P90: =P$13/O$13*O90 -> 0 | R90: =R$13/Q$13*Q90 -> 0 | T90: =T$13/S$13*S90 -> 0 | V90: =V$13/U$13*U90 -> 0 | X90: =X$13/W$13*W90 -> 0 | Y90: =M90+O90+Q90+S90+U90+W90 -> 0 | Z90: =N90+P90+R90+T90+V90+X90 -> 0 | AA90: 0.01 | AB90: =AB$13/AA$13*AA90 -> 0.30533636 | AC90: 0.01 | AD90: =AD$13/AC$13*AC90 -> 0.30533636 | AE90: 0.01 | AF90: =AF$13/AE$13*AE90 -> 0.30533636 | AG90: 0.01 | AH90: =AH$13/AG$13*AG90 -> 0.30533636 | AI90: 0.01 | AJ90: =AJ$13/AI$13*AI90 -> 0.30533636 | AL90: =AL$13/AK$13*AK90 -> 0 | AM90: =AA90+AC90+AE90+AG90+AK90 -> 0.04 | AN90: =AB90+AD90+AF90+AH90+AL90 -> 1.2213455 | AP90: =AP$13/AO$13*AO90 -> 0 | AQ90: =AO90 -> 0 | AR90: =AP90 -> 0 | AS90: =K90+Y90+AM90+AQ90 -> 0.04 | AT90: =L90+Z90+AN90+AR90 -> 1.2213455 | AU90: - | AV90: =IF(AU90="●",AT90,0) -> 0
C91: 78 | D91: 進捗報告会 | E91: 前日の生産進捗・工員出欠を各工場長より確認 | F91: 日次 | H91: =H$13/G$13*G91 -> 0 | K91: =G91+I91 -> 0 | L91: =H91+J91 -> 0 | M91: 0.01 | N91: =N$13/M$13*M91 -> 0.30533636 | P91: =P$13/O$13*O91 -> 0 | R91: =R$13/Q$13*Q91 -> 0 | T91: =T$13/S$13*S91 -> 0 | V91: =V$13/U$13*U91 -> 0 | X91: =X$13/W$13*W91 -> 0 | Y91: =M91+O91+Q91+S91+U91+W91 -> 0.01 | Z91: =N91+P91+R91+T91+V91+X91 -> 0.30533636 | AA91: 0.01 | AB91: =AB$13/AA$13*AA91 -> 0.30533636 | AC91: 0.01 | AD91: =AD$13/AC$13*AC91 -> 0.30533636 | AE91: 0.01 | AF91: =AF$13/AE$13*AE91 -> 0.30533636 | AG91: 0.01 | AH91: =AH$13/AG$13*AG91 -> 0.30533636 | AI91: 0.01 | AJ91: =AJ$13/AI$13*AI91 -> 0.30533636 | AK91: 0.01 | AL91: =AL$13/AK$13*AK91 -> 0.30533636 | AM91: =AA91+AC91+AE91+AG91+AK91 -> 0.05 | AN91: =AB91+AD91+AF91+AH91+AL91 -> 1.5266818 | AP91: =AP$13/AO$13*AO91 -> 0 | AQ91: =AO91 -> 0 | AR91: =AP91 -> 0 | AS91: =K91+Y91+AM91+AQ91 -> 0.06 | AT91: =L91+Z91+AN91+AR91 -> 1.8320182 | AU91: - | AV91: =IF(AU91="●",AT91,0) -> 0
C92: 79 | D92: 技術MTG | E92: 工場技術・品管リーダーより前日のトピックスを確認 | F92: 日次 | H92: =H$13/G$13*G92 -> 0 | K92: =G92+I92 -> 0 | L92: =H92+J92 -> 0 | M92: 0.01 | N92: =N$13/M$13*M92 -> 0.30533636 | P92: =P$13/O$13*O92 -> 0 | R92: =R$13/Q$13*Q92 -> 0 | T92: =T$13/S$13*S92 -> 0 | V92: =V$13/U$13*U92 -> 0 | W92: 0.01 | X92: =X$13/W$13*W92 -> 0.30533636 | Y92: =M92+O92+Q92+S92+U92+W92 -> 0.02 | Z92: =N92+P92+R92+T92+V92+X92 -> 0.61067273 | AA92: 0.01 | AB92: =AB$13/AA$13*AA92 -> 0.30533636 | AC92: 0.01 | AD92: =AD$13/AC$13*AC92 -> 0.30533636 | AE92: 0.01 | AF92: =AF$13/AE$13*AE92 -> 0.30533636 | AG92: 0.01 | AH92: =AH$13/AG$13*AG92 -> 0.30533636 | AI92: 0.01 | AJ92: =AJ$13/AI$13*AI92 -> 0.30533636 | AK92: 0.01 | AL92: =AL$13/AK$13*AK92 -> 0.30533636 | AM92: =AA92+AC92+AE92+AG92+AK92 -> 0.05 | AN92: =AB92+AD92+AF92+AH92+AL92 -> 1.5266818 | AP92: =AP$13/AO$13*AO92 -> 0 | AQ92: =AO92 -> 0 | AR92: =AP92 -> 0 | AS92: =K92+Y92+AM92+AQ92 -> 0.07 | AT92: =L92+Z92+AN92+AR92 -> 2.1373545 | AU92: - | AV92: =IF(AU92="●",AT92,0) -> 0
C93: 80 | D93: 工場ラウンド | E93: 工場報告内容確認 | F93: 日次 | G93: 0.01 | H93: =H$13/G$13*G93 -> 1.8075 | K93: =G93+I93 -> 0.01 | L93: =H93+J93 -> 1.8075 | M93: 0.03 | N93: =N$13/M$13*M93 -> 0.91600909 | O93: 0.01 | P93: =P$13/O$13*O93 -> 0.30533636 | Q93: 0.01 | R93: =R$13/Q$13*Q93 -> 0.30533636 | S93: 0.01 | T93: =T$13/S$13*S93 -> 0.30533636 | U93: 0.01 | V93: =V$13/U$13*U93 -> 0.30533636 | W93: 0.01 | X93: =X$13/W$13*W93 -> 0.30533636 | Y93: =M93+O93+Q93+S93+U93+W93 -> 0.08 | Z93: =N93+P93+R93+T93+V93+X93 -> 2.4426909 | AA93: 0.01 | AB93: =AB$13/AA$13*AA93 -> 0.30533636 | AC93: 0.01 | AD93: =AD$13/AC$13*AC93 -> 0.30533636 | AE93: 0.01 | AF93: =AF$13/AE$13*AE93 -> 0.30533636 | AG93: 0.01 | AH93: =AH$13/AG$13*AG93 -> 0.30533636 | AI93: 0.06 | AJ93: =AJ$13/AI$13*AI93 -> 1.8320182 | AL93: =AL$13/AK$13*AK93 -> 0 | AM93: =AA93+AC93+AE93+AG93+AK93 -> 0.04 | AN93: =AB93+AD93+AF93+AH93+AL93 -> 1.2213455 | AP93: =AP$13/AO$13*AO93 -> 0 | AQ93: =AO93 -> 0 | AR93: =AP93 -> 0 | AS93: =K93+Y93+AM93+AQ93 -> 0.13 | AT93: =L93+Z93+AN93+AR93 -> 5.4715364 | AU93: - | AV93: =IF(AU93="●",AT93,0) -> 0
C94: 81 | D94: HCMより材料引き取り | E94: 材料引き取り方法確認 | F94: 日次 | H94: =H$13/G$13*G94 -> 0 | K94: =G94+I94 -> 0 | L94: =H94+J94 -> 0 | M94: 0.01 | N94: =N$13/M$13*M94 -> 0.30533636 | O94: 0.01 | P94: =P$13/O$13*O94 -> 0.30533636 | Q94: 0.01 | R94: =R$13/Q$13*Q94 -> 0.30533636 | S94: 0.01 | T94: =T$13/S$13*S94 -> 0.30533636 | U94: 0.01 | V94: =V$13/U$13*U94 -> 0.30533636 | W94: 0.01 | X94: =X$13/W$13*W94 -> 0.30533636 | Y94: =M94+O94+Q94+S94+U94+W94 -> 0.06 | Z94: =N94+P94+R94+T94+V94+X94 -> 1.8320182 | AB94: =AB$13/AA$13*AA94 -> 0 | AD94: =AD$13/AC$13*AC94 -> 0 | AF94: =AF$13/AE$13*AE94 -> 0 | AH94: =AH$13/AG$13*AG94 -> 0 | AJ94: =AJ$13/AI$13*AI94 -> 0 | AL94: =AL$13/AK$13*AK94 -> 0 | AM94: =AA94+AC94+AE94+AG94+AK94 -> 0 | AN94: =AB94+AD94+AF94+AH94+AL94 -> 0 | AP94: =AP$13/AO$13*AO94 -> 0 | AQ94: =AO94 -> 0 | AR94: =AP94 -> 0 | AS94: =K94+Y94+AM94+AQ94 -> 0.06 | AT94: =L94+Z94+AN94+AR94 -> 1.8320182 | AU94: - | AV94: =IF(AU94="●",AT94,0) -> 0
B95: 週次作業 | C95: 82 | D95: 生産MTG | E95: 次週以降の生産計画を工場と調整・確認 | F95: 週次 | G95: 0.07 | H95: =H$13/G$13*G95 -> 12.6525 | K95: =G95+I95 -> 0.07 | L95: =H95+J95 -> 12.6525 | M95: 0.03 | N95: =N$13/M$13*M95 -> 0.91600909 | O95: 0.01 | P95: =P$13/O$13*O95 -> 0.30533636 | Q95: 0.01 | R95: =R$13/Q$13*Q95 -> 0.30533636 | S95: 0.01 | T95: =T$13/S$13*S95 -> 0.30533636 | U95: 0.01 | V95: =V$13/U$13*U95 -> 0.30533636 | W95: 0.01 | X95: =X$13/W$13*W95 -> 0.30533636 | Y95: =M95+O95+Q95+S95+U95+W95 -> 0.08 | Z95: =N95+P95+R95+T95+V95+X95 -> 2.4426909 | AB95: =AB$13/AA$13*AA95 -> 0 | AD95: =AD$13/AC$13*AC95 -> 0 | AF95: =AF$13/AE$13*AE95 -> 0 | AH95: =AH$13/AG$13*AG95 -> 0 | AJ95: =AJ$13/AI$13*AI95 -> 0 | AL95: =AL$13/AK$13*AK95 -> 0 | AM95: =AA95+AC95+AE95+AG95+AK95 -> 0 | AN95: =AB95+AD95+AF95+AH95+AL95 -> 0 | AP95: =AP$13/AO$13*AO95 -> 0 | AQ95: =AO95 -> 0 | AR95: =AP95 -> 0 | AS95: =K95+Y95+AM95+AQ95 -> 0.15 | AT95: =L95+Z95+AN95+AR95 -> 15.095191 | AU95: - | AV95: =IF(AU95="●",AT95,0) -> 0
C96: 83 | D96: サンプルMTG | E96: 2府先までのサンプル班計画を調整・確認 | F96: 週次 | H96: =H$13/G$13*G96 -> 0 | K96: =G96+I96 -> 0 | L96: =H96+J96 -> 0 | M96: 0.01 | N96: =N$13/M$13*M96 -> 0.30533636 | O96: 0.01 | P96: =P$13/O$13*O96 -> 0.30533636 | Q96: 0.01 | R96: =R$13/Q$13*Q96 -> 0.30533636 | S96: 0.01 | T96: =T$13/S$13*S96 -> 0.30533636 | U96: 0.01 | V96: =V$13/U$13*U96 -> 0.30533636 | W96: 0.01 | X96: =X$13/W$13*W96 -> 0.30533636 | Y96: =M96+O96+Q96+S96+U96+W96 -> 0.06 | Z96: =N96+P96+R96+T96+V96+X96 -> 1.8320182 | AA96: 0.01 | AB96: =AB$13/AA$13*AA96 -> 0.30533636 | AC96: 0.02 | AD96: =AD$13/AC$13*AC96 -> 0.61067273 | AE96: 0.01 | AF96: =AF$13/AE$13*AE96 -> 0.30533636 | AG96: 0.01 | AH96: =AH$13/AG$13*AG96 -> 0.30533636 | AI96: 0.01 | AJ96: =AJ$13/AI$13*AI96 -> 0.30533636 | AL96: =AL$13/AK$13*AK96 -> 0 | AM96: =AA96+AC96+AE96+AG96+AK96 -> 0.05 | AN96: =AB96+AD96+AF96+AH96+AL96 -> 1.5266818 | AP96: =AP$13/AO$13*AO96 -> 0 | AQ96: =AO96 -> 0 | AR96: =AP96 -> 0 | AS96: =K96+Y96+AM96+AQ96 -> 0.11 | AT96: =L96+Z96+AN96+AR96 -> 3.3587 | AU96: - | AV96: =IF(AU96="●",AT96,0) -> 0
C97: 84 | D97: 業務週報 | E97: 当週の行内容をTI東京へ報告 | G97: 0.05 | H97: =H$13/G$13*G97 -> 9.0375 | K97: =G97+I97 -> 0.05 | L97: =H97+J97 -> 9.0375 | N97: =N$13/M$13*M97 -> 0 | P97: =P$13/O$13*O97 -> 0 | R97: =R$13/Q$13*Q97 -> 0 | T97: =T$13/S$13*S97 -> 0 | V97: =V$13/U$13*U97 -> 0 | X97: =X$13/W$13*W97 -> 0 | Y97: =M97+O97+Q97+S97+U97+W97 -> 0 | Z97: =N97+P97+R97+T97+V97+X97 -> 0 | AB97: =AB$13/AA$13*AA97 -> 0 | AD97: =AD$13/AC$13*AC97 -> 0 | AF97: =AF$13/AE$13*AE97 -> 0 | AH97: =AH$13/AG$13*AG97 -> 0 | AJ97: =AJ$13/AI$13*AI97 -> 0 | AL97: =AL$13/AK$13*AK97 -> 0 | AM97: =AA97+AC97+AE97+AG97+AK97 -> 0 | AN97: =AB97+AD97+AF97+AH97+AL97 -> 0 | AP97: =AP$13/AO$13*AO97 -> 0 | AQ97: =AO97 -> 0 | AR97: =AP97 -> 0 | AS97: =K97+Y97+AM97+AQ97 -> 0.05 | AT97: =L97+Z97+AN97+AR97 -> 9.0375 | AU97: - | AV97: =IF(AU97="●",AT97,0) -> 0
C98: 85 | D98: 計画修正連絡 | E98: 生産管理課へ計画修正案・空きライン・問題点を連絡 | F98: 週次 | G98: 0.01 | H98: =H$13/G$13*G98 -> 1.8075 | K98: =G98+I98 -> 0.01 | L98: =H98+J98 -> 1.8075 | M98: 0.03 | N98: =N$13/M$13*M98 -> 0.91600909 | O98: 0.01 | P98: =P$13/O$13*O98 -> 0.30533636 | Q98: 0.01 | R98: =R$13/Q$13*Q98 -> 0.30533636 | S98: 0.01 | T98: =T$13/S$13*S98 -> 0.30533636 | U98: 0.01 | V98: =V$13/U$13*U98 -> 0.30533636 | W98: 0.01 | X98: =X$13/W$13*W98 -> 0.30533636 | Y98: =M98+O98+Q98+S98+U98+W98 -> 0.08 | Z98: =N98+P98+R98+T98+V98+X98 -> 2.4426909 | AB98: =AB$13/AA$13*AA98 -> 0 | AD98: =AD$13/AC$13*AC98 -> 0 | AF98: =AF$13/AE$13*AE98 -> 0 | AH98: =AH$13/AG$13*AG98 -> 0 | AJ98: =AJ$13/AI$13*AI98 -> 0 | AL98: =AL$13/AK$13*AK98 -> 0 | AM98: =AA98+AC98+AE98+AG98+AK98 -> 0 | AN98: =AB98+AD98+AF98+AH98+AL98 -> 0 | AP98: =AP$13/AO$13*AO98 -> 0 | AQ98: =AO98 -> 0 | AR98: =AP98 -> 0 | AS98: =K98+Y98+AM98+AQ98 -> 0.09 | AT98: =L98+Z98+AN98+AR98 -> 4.2501909 | AU98: - | AV98: =IF(AU98="●",AT98,0) -> 0
C99: 86 | D99: プランテーブル修正 | E99: 生産管理課へ修正計画を盛り込んだプランテーブルを送付 | F99: 週次 | G99: 0.01 | H99: =H$13/G$13*G99 -> 1.8075 | K99: =G99+I99 -> 0.01 | L99: =H99+J99 -> 1.8075 | M99: 0.02 | N99: =N$13/M$13*M99 -> 0.61067273 | O99: 0 | P99: =P$13/O$13*O99 -> 0 | Q99: 0 | R99: =R$13/Q$13*Q99 -> 0 | S99: 0 | T99: =T$13/S$13*S99 -> 0 | U99: 0 | V99: =V$13/U$13*U99 -> 0 | W99: 0 | X99: =X$13/W$13*W99 -> 0 | Y99: =M99+O99+Q99+S99+U99+W99 -> 0.02 | Z99: =N99+P99+R99+T99+V99+X99 -> 0.61067273 | AB99: =AB$13/AA$13*AA99 -> 0 | AD99: =AD$13/AC$13*AC99 -> 0 | AF99: =AF$13/AE$13*AE99 -> 0 | AH99: =AH$13/AG$13*AG99 -> 0 | AJ99: =AJ$13/AI$13*AI99 -> 0 | AL99: =AL$13/AK$13*AK99 -> 0 | AM99: =AA99+AC99+AE99+AG99+AK99 -> 0 | AN99: =AB99+AD99+AF99+AH99+AL99 -> 0 | AP99: =AP$13/AO$13*AO99 -> 0 | AQ99: =AO99 -> 0 | AR99: =AP99 -> 0 | AS99: =K99+Y99+AM99+AQ99 -> 0.03 | AT99: =L99+Z99+AN99+AR99 -> 2.4181727 | AU99: - | AV99: =IF(AU99="●",AT99,0) -> 0
C100: 87 | D100: Update修正内容確認 | E100: 計画修正されたUpdateとプランテーブルの照合 | F100: 週次 | G100: 0.05 | H100: =H$13/G$13*G100 -> 9.0375 | K100: =G100+I100 -> 0.05 | L100: =H100+J100 -> 9.0375 | M100: 0.03 | N100: =N$13/M$13*M100 -> 0.91600909 | O100: 0.02 | P100: =P$13/O$13*O100 -> 0.61067273 | Q100: 0.02 | R100: =R$13/Q$13*Q100 -> 0.61067273 | S100: 0.02 | T100: =T$13/S$13*S100 -> 0.61067273 | U100: 0.02 | V100: =V$13/U$13*U100 -> 0.61067273 | W100: 0.02 | X100: =X$13/W$13*W100 -> 0.61067273 | Y100: =M100+O100+Q100+S100+U100+W100 -> 0.13 | Z100: =N100+P100+R100+T100+V100+X100 -> 3.9693727 | AB100: =AB$13/AA$13*AA100 -> 0 | AD100: =AD$13/AC$13*AC100 -> 0 | AF100: =AF$13/AE$13*AE100 -> 0 | AH100: =AH$13/AG$13*AG100 -> 0 | AJ100: =AJ$13/AI$13*AI100 -> 0 | AL100: =AL$13/AK$13*AK100 -> 0 | AM100: =AA100+AC100+AE100+AG100+AK100 -> 0 | AN100: =AB100+AD100+AF100+AH100+AL100 -> 0 | AP100: =AP$13/AO$13*AO100 -> 0 | AQ100: =AO100 -> 0 | AR100: =AP100 -> 0 | AS100: =K100+Y100+AM100+AQ100 -> 0.18 | AT100: =L100+Z100+AN100+AR100 -> 13.006873 | AU100: - | AV100: =IF(AU100="●",AT100,0) -> 0
...

Sheet 参考a_年間支払額(2024予算策定）USD表記
B1: TIVNへの生産管理業委託費予算（案）2024年度 | AE1: 45271
B2: 【ベトナム人】 | D2: APIC | I2: BTNB | N2: APIC+BTNB 合計 | S2: TIVN QN | X2: TIVN HCM | AC2: 直課業務委託費計
B3: （単位：千US$） | D3: 23予 | E3: 23実 | F3: 24予 | G3: 差異 | H3: 率 | I3: 23予 | J3: 23実 | K3: 24予 | L3: 差異 | M3: 率 | N3: 23予 | O3: 23実 | P3: 24予 | Q3: 差異 | R3: 率 | S3: 23予 | T3: 23実 | U3: 24予 | V3: 差異 | W3: 率 | X3: 23予 | Y3: 23実 | Z3: 24予 | AA3: 差異 | AB3: 率 | AC3: 23予 | AD3: 23実 | AE3: 24予 | AF3: 差異 | AG3: 率
D4: A | E4: B | F4: C | G4: C-B | H4: C/B | I4: A | J4: B | K4: C | L4: C-B | M4: C/B | N4: A | O4: B | P4: C | Q4: C-B | R4: C/B | S4: A | T4: B | U4: C | V4: C-B | W4: C/B | X4: A | Y4: B | Z4: C | AA4: C-B | AB4: C/B | AC4: A | AD4: B | AE4: C | AF4: C-B | AG4: C/B
B5: 要員数（人） | D5: 12 | E5: =D5 -> 12 | F5: 13 | G5: =+F5-E5 -> 1 | H5: =IF(E5=0,"",F5/E5) -> 1.0833333 | I5: 10 | J5: =I5 -> 10 | K5: 12 | L5: =+K5-J5 -> 2 | M5: =IF(J5=0,"",K5/J5) -> 1.2 | N5: =+I5+D5 -> 22 | O5: =+J5+E5 -> 22 | P5: =+K5+F5 -> 25 | Q5: =+L5+G5 -> 3 | R5: =IF(O5=0,"",P5/O5) -> 1.1363636 | S5: 0 | T5: =S5 -> 0 | U5: 0 | V5: =+U5-T5 -> 0 | W5: =IF(T5=0,"",U5/T5) | X5: 0 | Y5: =X5 -> 0 | Z5: 0 | AA5: =+Z5-Y5 -> 0 | AB5: =IF(Y5=0,"",Z5/Y5) | AC5: =+N5+S5+X5 -> 22 | AD5: =+O5+T5+Y5 -> 22 | AE5: =+P5+U5+Z5 -> 25 | AF5: =AE5-AD5 -> 3 | AG5: =IF(AD5=0,"",AE5/AD5) -> 1.1363636
F6: 賃金=23年予算比7％UP | K6: 賃金=23年予算比7％UP
B7: 賃金 | D7: 216.8406 | E7: =D7 -> 216.8406 | F7: 221.36 | G7: =+F7-E7 -> 4.5193996 | H7: =IF(E7=0,"",F7/E7) -> 1.020842 | I7: 194.25667 | J7: =I7 -> 194.25667 | K7: 230.33 | L7: =+K7-J7 -> 36.073334 | M7: =IF(J7=0,"",K7/J7) -> 1.1856993 | N7: =+I7+D7 -> 411.09727 | O7: =+J7+E7 -> 411.09727 | P7: =+K7+F7 -> 451.69 | Q7: =+L7+G7 -> 40.592733 | R7: =IF(O7=0,"",P7/O7) -> 1.0987424 | S7: 0 | T7: =S7 -> 0 | U7: 0 | V7: =+U7-T7 -> 0 | W7: =IF(T7=0,"",U7/T7) | X7: 0 | Y7: =X7 -> 0 | Z7: 0 | AA7: =+Z7-Y7 -> 0 | AB7: =IF(Y7=0,"",Z7/Y7) | AC7: =+N7+S7+X7 -> 411.09727 | AD7: =+O7+T7+Y7 -> 411.09727 | AE7: =+P7+U7+Z7 -> 451.69 | AF7: =AE7-AD7 -> 40.592733 | AG7: =IF(AD7=0,"",AE7/AD7) -> 1.0987424
B8: 社会保険 | D8: 33.565217 | E8: =D8 -> 33.565217 | F8: 33.6 | G8: =+F8-E8 -> 0.034782609 | H8: =IF(E8=0,"",F8/E8) -> 1.0010363 | I8: 30.869565 | J8: =I8 -> 30.869565 | K8: 30.87 | L8: =+K8-J8 -> 0.00043478261 | M8: =IF(J8=0,"",K8/J8) -> 1.0000141 | N8: =+I8+D8 -> 64.434783 | O8: =+J8+E8 -> 64.434783 | P8: =+K8+F8 -> 64.47 | Q8: =+L8+G8 -> 0.035217391 | R8: =IF(O8=0,"",P8/O8) -> 1.0005466 | S8: 0 | T8: =S8 -> 0 | U8: 0 | V8: =+U8-T8 -> 0 | W8: =IF(T8=0,"",U8/T8) | X8: 0 | Y8: =X8 -> 0 | Z8: 0 | AA8: =+Z8-Y8 -> 0 | AB8: =IF(Y8=0,"",Z8/Y8) | AC8: =+N8+S8+X8 -> 64.434783 | AD8: =+O8+T8+Y8 -> 64.434783 | AE8: =+P8+U8+Z8 -> 64.47 | AF8: =AE8-AD8 -> 0.035217391 | AG8: =IF(AD8=0,"",AE8/AD8) -> 1.0005466
B9: 福利厚生費 | D9: 11.869565 | E9: =D9 -> 11.869565 | F9: 11.87 | G9: =+F9-E9 -> 0.00043478261 | H9: =IF(E9=0,"",F9/E9) -> 1.0000366 | I9: 32.173913 | J9: =I9 -> 32.173913 | K9: 32.17 | L9: =+K9-J9 -> -0.0039130435 | M9: =IF(J9=0,"",K9/J9) -> 0.99987838 | N9: =+I9+D9 -> 44.043478 | O9: =+J9+E9 -> 44.043478 | P9: =+K9+F9 -> 44.04 | Q9: =+L9+G9 -> -0.0034782609 | R9: =IF(O9=0,"",P9/O9) -> 0.99992103 | S9: 0 | T9: =S9 -> 0 | U9: 0 | V9: =+U9-T9 -> 0 | W9: =IF(T9=0,"",U9/T9) | X9: 0 | Y9: =X9 -> 0 | Z9: 0 | AA9: =+Z9-Y9 -> 0 | AB9: =IF(Y9=0,"",Z9/Y9) | AC9: =+N9+S9+X9 -> 44.043478 | AD9: =+O9+T9+Y9 -> 44.043478 | AE9: =+P9+U9+Z9 -> 44.04 | AF9: =AE9-AD9 -> -0.0034782609 | AG9: =IF(AD9=0,"",AE9/AD9) -> 0.99992103
B10: 労務費計 | D10: =SUM(D7:D9) -> 262.27538 | E10: =SUM(E7:E9) -> 262.27538 | F10: =SUM(F7:F9) -> 266.83 | G10: =+F10-E10 -> 4.554617 | H10: =IF(E10=0,"",F10/E10) -> 1.0173658 | I10: =SUM(I7:I9) -> 257.30014 | J10: =SUM(J7:J9) -> 257.30014 | K10: =SUM(K7:K9) -> 293.37 | L10: =+K10-J10 -> 36.069855 | M10: =IF(J10=0,"",K10/J10) -> 1.1401859 | N10: =+I10+D10 -> 519.57553 | O10: =+J10+E10 -> 519.57553 | P10: =+K10+F10 -> 560.2 | Q10: =+L10+G10 -> 40.624472 | R10: =IF(O10=0,"",P10/O10) -> 1.0781878 | S10: =SUM(S7:S9) -> 0 | T10: =SUM(T7:T9) -> 0 | U10: =SUM(U7:U9) -> 0 | V10: =+U10-T10 -> 0 | W10: =IF(T10=0,"",U10/T10) | X10: =SUM(X7:X9) -> 0 | Y10: =SUM(Y7:Y9) -> 0 | Z10: =SUM(Z7:Z9) -> 0 | AA10: =+Z10-Y10 -> 0 | AB10: =IF(Y10=0,"",Z10/Y10) | AC10: =+N10+S10+X10 -> 519.57553 | AD10: =+O10+T10+Y10 -> 519.57553 | AE10: =+P10+U10+Z10 -> 560.2 | AF10: =AE10-AD10 -> 40.624472 | AG10: =IF(AD10=0,"",AE10/AD10) -> 1.0781878
B12: 海外旅費 | D12: 0 | E12: =D12 -> 0 | F12: =E12 -> 0 | G12: =+F12-E12 -> 0 | H12: =IF(E12=0,"",F12/E12) | I12: 0 | J12: =I12 -> 0 | K12: =J12 -> 0 | L12: =+K12-J12 -> 0 | M12: =IF(J12=0,"",K12/J12) | N12: =+I12+D12 -> 0 | O12: =+J12+E12 -> 0 | P12: =+K12+F12 -> 0 | Q12: =+L12+G12 -> 0 | R12: =IF(O12=0,"",P12/O12) | S12: 0 | T12: =S12 -> 0 | U12: 0 | V12: =+U12-T12 -> 0 | W12: =IF(T12=0,"",U12/T12) | X12: 0 | Y12: =X12 -> 0 | Z12: 0 | AA12: =+Z12-Y12 -> 0 | AB12: =IF(Y12=0,"",Z12/Y12) | AC12: =+N12+S12+X12 -> 0 | AD12: =+O12+T12+Y12 -> 0 | AE12: =+P12+U12+Z12 -> 0 | AF12: =AE12-AD12 -> 0 | AG12: =IF(AD12=0,"",AE12/AD12)
B13: 国内旅費 | D13: 2.826087 | E13: =D13 -> 2.826087 | F13: 6 | G13: =+F13-E13 -> 3.173913 | H13: =IF(E13=0,"",F13/E13) -> 2.1230769 | I13: 3.1956522 | J13: =I13 -> 3.1956522 | K13: 0 | L13: =+K13-J13 -> -3.1956522 | M13: =IF(J13=0,"",K13/J13) -> 0 | N13: =+I13+D13 -> 6.0217391 | O13: =+J13+E13 -> 6.0217391 | P13: =+K13+F13 -> 6 | Q13: =+L13+G13 -> -0.02173913 | R13: =IF(O13=0,"",P13/O13) -> 0.99638989 | S13: 0 | T13: =S13 -> 0 | U13: 0 | V13: =+U13-T13 -> 0 | W13: =IF(T13=0,"",U13/T13) | X13: 0 | Y13: =X13 -> 0 | Z13: 0 | AA13: =+Z13-Y13 -> 0 | AB13: =IF(Y13=0,"",Z13/Y13) | AC13: =+N13+S13+X13 -> 6.0217391 | AD13: =+O13+T13+Y13 -> 6.0217391 | AE13: =+P13+U13+Z13 -> 6 | AF13: =AE13-AD13 -> -0.02173913 | AG13: =IF(AD13=0,"",AE13/AD13) -> 0.99638989
B14: 交際・会議費 | D14: 0.65217391 | E14: =D14 -> 0.65217391 | F14: 0.5 | G14: =+F14-E14 -> -0.15217391 | H14: =IF(E14=0,"",F14/E14) -> 0.76666667 | I14: 1.3913043 | J14: =I14 -> 1.3913043 | K14: 4.5 | L14: =+K14-J14 -> 3.1086957 | M14: =IF(J14=0,"",K14/J14) -> 3.234375 | N14: =+I14+D14 -> 2.0434783 | O14: =+J14+E14 -> 2.0434783 | P14: =+K14+F14 -> 5 | Q14: =+L14+G14 -> 2.9565217 | R14: =IF(O14=0,"",P14/O14) -> 2.4468085 | S14: 0 | T14: =S14 -> 0 | U14: 0 | V14: =+U14-T14 -> 0 | W14: =IF(T14=0,"",U14/T14) | X14: 0 | Y14: =X14 -> 0 | Z14: 0 | AA14: =+Z14-Y14 -> 0 | AB14: =IF(Y14=0,"",Z14/Y14) | AC14: =+N14+S14+X14 -> 2.0434783 | AD14: =+O14+T14+Y14 -> 2.0434783 | AE14: =+P14+U14+Z14 -> 5 | AF14: =AE14-AD14 -> 2.9565217 | AG14: =IF(AD14=0,"",AE14/AD14) -> 2.4468085
B15: 査定経費計 | D15: =SUM(D12:D14) -> 3.4782609 | E15: =SUM(E12:E14) -> 3.4782609 | F15: =SUM(F12:F14) -> 6.5 | G15: =+F15-E15 -> 3.0217391 | H15: =IF(E15=0,"",F15/E15) -> 1.86875 | I15: =SUM(I12:I14) -> 4.5869565 | J15: =SUM(J12:J14) -> 4.5869565 | K15: =SUM(K12:K14) -> 4.5 | L15: =+K15-J15 -> -0.086956522 | M15: =IF(J15=0,"",K15/J15) -> 0.98104265 | N15: =+I15+D15 -> 8.0652174 | O15: =+J15+E15 -> 8.0652174 | P15: =+K15+F15 -> 11 | Q15: =+L15+G15 -> 2.9347826 | R15: =IF(O15=0,"",P15/O15) -> 1.3638814 | S15: =SUM(S12:S14) -> 0 | T15: =SUM(T12:T14) -> 0 | U15: =SUM(U12:U14) -> 0 | V15: =+U15-T15 -> 0 | W15: =IF(T15=0,"",U15/T15) | X15: =SUM(X12:X14) -> 0 | Y15: =SUM(Y12:Y14) -> 0 | Z15: =SUM(Z12:Z14) -> 0 | AA15: =+Z15-Y15 -> 0 | AB15: =IF(Y15=0,"",Z15/Y15) | AC15: =+N15+S15+X15 -> 8.0652174 | AD15: =+O15+T15+Y15 -> 8.0652174 | AE15: =+P15+U15+Z15 -> 11 | AF15: =AE15-AD15 -> 2.9347826 | AG15: =IF(AD15=0,"",AE15/AD15) -> 1.3638814
B17: 通信費 | D17: 6.2608696 | E17: =D17 -> 6.2608696 | F17: 2.5 | G17: =+F17-E17 -> -3.7608696 | H17: =IF(E17=0,"",F17/E17) -> 0.39930556 | I17: 7.4782609 | J17: =I17 -> 7.4782609 | K17: 2 | L17: =+K17-J17 -> -5.4782609 | M17: =IF(J17=0,"",K17/J17) -> 0.26744186 | N17: =+I17+D17 -> 13.73913 | O17: =+J17+E17 -> 13.73913 | P17: =+K17+F17 -> 4.5 | Q17: =+L17+G17 -> -9.2391304 | R17: =IF(O17=0,"",P17/O17) -> 0.32753165 | S17: 0 | T17: =S17 -> 0 | U17: 0 | V17: =+U17-T17 -> 0 | W17: =IF(T17=0,"",U17/T17) | X17: 0 | Y17: =X17 -> 0 | Z17: 0 | AA17: =+Z17-Y17 -> 0 | AB17: =IF(Y17=0,"",Z17/Y17) | AC17: =+N17+S17+X17 -> 13.73913 | AD17: =+O17+T17+Y17 -> 13.73913 | AE17: =+P17+U17+Z17 -> 4.5 | AF17: =AE17-AD17 -> -9.2391304 | AG17: =IF(AD17=0,"",AE17/AD17) -> 0.32753165
B18: レンタカー | D18: 0.86956522 | E18: =D18 -> 0.86956522 | F18: 0 | G18: =+F18-E18 -> -0.86956522 | H18: =IF(E18=0,"",F18/E18) -> 0 | I18: 11 | J18: =I18 -> 11 | K18: 10 | L18: =+K18-J18 -> -1 | M18: =IF(J18=0,"",K18/J18) -> 0.90909091 | N18: =+I18+D18 -> 11.869565 | O18: =+J18+E18 -> 11.869565 | P18: =+K18+F18 -> 10 | Q18: =+L18+G18 -> -1.8695652 | R18: =IF(O18=0,"",P18/O18) -> 0.84249084 | S18: 0 | T18: =S18 -> 0 | U18: 0 | V18: =+U18-T18 -> 0 | W18: =IF(T18=0,"",U18/T18) | X18: 0 | Y18: =X18 -> 0 | Z18: 0 | AA18: =+Z18-Y18 -> 0 | AB18: =IF(Y18=0,"",Z18/Y18) | AC18: =+N18+S18+X18 -> 11.869565 | AD18: =+O18+T18+Y18 -> 11.869565 | AE18: =+P18+U18+Z18 -> 10 | AF18: =AE18-AD18 -> -1.8695652 | AG18: =IF(AD18=0,"",AE18/AD18) -> 0.84249084
B19: 光熱費 | D19: 0 | E19: =D19 -> 0 | F19: =E19 -> 0 | G19: =+F19-E19 -> 0 | H19: =IF(E19=0,"",F19/E19) | I19: 0 | J19: =I19 -> 0 | K19: =J19 -> 0 | L19: =+K19-J19 -> 0 | M19: =IF(J19=0,"",K19/J19) | N19: =+I19+D19 -> 0 | O19: =+J19+E19 -> 0 | P19: =+K19+F19 -> 0 | Q19: =+L19+G19 -> 0 | R19: =IF(O19=0,"",P19/O19) | S19: 0 | T19: =S19 -> 0 | U19: 0 | V19: =+U19-T19 -> 0 | W19: =IF(T19=0,"",U19/T19) | X19: 0 | Y19: =X19 -> 0 | Z19: 0 | AA19: =+Z19-Y19 -> 0 | AB19: =IF(Y19=0,"",Z19/Y19) | AC19: =+N19+S19+X19 -> 0 | AD19: =+O19+T19+Y19 -> 0 | AE19: =+P19+U19+Z19 -> 0 | AF19: =AE19-AD19 -> 0 | AG19: =IF(AD19=0,"",AE19/AD19)
B20: リース・保守 | D20: 0 | E20: =D20 -> 0 | F20: 5 | G20: =+F20-E20 -> 5 | H20: =IF(E20=0,"",F20/E20) | I20: 5.4782609 | J20: =I20 -> 5.4782609 | K20: 12.5 | L20: =+K20-J20 -> 7.0217391 | M20: =IF(J20=0,"",K20/J20) -> 2.281746 | N20: =+I20+D20 -> 5.4782609 | O20: =+J20+E20 -> 5.4782609 | P20: =+K20+F20 -> 17.5 | Q20: =+L20+G20 -> 12.021739 | R20: =IF(O20=0,"",P20/O20) -> 3.1944444 | S20: 0 | T20: =S20 -> 0 | U20: 0 | V20: =+U20-T20 -> 0 | W20: =IF(T20=0,"",U20/T20) | X20: 0 | Y20: =X20 -> 0 | Z20: 0 | AA20: =+Z20-Y20 -> 0 | AB20: =IF(Y20=0,"",Z20/Y20) | AC20: =+N20+S20+X20 -> 5.4782609 | AD20: =+O20+T20+Y20 -> 5.4782609 | AE20: =+P20+U20+Z20 -> 17.5 | AF20: =AE20-AD20 -> 12.021739 | AG20: =IF(AD20=0,"",AE20/AD20) -> 3.1944444
B21: 消耗品費 | D21: 1.8695652 | E21: =D21 -> 1.8695652 | F21: 0 | G21: =+F21-E21 -> -1.8695652 | H21: =IF(E21=0,"",F21/E21) -> 0 | I21: 0.52173913 | J21: =I21 -> 0.52173913 | K21: 0 | L21: =+K21-J21 -> -0.52173913 | M21: =IF(J21=0,"",K21/J21) -> 0 | N21: =+I21+D21 -> 2.3913043 | O21: =+J21+E21 -> 2.3913043 | P21: =+K21+F21 -> 0 | Q21: =+L21+G21 -> -2.3913043 | R21: =IF(O21=0,"",P21/O21) -> 0 | S21: 0 | T21: =S21 -> 0 | U21: 0 | V21: =+U21-T21 -> 0 | W21: =IF(T21=0,"",U21/T21) | X21: 0 | Y21: =X21 -> 0 | Z21: 0 | AA21: =+Z21-Y21 -> 0 | AB21: =IF(Y21=0,"",Z21/Y21) | AC21: =+N21+S21+X21 -> 2.3913043 | AD21: =+O21+T21+Y21 -> 2.3913043 | AE21: =+P21+U21+Z21 -> 0 | AF21: =AE21-AD21 -> -2.3913043 | AG21: =IF(AD21=0,"",AE21/AD21) -> 0
B22: 雑費 | D22: 0.60869565 | E22: =D22 -> 0.60869565 | F22: 5 | G22: =+F22-E22 -> 4.3913043 | H22: =IF(E22=0,"",F22/E22) -> 8.2142857 | I22: 2.2826087 | J22: =I22 -> 2.2826087 | K22: 5 | L22: =+K22-J22 -> 2.7173913 | M22: =IF(J22=0,"",K22/J22) -> 2.1904762 | N22: =+I22+D22 -> 2.8913043 | O22: =+J22+E22 -> 2.8913043 | P22: =+K22+F22 -> 10 | Q22: =+L22+G22 -> 7.1086957 | R22: =IF(O22=0,"",P22/O22) -> 3.4586466 | S22: 0 | T22: =S22 -> 0 | U22: 0 | V22: =+U22-T22 -> 0 | W22: =IF(T22=0,"",U22/T22) | X22: 0 | Y22: =X22 -> 0 | Z22: 0 | AA22: =+Z22-Y22 -> 0 | AB22: =IF(Y22=0,"",Z22/Y22) | AC22: =+N22+S22+X22 -> 2.8913043 | AD22: =+O22+T22+Y22 -> 2.8913043 | AE22: =+P22+U22+Z22 -> 10 | AF22: =AE22-AD22 -> 7.1086957 | AG22: =IF(AD22=0,"",AE22/AD22) -> 3.4586466
B23: その他 | D23: 0 | E23: =D23 -> 0 | F23: 10 | G23: =+F23-E23 -> 10 | H23: =IF(E23=0,"",F23/E23) | I23: 0 | J23: =I23 -> 0 | K23: 8.5 | L23: =+K23-J23 -> 8.5 | M23: =IF(J23=0,"",K23/J23) | N23: =+I23+D23 -> 0 | O23: =+J23+E23 -> 0 | P23: =+K23+F23 -> 18.5 | Q23: =+L23+G23 -> 18.5 | R23: =IF(O23=0,"",P23/O23) | S23: 0 | T23: =S23 -> 0 | U23: 0 | V23: =+U23-T23 -> 0 | W23: =IF(T23=0,"",U23/T23) | X23: 0 | Y23: =X23 -> 0 | Z23: 0 | AA23: =+Z23-Y23 -> 0 | AB23: =IF(Y23=0,"",Z23/Y23) | AC23: =+N23+S23+X23 -> 0 | AD23: =+O23+T23+Y23 -> 0 | AE23: =+P23+U23+Z23 -> 18.5 | AF23: =AE23-AD23 -> 18.5 | AG23: =IF(AD23=0,"",AE23/AD23)
B24: 一般経費計 | D24: =SUM(D17:D23) -> 9.6086957 | E24: =SUM(E17:E23) -> 9.6086957 | F24: =SUM(F17:F23) -> 22.5 | G24: =+F24-E24 -> 12.891304 | H24: =IF(E24=0,"",F24/E24) -> 2.341629 | I24: =SUM(I17:I23) -> 26.76087 | J24: =SUM(J17:J23) -> 26.76087 | K24: =SUM(K17:K23) -> 38 | L24: =+K24-J24 -> 11.23913 | M24: =IF(J24=0,"",K24/J24) -> 1.4199838 | N24: =+I24+D24 -> 36.369565 | O24: =+J24+E24 -> 36.369565 | P24: =+K24+F24 -> 60.5 | Q24: =+L24+G24 -> 24.130435 | R24: =IF(O24=0,"",P24/O24) -> 1.6634788 | S24: =SUM(S17:S23) -> 0 | T24: =SUM(T17:T23) -> 0 | U24: =SUM(U17:U23) -> 0 | V24: =+U24-T24 -> 0 | W24: =IF(T24=0,"",U24/T24) | X24: =SUM(X17:X23) -> 0 | Y24: =SUM(Y17:Y23) -> 0 | Z24: =SUM(Z17:Z23) -> 0 | AA24: =+Z24-Y24 -> 0 | AB24: =IF(Y24=0,"",Z24/Y24) | AC24: =+N24+S24+X24 -> 36.369565 | AD24: =+O24+T24+Y24 -> 36.369565 | AE24: =+P24+U24+Z24 -> 60.5 | AF24: =AE24-AD24 -> 24.130435 | AG24: =IF(AD24=0,"",AE24/AD24) -> 1.6634788
B25: 経費合計 | D25: =+D10+D15+D24 -> 275.36234 | E25: =+E10+E15+E24 -> 275.36234 | F25: =+F10+F15+F24 -> 295.83 | G25: =+F25-E25 -> 20.46766 | H25: =IF(E25=0,"",F25/E25) -> 1.0743299 | I25: =+I10+I15+I24 -> 288.64797 | J25: =+J10+J15+J24 -> 288.64797 | K25: =+K10+K15+K24 -> 335.87 | L25: =+K25-J25 -> 47.222029 | M25: =IF(J25=0,"",K25/J25) -> 1.1635973 | N25: =+I25+D25 -> 564.01031 | O25: =+J25+E25 -> 564.01031 | P25: =+K25+F25 -> 631.7 | Q25: =+L25+G25 -> 67.68969 | R25: =IF(O25=0,"",P25/O25) -> 1.120015 | S25: =+S10+S15+S24 -> 0 | T25: =+T10+T15+T24 -> 0 | U25: =+U10+U15+U24 -> 0 | V25: =+U25-T25 -> 0 | W25: =IF(T25=0,"",U25/T25) | X25: =+X10+X15+X24 -> 0 | Y25: =+Y10+Y15+Y24 -> 0 | Z25: =+Z10+Z15+Z24 -> 0 | AA25: =+Z25-Y25 -> 0 | AB25: =IF(Y25=0,"",Z25/Y25) | AC25: =+N25+S25+X25 -> 564.01031 | AD25: =+O25+T25+Y25 -> 564.01031 | AE25: =+P25+U25+Z25 -> 631.7 | AF25: =AE25-AD25 -> 67.68969 | AG25: =IF(AD25=0,"",AE25/AD25) -> 1.120015
B27: 【日本人】 | D27: APIC | I27: BTNB | N27: APIC+BTNB 合計 | S27: TIVN QN | X27: TIVN HCM | AC27: 直課業務委託費計
B28: （単位：千US$） | D28: 23予 | E28: 23実 | F28: 24予 | G28: 差異 | H28: 率 | I28: 23予 | J28: 23実 | K28: 24予 | L28: 差異 | M28: 率 | N28: 23予 | O28: 23実 | P28: 24予 | Q28: 差異 | R28: 率 | S28: 23予 | T28: 23実 | U28: 24予 | V28: 差異 | W28: 率 | X28: 23予 | Y28: 23実 | Z28: 24予 | AA28: 差異 | AB28: 率 | AC28: 23予 | AD28: 23実 | AE28: 24予 | AF28: 差異 | AG28: 率
D29: A | E29: B | F29: C | G29: C-B | I29: A | J29: B | K29: C | L29: C-B | N29: A | O29: B | P29: C | Q29: C-B | S29: A | T29: B | U29: C | V29: C-B | X29: A | Y29: B | Z29: C | AA29: C-B | AC29: A | AD29: B | AE29: C | AF29: C-B | AG29: C/B
B30: 要員数（人） | D30: 1 | E30: =D30 -> 1 | F30: 0 | G30: =+F30-E30 -> -1 | H30: =IF(E30=0,"",F30/E30) -> 0 | I30: 1 | J30: =I30 -> 1 | K30: 0 | L30: =+K30-J30 -> -1 | M30: =IF(J30=0,"",K30/J30) -> 0 | N30: =+I30+D30 -> 2 | O30: =+J30+E30 -> 2 | P30: =+K30+F30 -> 0 | Q30: =+L30+G30 -> -2 | R30: =IF(O30=0,"",P30/O30) -> 0 | S30: 3 | T30: =S30 -> 3 | U30: 3 | V30: =+U30-T30 -> 0 | W30: =IF(T30=0,"",U30/T30) -> 1 | X30: 3 | Y30: =X30 -> 3 | Z30: 4 | AA30: =+Z30-Y30 -> 1 | AB30: =IF(Y30=0,"",Z30/Y30) -> 1.3333333 | AC30: =+N30+S30+X30 -> 8 | AD30: =+O30+T30+Y30 -> 8 | AE30: =+P30+U30+Z30 -> 7 | AF30: =AE30-AD30 -> -1 | AG30: =IF(AD30=0,"",AE30/AD30) -> 0.875
D31: 常駐業務委託者なし | I31: 常駐業務委託者なし | U31: 荒谷 天方 新規1名 | Z31: 泉 井上 内藤 堀
B32: 業務委託料（給与） | D32: 50.4 | E32: =D32 -> 50.4 | F32: 0 | G32: =+F32-E32 -> -50.4 | H32: =IF(E32=0,"",F32/E32) -> 0 | I32: 57.6 | J32: =I32 -> 57.6 | K32: 0 | L32: =+K32-J32 -> -57.6 | M32: =IF(J32=0,"",K32/J32) -> 0 | N32: =+I32+D32 -> 108 | O32: =+J32+E32 -> 108 | P32: =+K32+F32 -> 0 | Q32: =+L32+G32 -> -108 | R32: =IF(O32=0,"",P32/O32) -> 0 | S32: 160 | T32: =S32 -> 160 | U32: 192.174 | W32: =IF(T32=0,"",U32/T32) -> 1.2010875 | X32: 393.89939 | Y32: =X32 -> 393.89939 | Z32: 588 | AB32: =IF(Y32=0,"",Z32/Y32) -> 1.492767 | AC32: =+N32+S32+X32 -> 661.89939 | AD32: =+O32+T32+Y32 -> 661.89939 | AE32: =+P32+U32+Z32 -> 780.174 | AF32: =AE32-AD32 -> 118.27461 | AG32: =IF(AD32=0,"",AE32/AD32) -> 1.1786897
B33: 所得税（全世界） | D33: 19.458 | E33: =D33 -> 19.458 | F33: 0 | G33: =+F33-E33 -> -19.458 | H33: =IF(E33=0,"",F33/E33) -> 0 | I33: 21.942 | J33: =I33 -> 21.942 | K33: 0 | L33: =+K33-J33 -> -21.942 | M33: =IF(J33=0,"",K33/J33) -> 0 | N33: =+I33+D33 -> 41.4 | O33: =+J33+E33 -> 41.4 | P33: =+K33+F33 -> 0 | Q33: =+L33+G33 -> -41.4 | R33: =IF(O33=0,"",P33/O33) -> 0 | S33: 62.1 | T33: =S33 -> 62.1 | U33: 94.085 | W33: =IF(T33=0,"",U33/T33) -> 1.5150564 | X33: 160.73529 | Y33: =X33 -> 160.73529 | AB33: =IF(Y33=0,"",Z33/Y33) -> 0 | AC33: =+N33+S33+X33 -> 264.23529 | AD33: =+O33+T33+Y33 -> 264.23529 | AE33: =+P33+U33+Z33 -> 94.085 | AF33: =AE33-AD33 -> -170.15029 | AG33: =IF(AD33=0,"",AE33/AD33) -> 0.35606523
B34: 委託料以外諸費用 | D34: 17.712 | E34: =D34 -> 17.712 | F34: 0 | G34: =+F34-E34 -> -17.712 | H34: =IF(E34=0,"",F34/E34) -> 0 | I34: 10.512 | J34: =I34 -> 10.512 | K34: 0 | L34: =+K34-J34 -> -10.512 | M34: =IF(J34=0,"",K34/J34) -> 0 | N34: =+I34+D34 -> 28.224 | O34: =+J34+E34 -> 28.224 | P34: =+K34+F34 -> 0 | Q34: =+L34+G34 -> -28.224 | R34: =IF(O34=0,"",P34/O34) -> 0 | W34: =IF(T34=0,"",U34/T34) | AB34: =IF(Y34=0,"",Z34/Y34) | AC34: =+N34+S34+X34 -> 28.224 | AD34: =+O34+T34+Y34 -> 28.224 | AE34: =+P34+U34+Z34 -> 0 | AF34: =AE34-AD34 -> -28.224 | AG34: =IF(AD34=0,"",AE34/AD34) -> 0
B35: 外国人契約税 | D35: 10.109 | E35: =D35 -> 10.109 | F35: 0 | G35: =+F35-E35 -> -10.109 | H35: =IF(E35=0,"",F35/E35) -> 0 | I35: 10.377 | J35: =I35 -> 10.377 | K35: 0 | L35: =+K35-J35 -> -10.377 | M35: =IF(J35=0,"",K35/J35) -> 0 | N35: =+I35+D35 -> 20.486 | O35: =+J35+E35 -> 20.486 | P35: =+K35+F35 -> 0 | Q35: =+L35+G35 -> -20.486 | R35: =IF(O35=0,"",P35/O35) -> 0 | W35: =IF(T35=0,"",U35/T35) | AB35: =IF(Y35=0,"",Z35/Y35) | AC35: =+N35+S35+X35 -> 20.486 | AD35: =+O35+T35+Y35 -> 20.486 | AE35: =+P35+U35+Z35 -> 0 | AF35: =AE35-AD35 -> -20.486 | AG35: =IF(AD35=0,"",AE35/AD35) -> 0
F36: =SUM(F32:F35) -> 0 | I36: =SUM(I32:I35) -> 100.431 | J36: =SUM(J32:J35) -> 100.431 | K36: =SUM(K32:K35) -> 0 | L36: =+K36-J36 -> -100.431 | P36: =SUM(P32:P35) -> 0 | U36: =SUM(U32:U35) -> 286.259 | Z36: =SUM(Z32:Z35) -> 588 | AE36: =SUM(AE32:AE35) -> 874.259
B37: アパート家賃 | D37: 6 | E37: =D37 -> 6 | F37: 0 | G37: =+F37-E37 -> -6 | H37: =IF(E37=0,"",F37/E37) -> 0 | I37: 6 | J37: =I37 -> 6 | K37: 0 | L37: =+K37-J37 -> -6 | M37: =IF(J37=0,"",K37/J37) -> 0 | N37: =+I37+D37 -> 12 | O37: =+J37+E37 -> 12 | P37: =+K37+F37 -> 0 | Q37: =+L37+G37 -> -12 | R37: =IF(O37=0,"",P37/O37) -> 0 | S37: 20 | T37: =S37 -> 20 | U37: 45.75 | V37: =+U37-T37 -> 25.75 | W37: =IF(T37=0,"",U37/T37) -> 2.2875 | X37: 72 | Y37: =X37 -> 72 | AA37: =+Z37-Y37 -> -72 | AB37: =IF(Y37=0,"",Z37/Y37) -> 0 | AC37: =+N37+S37+X37 -> 104 | AD37: =+O37+T37+Y37 -> 104 | AE37: =+P37+U37+Z37 -> 45.75 | AF37: =AE37-AD37 -> -58.25 | AG37: =IF(AD37=0,"",AE37/AD37) -> 0.43990385
B38: 委託費(労務費)計 | D38: =SUM(D32:D35,D37) -> 103.679 | E38: =SUM(E32:E35,E37) -> 103.679 | F38: =SUM(F32:F35,F37) -> 0 | G38: =SUM(G32:G35,G37) -> -103.679 | H38: =IF(E38=0,"",F38/E38) -> 0 | I38: =SUM(I32:I35,I37) -> 106.431 | J38: =SUM(J32:J35,J37) -> 106.431 | K38: =SUM(K32:K35,K37) -> 0 | L38: =SUM(L32:L35,L37) -> -106.431 | M38: =IF(J38=0,"",K38/J38) -> 0 | N38: =SUM(N32:N35,N37) -> 210.11 | O38: =SUM(O32:O35,O37) -> 210.11 | P38: =SUM(P32:P35,P37) -> 0 | Q38: =SUM(Q32:Q35,Q37) -> -210.11 | R38: =IF(O38=0,"",P38/O38) -> 0 | S38: =SUM(S32:S35,S37) -> 242.1 | T38: =SUM(T32:T35,T37) -> 242.1 | U38: =SUM(U32:U35,U37) -> 332.009 | V38: =SUM(V32:V35,V37) -> 25.75 | W38: =IF(T38=0,"",U38/T38) -> 1.3713713 | X38: =SUM(X32:X35,X37) -> 626.63469 | Y38: =SUM(Y32:Y35,Y37) -> 626.63469 | Z38: =SUM(Z32:Z35,Z37) -> 588 | AA38: =SUM(AA32:AA35,AA37) -> -72 | AB38: =IF(Y38=0,"",Z38/Y38) -> 0.93834576 | AC38: =+N38+S38+X38 -> 1078.8447 | AD38: =+O38+T38+Y38 -> 1078.8447 | AE38: =+P38+U38+Z38 -> 920.009 | AF38: =AE38-AD38 -> -158.83569 | AG38: =IF(AD38=0,"",AE38/AD38) -> 0.85277243
B40: 海外旅費 | D40: 0 | E40: =D40 -> 0 | F40: 0 | G40: =+F40-E40 -> 0 | H40: =IF(E40=0,"",F40/E40) | I40: 0 | J40: =I40 -> 0 | K40: 0 | L40: =+K40-J40 -> 0 | M40: =IF(J40=0,"",K40/J40) | N40: =+I40+D40 -> 0 | O40: =+J40+E40 -> 0 | P40: =+K40+F40 -> 0 | Q40: =+L40+G40 -> 0 | R40: =IF(O40=0,"",P40/O40) | S40: 0 | T40: =S40 -> 0 | U40: 0 | V40: =+U40-T40 -> 0 | W40: =IF(T40=0,"",U40/T40) | X40: 6 | Y40: =X40 -> 6 | Z40: 80 | AA40: =+Z40-Y40 -> 74 | AB40: =IF(Y40=0,"",Z40/Y40) -> 13.333333 | AC40: =+N40+S40+X40 -> 6 | AD40: =+O40+T40+Y40 -> 6 | AE40: =+P40+U40+Z40 -> 80 | AF40: =AE40-AD40 -> 74 | AG40: =IF(AD40=0,"",AE40/AD40) -> 13.333333
B41: 国内旅費 | D41: 3 | E41: =D41 -> 3 | F41: 0 | G41: =+F41-E41 -> -3 | H41: =IF(E41=0,"",F41/E41) -> 0 | I41: 3 | J41: =I41 -> 3 | K41: 0 | L41: =+K41-J41 -> -3 | M41: =IF(J41=0,"",K41/J41) -> 0 | N41: =+I41+D41 -> 6 | O41: =+J41+E41 -> 6 | P41: =+K41+F41 -> 0 | Q41: =+L41+G41 -> -6 | R41: =IF(O41=0,"",P41/O41) -> 0 | S41: 9 | T41: =S41 -> 9 | U41: 0 | V41: =+U41-T41 -> -9 | W41: =IF(T41=0,"",U41/T41) -> 0 | X41: 16.588 | Y41: =X41 -> 16.588 | Z41: 18 | AA41: =+Z41-Y41 -> 1.412 | AB41: =IF(Y41=0,"",Z41/Y41) -> 1.0851218 | AC41: =+N41+S41+X41 -> 31.588 | AD41: =+O41+T41+Y41 -> 31.588 | AE41: =+P41+U41+Z41 -> 18 | AF41: =AE41-AD41 -> -13.588 | AG41: =IF(AD41=0,"",AE41/AD41) -> 0.56983665
